Workbook

Sheet Historical Financials
B1: MARUTI SUZUKI LTD
B2: (IN CRORES)
B3: ="Historical Financial Statement"&" - "&B1 -> Historical Financial Statement - MARUTI SUZUKI LTD
B4: Year | C4: 2016 | D4: =C4+1 -> 2017 | E4: =D4+1 -> 2018 | F4: =E4+1 -> 2019 | G4: =F4+1 -> 2020 | H4: =G4+1 -> 2021 | I4: =H4+1 -> 2022 | J4: =I4+1 -> 2023 | K4: =J4+1 -> 2024 | L4: =K4+1 -> 2025
B6: ="Income Statement"&" - "&B1 -> Income Statement - MARUTI SUZUKI LTD
B7: Revenue | C7: ='Data Sheet'!B17 -> 57589 | D7: ='Data Sheet'!C17 -> 68085 | E7: ='Data Sheet'!D17 -> 79809.4 | F7: ='Data Sheet'!E17 -> 86068.5 | G7: ='Data Sheet'!F17 -> 75660 | H7: ='Data Sheet'!G17 -> 70372 | I7: ='Data Sheet'!H17 -> 88329.8 | J7: ='Data Sheet'!I17 -> 118409.9 | ... L7: ='Data Sheet'!K17 -> 152913
B8: COGS | C8: =SUM('Data Sheet'!B18,'Data Sheet'!B20,'Data Sheet'!B21,'Data Sheet'!B22)*1-'Data Sheet'!B19 -> 41828.2 | D8: =SUM('Data Sheet'!C18,'Data Sheet'!C20,'Data Sheet'!C21,'Data Sheet'!C22)*1-'Data Sheet'!C19 -> 50004 | E8: =SUM('Data Sheet'!D18,'Data Sheet'!D20,'Data Sheet'!D21,'Data Sheet'!D22)*1-'Data Sheet'!D19 -> 58985 | F8: =SUM('Data Sheet'!E18,'Data Sheet'!E20,'Data Sheet'!E21,'Data Sheet'!E22)*1-'Data Sheet'!E19 -> 64182.2 | G8: =SUM('Data Sheet'!F18,'Data Sheet'!F20,'Data Sheet'!F21,'Data Sheet'!F22)*1-'Data Sheet'!F19 -> 57657.1 | H8: =SUM('Data Sheet'!G18,'Data Sheet'!G20,'Data Sheet'!G21,'Data Sheet'!G22)*1-'Data Sheet'!G19 -> 55415.6 | I8: =SUM('Data Sheet'!H18,'Data Sheet'!H20,'Data Sheet'!H21,'Data Sheet'!H22)*1-'Data Sheet'!H19 -> 71578.8 | J8: =SUM('Data Sheet'!I18,'Data Sheet'!I20,'Data Sheet'!I21,'Data Sheet'!I22)*1-'Data Sheet'!I19 -> 92730.6 | ... L8: =SUM('Data Sheet'!K18,'Data Sheet'!K20,'Data Sheet'!K21,'Data Sheet'!K22)*1-'Data Sheet'!K19 -> 114516.8
B9: Gross Profit | C9: =C7-C8 -> 15760.8 | D9: =D7-D8 -> 18081 | E9: =E7-E8 -> 20824.4 | F9: =F7-F8 -> 21886.3 | G9: =G7-G8 -> 18002.9 | H9: =H7-H8 -> 14956.4 | I9: =I7-I8 -> 16751 | J9: =J7-J8 -> 25679.3 | ... L9: =L7-L8 -> 38396.2
B10: Selling & General Expenses | C10: =SUM('Data Sheet'!B23:B24) -> 6736.7 | D10: =SUM('Data Sheet'!C23:C24) -> 7659.7 | E10: =SUM('Data Sheet'!D23:D24) -> 8706.5 | F10: =SUM('Data Sheet'!E23:E24) -> 10830 | G10: =SUM('Data Sheet'!F23:F24) -> 10647.9 | H10: =SUM('Data Sheet'!G23:G24) -> 9545.8 | I10: =SUM('Data Sheet'!H23:H24) -> 10999 | J10: =SUM('Data Sheet'!I23:I24) -> 12557.8 | ... L10: =SUM('Data Sheet'!K23:K24) -> 18239.9
B11: EBITDA | C11: =C9-C10 -> 9024.1 | D11: =D9-D10 -> 10421.3 | E11: =E9-E10 -> 12117.9 | F11: =F9-F10 -> 11056.3 | G11: =G9-G10 -> 7355 | H11: =H9-H10 -> 5410.6 | I11: =I9-I10 -> 5752 | J11: =J9-J10 -> 13121.5 | ... L11: =L9-L10 -> 20156.3
B12: Depreciation | C12: ='Data Sheet'!B26 -> 2821.8 | D12: ='Data Sheet'!C26 -> 2603.9 | E12: ='Data Sheet'!D26 -> 2759.8 | F12: ='Data Sheet'!E26 -> 3020.8 | G12: ='Data Sheet'!F26 -> 3528.4 | H12: ='Data Sheet'!G26 -> 3034.1 | I12: ='Data Sheet'!H26 -> 2789 | J12: ='Data Sheet'!I26 -> 4846 | ... L12: ='Data Sheet'!K26 -> 5608.2
B13: EBIT | C13: =C11-C12 -> 6202.3 | D13: =D11-D12 -> 7817.4 | E13: =E11-E12 -> 9358.1 | F13: =F11-F12 -> 8035.5 | G13: =G11-G12 -> 3826.6 | H13: =H11-H12 -> 2376.5 | I13: =I11-I12 -> 2963 | J13: =J11-J12 -> 8275.5 | ... L13: =L11-L12 -> 14548.1
B14: Interest | C14: ='Data Sheet'!B27 -> 81.7 | D14: ='Data Sheet'!C27 -> 89.4 | E14: ='Data Sheet'!D27 -> 345.8 | F14: ='Data Sheet'!E27 -> 75.9 | G14: ='Data Sheet'!F27 -> 134.2 | H14: ='Data Sheet'!G27 -> 101.8 | I14: ='Data Sheet'!H27 -> 126.6 | J14: ='Data Sheet'!I27 -> 252.3 | ... L14: ='Data Sheet'!K27 -> 194.2
B15: Other Income | C15: ='Data Sheet'!B25 -> 1464.1 | D15: ='Data Sheet'!C25 -> 2399.2 | E15: ='Data Sheet'!D25 -> 2154.6 | F15: ='Data Sheet'!E25 -> 2664.2 | G15: ='Data Sheet'!F25 -> 3410.4 | H15: ='Data Sheet'!G25 -> 3046.3 | I15: ='Data Sheet'!H25 -> 1860.8 | J15: ='Data Sheet'!I25 -> 2415 | ... L15: ='Data Sheet'!K25 -> 5266.1
B16: EBT | C16: =C13-SUM(C14:C15) -> 4656.5 | D16: =D13-SUM(D14:D15) -> 5328.8 | E16: =E13-SUM(E14:E15) -> 6857.7 | F16: =F13-SUM(F14:F15) -> 5295.4 | G16: =G13-SUM(G14:G15) -> 282 | H16: =H13-SUM(H14:H15) -> -771.6 | I16: =I13-SUM(I14:I15) -> 975.6 | J16: =J13-SUM(J14:J15) -> 5608.2 | ... L16: =L13-SUM(L14:L15) -> 9087.8
B17: Tax | C17: ='Data Sheet'!B29 -> 2087.5 | D17: ='Data Sheet'!C29 -> 2616.2 | E17: ='Data Sheet'!D29 -> 3286.2 | F17: ='Data Sheet'!E29 -> 2973.2 | G17: ='Data Sheet'!F29 -> 1425.2 | H17: ='Data Sheet'!G29 -> 931.9 | I17: ='Data Sheet'!H29 -> 817.7 | J17: ='Data Sheet'!I29 -> 2174.5 | ... L17: ='Data Sheet'!K29 -> 5119.8
B18: Net Income | C18: =C16-C17 -> 2569 | D18: =D16-D17 -> 2712.6 | E18: =E16-E17 -> 3571.5 | F18: =F16-F17 -> 2322.2 | G18: =G16-G17 -> -1143.2 | H18: =H16-H17 -> -1703.5 | I18: =I16-I17 -> 157.9 | J18: =J16-J17 -> 3433.7 | ... L18: =L16-L17 -> 3968
B20: No. of Equity Shares | C20: ='Data Sheet'!B57/'Data Sheet'!B72 -> 30.2 | D20: ='Data Sheet'!C57/'Data Sheet'!C72 -> 30.2 | E20: ='Data Sheet'!D57/'Data Sheet'!D72 -> 30.2 | F20: ='Data Sheet'!E57/'Data Sheet'!E72 -> 30.2 | G20: ='Data Sheet'!F57/'Data Sheet'!F72 -> 30.2 | H20: ='Data Sheet'!G57/'Data Sheet'!G72 -> 30.2 | I20: ='Data Sheet'!H57/'Data Sheet'!H72 -> 30.2 | J20: ='Data Sheet'!I57/'Data Sheet'!I72 -> 31.44 | ... L20: ='Data Sheet'!K57/'Data Sheet'!K72 -> 31.44
B22: EPS | C22: =C18/C20 -> 85.066225 | D22: =D18/D20 -> 89.821192 | E22: =E18/E20 -> 118.26159 | F22: =F18/F20 -> 76.89404 | G22: =G18/G20 -> -37.854305 | H22: =H18/H20 -> -56.407285 | I22: =I18/I20 -> 5.2284768 | J22: =J18/J20 -> 109.21438 | ... L22: =L18/L20 -> 126.20865
B24: DPS | C24: ='Data Sheet'!B31/'Historical Financials'!C20 -> 35 | D24: ='Data Sheet'!C31/'Historical Financials'!D20 -> 75 | E24: ='Data Sheet'!D31/'Historical Financials'!E20 -> 80 | F24: ='Data Sheet'!E31/'Historical Financials'!F20 -> 80 | G24: ='Data Sheet'!F31/'Historical Financials'!G20 -> 60 | H24: ='Data Sheet'!G31/'Historical Financials'!H20 -> 45 | I24: ='Data Sheet'!H31/'Historical Financials'!I20 -> 60 | J24: ='Data Sheet'!I31/'Historical Financials'!J20 -> 90 | ... L24: ='Data Sheet'!K31/'Historical Financials'!L20 -> 135
B25: Dividend Payout Ratio % | C25: =C24/C22 -> 0.41144414 | D25: =D24/D22 -> 0.83499226 | E25: =E24/E22 -> 0.67646647 | F25: =F24/F22 -> 1.0403927 | G25: =G24/G22 -> -1.5850245 | H25: =H24/H22 -> -0.7977693 | I25: =I24/I22 -> 11.475617 | J25: =J24/J22 -> 0.82406733 | ... L25: =L24/L22 -> 1.0696573
B27: Retained Earnings % | C27: =IFERROR(IF(C22>C24,1-C25,0),0) -> 0.58855586 | D27: =IFERROR(IF(D22>D24,1-D25,0),0) -> 0.16500774 | E27: =IFERROR(IF(E22>E24,1-E25,0),0) -> 0.32353353 | F27: =IFERROR(IF(F22>F24,1-F25,0),0) -> 0 | G27: =IFERROR(IF(G22>G24,1-G25,0),0) -> 0 | H27: =IFERROR(IF(H22>H24,1-H25,0),0) -> 0 | I27: =IFERROR(IF(I22>I24,1-I25,0),0) -> 0 | J27: =IFERROR(IF(J22>J24,1-J25,0),0) -> 0.17593267 | ... L27: =IFERROR(IF(L22>L24,1-L25,0),0) -> 0
B29: ="Balance Sheet"&" - "&B1 -> Balance Sheet - MARUTI SUZUKI LTD
B30: Equity Share Capital | C30: ='Data Sheet'!B57 -> 151 | D30: ='Data Sheet'!C57 -> 151 | E30: ='Data Sheet'!D57 -> 151 | F30: ='Data Sheet'!E57 -> 151 | G30: ='Data Sheet'!F57 -> 151 | H30: ='Data Sheet'!G57 -> 151 | I30: ='Data Sheet'!H57 -> 151 | J30: ='Data Sheet'!I57 -> 157.2 | ... L30: ='Data Sheet'!K57 -> 157.2
B31: Reserves | C31: ='Data Sheet'!B58 -> 30465 | D31: ='Data Sheet'!C58 -> 36924.1 | E31: ='Data Sheet'!D58 -> 42408.4 | F31: ='Data Sheet'!E58 -> 46941.1 | G31: ='Data Sheet'!F58 -> 49262 | H31: ='Data Sheet'!G58 -> 52349.6 | I31: ='Data Sheet'!H58 -> 55182.5 | J31: ='Data Sheet'!I58 -> 74443 | ... L31: ='Data Sheet'!K58 -> 96082.7
B32: Borrowings | C32: ='Data Sheet'!B59 -> 230.9 | D32: ='Data Sheet'!C59 -> 483.6 | E32: ='Data Sheet'!D59 -> 120.8 | F32: ='Data Sheet'!E59 -> 159.6 | G32: ='Data Sheet'!F59 -> 184.1 | H32: ='Data Sheet'!G59 -> 540.9 | I32: ='Data Sheet'!H59 -> 425.5 | J32: ='Data Sheet'!I59 -> 1247.6 | ... L32: ='Data Sheet'!K59 -> 87
B33: Other Liabilities | C33: ='Data Sheet'!B60 -> 11878.6 | D33: ='Data Sheet'!C60 -> 14401.8 | E33: ='Data Sheet'!D60 -> 17568.2 | F33: ='Data Sheet'!E60 -> 16717 | G33: ='Data Sheet'!F60 -> 14030.6 | H33: ='Data Sheet'!G60 -> 18334.6 | I33: ='Data Sheet'!H60 -> 18896.5 | J33: ='Data Sheet'!I60 -> 24258.2 | ... L33: ='Data Sheet'!K60 -> 35644.9
B34: Total Liabilities | C34: =SUM(C30:C33) -> 42725.5 | D34: =SUM(D30:D33) -> 51960.5 | E34: =SUM(E30:E33) -> 60248.4 | F34: =SUM(F30:F33) -> 63968.7 | G34: =SUM(G30:G33) -> 63627.7 | H34: =SUM(H30:H33) -> 71376.1 | I34: =SUM(I30:I33) -> 74655.5 | J34: =SUM(J30:J33) -> 100106 | ... L34: =SUM(L30:L33) -> 131971.8
B36: Fixed Assets Net Block | C36: ='Data Sheet'!B62 -> 12529.6 | D36: ='Data Sheet'!C62 -> 13310.7 | E36: ='Data Sheet'!D62 -> 13388.8 | F36: ='Data Sheet'!E62 -> 15437.3 | G36: ='Data Sheet'!F62 -> 15744.4 | H36: ='Data Sheet'!G62 -> 14988.7 | I36: ='Data Sheet'!H62 -> 13747.2 | J36: ='Data Sheet'!I62 -> 27941.4 | ... L36: ='Data Sheet'!K62 -> 33384.5
B37: Capital Work in Progress | C37: ='Data Sheet'!B63 -> 1006.9 | D37: ='Data Sheet'!C63 -> 1252.3 | E37: ='Data Sheet'!D63 -> 2132.1 | F37: ='Data Sheet'!E63 -> 1606.9 | G37: ='Data Sheet'!F63 -> 1415.2 | H37: ='Data Sheet'!G63 -> 1496.8 | I37: ='Data Sheet'!H63 -> 2936.5 | J37: ='Data Sheet'!I63 -> 4143 | ... L37: ='Data Sheet'!K63 -> 7527.2
B38: Investments | C38: ='Data Sheet'!B64 -> 20675.8 | D38: ='Data Sheet'!C64 -> 29150.6 | E38: ='Data Sheet'!D64 -> 36123.1 | F38: ='Data Sheet'!E64 -> 37503.6 | G38: ='Data Sheet'!F64 -> 37488 | H38: ='Data Sheet'!G64 -> 42944.8 | I38: ='Data Sheet'!H64 -> 42034.7 | J38: ='Data Sheet'!I64 -> 49184.3 | ... L38: ='Data Sheet'!K64 -> 66265.4
B39: Other Assets | C39: ='Data Sheet'!B65 -> 8513.2 | D39: ='Data Sheet'!C65 -> 8246.9 | E39: ='Data Sheet'!D65 -> 8604.4 | F39: ='Data Sheet'!E65 -> 9420.9 | G39: ='Data Sheet'!F65 -> 8980.1 | H39: ='Data Sheet'!G65 -> 11945.8 | I39: ='Data Sheet'!H65 -> 15937.1 | J39: ='Data Sheet'!I65 -> 18837.3 | ... L39: ='Data Sheet'!K65 -> 24794.7
B40: Total Non-current Assets | C40: =SUM(C36:C39) -> 42725.5 | D40: =SUM(D36:D39) -> 51960.5 | E40: =SUM(E36:E39) -> 60248.4 | F40: =SUM(F36:F39) -> 63968.7 | G40: =SUM(G36:G39) -> 63627.7 | H40: =SUM(H36:H39) -> 71376.1 | I40: =SUM(I36:I39) -> 74655.5 | J40: =SUM(J36:J39) -> 100106 | ... L40: =SUM(L36:L39) -> 131971.8
B42: Receivables | C42: ='Data Sheet'!B67 -> 1323.4 | D42: ='Data Sheet'!C67 -> 1202.6 | E42: ='Data Sheet'!D67 -> 1465.4 | F42: ='Data Sheet'!E67 -> 2312.8 | G42: ='Data Sheet'!F67 -> 1977.7 | H42: ='Data Sheet'!G67 -> 1279.9 | I42: ='Data Sheet'!H67 -> 2034.5 | J42: ='Data Sheet'!I67 -> 3284.8 | ... L42: ='Data Sheet'!K67 -> 6539.7
B43: Inventory | C43: ='Data Sheet'!B68 -> 3132.6 | D43: ='Data Sheet'!C68 -> 3263.7 | E43: ='Data Sheet'!D68 -> 3160.2 | F43: ='Data Sheet'!E68 -> 3322.6 | G43: ='Data Sheet'!F68 -> 3213.9 | H43: ='Data Sheet'!G68 -> 3049 | I43: ='Data Sheet'!H68 -> 3532.3 | J43: ='Data Sheet'!I68 -> 5443.5 | ... L43: ='Data Sheet'!K68 -> 6913.2
B44: Cash & Bank | C44: ='Data Sheet'!B69 -> 50.7 | D44: ='Data Sheet'!C69 -> 23.5 | E44: ='Data Sheet'!D69 -> 74 | F44: ='Data Sheet'!E69 -> 187.8 | G44: ='Data Sheet'!F69 -> 29 | H44: ='Data Sheet'!G69 -> 3047.1 | I44: ='Data Sheet'!H69 -> 3042.2 | J44: ='Data Sheet'!I69 -> 2748.5 | ... L44: ='Data Sheet'!K69 -> 552.9
B45: Total Current Assets | C45: =SUM(C42:C44) -> 4506.7 | D45: =SUM(D42:D44) -> 4489.8 | E45: =SUM(E42:E44) -> 4699.6 | F45: =SUM(F42:F44) -> 5823.2 | G45: =SUM(G42:G44) -> 5220.6 | H45: =SUM(H42:H44) -> 7376 | I45: =SUM(I42:I44) -> 8609 | J45: =SUM(J42:J44) -> 11476.8 | ... L45: =SUM(L42:L44) -> 14005.8
B47: Total Assets | C47: =SUM(C40,C45) -> 47232.2 | D47: =SUM(D40,D45) -> 56450.3 | E47: =SUM(E40,E45) -> 64948 | F47: =SUM(F40,F45) -> 69791.9 | G47: =SUM(G40,G45) -> 68848.3 | H47: =SUM(H40,H45) -> 78752.1 | I47: =SUM(I40,I45) -> 83264.5 | J47: =SUM(J40,J45) -> 111582.8 | ... L47: =SUM(L40,L45) -> 145977.6
B49: ="Cash Flow Statement"&" - "&B1 -> Cash Flow Statement - MARUTI SUZUKI LTD
B50: Operating Activities
B51: Profit From Operations | C51: ='Cash Flow'!B4 -> 5111 | D51: ='Cash Flow'!C4 -> 6779 | E51: ='Cash Flow'!D4 -> 8935 | F51: ='Cash Flow'!E4 -> 10413 | G51: ='Cash Flow'!F4 -> 12036 | H51: ='Cash Flow'!G4 -> 11060 | I51: ='Cash Flow'!H4 -> 7503 | J51: ='Cash Flow'!I4 -> 5531 | ... L51: ='Cash Flow'!K4 -> 13176
B52: Receivables | C52: ='Cash Flow'!B5 -> 46 | D52: ='Cash Flow'!C5 -> 345 | E52: ='Cash Flow'!D5 -> -204 | F52: ='Cash Flow'!E5 -> 122 | G52: ='Cash Flow'!F5 -> -262 | H52: ='Cash Flow'!G5 -> -851 | I52: ='Cash Flow'!H5 -> 340 | J52: ='Cash Flow'!I5 -> 696 | ... L52: ='Cash Flow'!K5 -> -1270
B53: Inventory | C53: ='Cash Flow'!B6 -> 124 | D53: ='Cash Flow'!C6 -> -982 | E53: ='Cash Flow'!D6 -> -450 | F53: ='Cash Flow'!E6 -> -131 | G53: ='Cash Flow'!F6 -> 104 | H53: ='Cash Flow'!G6 -> -162 | I53: ='Cash Flow'!H6 -> 109 | J53: ='Cash Flow'!I6 -> 165 | ... L53: ='Cash Flow'!K6 -> -1050
B54: Payables | C54: ='Cash Flow'!B7 -> 813 | D54: ='Cash Flow'!C7 -> 712 | E54: ='Cash Flow'!D7 -> 1789 | F54: ='Cash Flow'!E7 -> 979 | G54: ='Cash Flow'!F7 -> 2128 | H54: ='Cash Flow'!G7 -> -858 | I54: ='Cash Flow'!H7 -> -2155 | J54: ='Cash Flow'!I7 -> 2680 | ... L54: ='Cash Flow'!K7 -> 2491
B55: Loan Advances | C55: ='Cash Flow'!B8 -> -563 | D55: ='Cash Flow'!C8 -> 23 | E55: ='Cash Flow'!D8 -> -1 | F55: ='Cash Flow'!E8 -> 1 | G55: ='Cash Flow'!F8 -> 0 | H55: ='Cash Flow'!G8 -> -13 | I55: ='Cash Flow'!H8 -> -1 | J55: ='Cash Flow'!I8 -> -6 | ... L55: ='Cash Flow'!K8 -> 1
B56: Operating Investments | C56: ='Cash Flow'!B9 -> 0 | D56: ='Cash Flow'!C9 -> 0 | E56: ='Cash Flow'!D9 -> 0 | F56: ='Cash Flow'!E9 -> 0 | G56: ='Cash Flow'!F9 -> 0 | H56: ='Cash Flow'!G9 -> 0 | I56: ='Cash Flow'!H9 -> 0 | J56: ='Cash Flow'!I9 -> 0 | ... L56: ='Cash Flow'!K9 -> 0
B57: Other WC Items | C57: ='Cash Flow'!B10 -> 321 | D57: ='Cash Flow'!C10 -> 648 | E57: ='Cash Flow'!D10 -> 325 | F57: ='Cash Flow'!E10 -> 1222 | G57: ='Cash Flow'!F10 -> 839 | H57: ='Cash Flow'!G10 -> 569 | I57: ='Cash Flow'!H10 -> -863 | J57: ='Cash Flow'!I10 -> 801 | ... L57: ='Cash Flow'!K10 -> -269
B58: Working Capital Changes | C58: ='Cash Flow'!B11 -> 742 | D58: ='Cash Flow'!C11 -> 745 | E58: ='Cash Flow'!D11 -> 1460 | F58: ='Cash Flow'!E11 -> 2192 | G58: ='Cash Flow'!F11 -> 2808 | H58: ='Cash Flow'!G11 -> -1315 | I58: ='Cash Flow'!H11 -> -2570 | J58: ='Cash Flow'!I11 -> 4336 | ... L58: ='Cash Flow'!K11 -> -97
B59: Direct Taxes | C59: ='Cash Flow'!B12 -> -858 | D59: ='Cash Flow'!C12 -> -1075 | E59: ='Cash Flow'!D12 -> -1912 | F59: ='Cash Flow'!E12 -> -2323 | G59: ='Cash Flow'!F12 -> -3056 | H59: ='Cash Flow'!G12 -> -3144 | I59: ='Cash Flow'!H12 -> -1438 | J59: ='Cash Flow'!I12 -> -1011 | ... L59: ='Cash Flow'!K12 -> -2265
B60: Cash From Operating Activities | C60: =SUM(C51:C59) -> 5736 | D60: =SUM(D51:D59) -> 7195 | E60: =SUM(E51:E59) -> 9942 | F60: =SUM(F51:F59) -> 12475 | G60: =SUM(G51:G59) -> 14597 | H60: =SUM(H51:H59) -> 5286 | I60: =SUM(I51:I59) -> 925 | J60: =SUM(J51:J59) -> 13192 | ... L60: =SUM(L51:L59) -> 10717
B62: Investing Activities
B63: Fixed assets purchased | C63: ='Cash Flow'!B14 -> -3545 | D63: ='Cash Flow'!C14 -> -3058 | E63: ='Cash Flow'!D14 -> -2469 | F63: ='Cash Flow'!E14 -> -3391 | G63: ='Cash Flow'!F14 -> -3912 | H63: ='Cash Flow'!G14 -> -4872 | I63: ='Cash Flow'!H14 -> -3437 | J63: ='Cash Flow'!I14 -> -2370 | ... L63: ='Cash Flow'!K14 -> -8065
B64: Fixed assets sold | C64: ='Cash Flow'!B15 -> 9 | D64: ='Cash Flow'!C15 -> 16 | E64: ='Cash Flow'!D15 -> 12 | F64: ='Cash Flow'!E15 -> 16 | G64: ='Cash Flow'!F15 -> 26 | H64: ='Cash Flow'!G15 -> 170 | I64: ='Cash Flow'!H15 -> 37 | J64: ='Cash Flow'!I15 -> 42 | ... L64: ='Cash Flow'!K15 -> 109
B65: Investments purchased | C65: ='Cash Flow'!B16 -> -13100 | D65: ='Cash Flow'!C16 -> -17354 | E65: ='Cash Flow'!D16 -> -12044 | F65: ='Cash Flow'!E16 -> -17716 | G65: ='Cash Flow'!F16 -> -47069 | H65: ='Cash Flow'!G16 -> -52957 | I65: ='Cash Flow'!H16 -> -44205 | J65: ='Cash Flow'!I16 -> -44869 | ... L65: ='Cash Flow'!K16 -> -66597
B66: Investments sold | C66: ='Cash Flow'!B17 -> 10450 | D66: ='Cash Flow'!C17 -> 15270 | E66: ='Cash Flow'!D17 -> 7378 | F66: ='Cash Flow'!E17 -> 11839 | G66: ='Cash Flow'!F17 -> 42564 | H66: ='Cash Flow'!G17 -> 53986 | I66: ='Cash Flow'!H17 -> 46969 | J66: ='Cash Flow'!I17 -> 42920 | ... L66: ='Cash Flow'!K17 -> 61605
B67: Interest received | C67: ='Cash Flow'!B18 -> 195 | D67: ='Cash Flow'!C18 -> 152 | E67: ='Cash Flow'!D18 -> 67 | F67: ='Cash Flow'!E18 -> 36 | G67: ='Cash Flow'!F18 -> 68 | H67: ='Cash Flow'!G18 -> 124 | I67: ='Cash Flow'!H18 -> 96 | J67: ='Cash Flow'!I18 -> 67 | ... L67: ='Cash Flow'!K18 -> 313
B68: Dividends received | C68: ='Cash Flow'!B19 -> 54 | D68: ='Cash Flow'!C19 -> 54 | E68: ='Cash Flow'!D19 -> 11 | F68: ='Cash Flow'!E19 -> 13 | G68: ='Cash Flow'!F19 -> 20 | H68: ='Cash Flow'!G19 -> 9 | I68: ='Cash Flow'!H19 -> 4 | J68: ='Cash Flow'!I19 -> 3 | ... L68: ='Cash Flow'!K19 -> 6
B69: Redemp n Canc of Shares | C69: ='Cash Flow'!B20 -> 0 | D69: ='Cash Flow'!C20 -> 0 | E69: ='Cash Flow'!D20 -> 0 | F69: ='Cash Flow'!E20 -> 22 | G69: ='Cash Flow'!F20 -> 0 | H69: ='Cash Flow'!G20 -> 0 | I69: ='Cash Flow'!H20 -> 0 | J69: ='Cash Flow'!I20 -> 0 | ... L69: ='Cash Flow'!K20 -> 0
B70: Acquisition of companies | C70: ='Cash Flow'!B21 -> 0 | D70: ='Cash Flow'!C21 -> 0 | E70: ='Cash Flow'!D21 -> 0 | F70: ='Cash Flow'!E21 -> 0 | G70: ='Cash Flow'!F21 -> 0 | H70: ='Cash Flow'!G21 -> 0 | I70: ='Cash Flow'!H21 -> -15 | J70: ='Cash Flow'!I21 -> -65 | ... L70: ='Cash Flow'!K21 -> 0
B71: Other investing items | C71: ='Cash Flow'!B22 -> 940 | D71: ='Cash Flow'!C22 -> 428 | E71: ='Cash Flow'!D22 -> -186 | F71: ='Cash Flow'!E22 -> 7 | G71: ='Cash Flow'!F22 -> 0 | H71: ='Cash Flow'!G22 -> 0 | I71: ='Cash Flow'!H22 -> -5 | J71: ='Cash Flow'!I22 -> -3019 | ... L71: ='Cash Flow'!K22 -> 3808
B72: Cash From Investing Activities | C72: =SUM(C63:C71) -> -4997 | D72: =SUM(D63:D71) -> -4492 | E72: =SUM(E63:E71) -> -7231 | F72: =SUM(F63:F71) -> -9174 | G72: =SUM(G63:G71) -> -8303 | H72: =SUM(H63:H71) -> -3540 | I72: =SUM(I63:I71) -> -556 | J72: =SUM(J63:J71) -> -7291 | ... L72: =SUM(L63:L71) -> -8821
B74: Financing Activities
B75: Proceeds from borrowings | C75: ='Cash Flow'!B24 -> 1264 | D75: ='Cash Flow'!C24 -> 92 | E75: ='Cash Flow'!D24 -> 77 | F75: ='Cash Flow'!E24 -> 484 | G75: ='Cash Flow'!F24 -> 10 | H75: ='Cash Flow'!G24 -> 39 | I75: ='Cash Flow'!H24 -> 0 | J75: ='Cash Flow'!I24 -> 380 | ... L75: ='Cash Flow'!K24 -> 831
B76: Repayment of borrowings | C76: ='Cash Flow'!B25 -> -885 | D76: ='Cash Flow'!C25 -> -1449 | E76: ='Cash Flow'!D25 -> -313 | F76: ='Cash Flow'!E25 -> -231 | G76: ='Cash Flow'!F25 -> -373 | H76: ='Cash Flow'!G25 -> 0 | I76: ='Cash Flow'!H25 -> -46 | J76: ='Cash Flow'!I25 -> 0 | ... L76: ='Cash Flow'!K25 -> 0
B77: Interest paid fin | C77: ='Cash Flow'!B26 -> -170 | D77: ='Cash Flow'!C26 -> -222 | E77: ='Cash Flow'!D26 -> -92 | F77: ='Cash Flow'!E26 -> -110 | G77: ='Cash Flow'!F26 -> -346 | H77: ='Cash Flow'!G26 -> -73 | I77: ='Cash Flow'!H26 -> -136 | J77: ='Cash Flow'!I26 -> -102 | ... L77: ='Cash Flow'!K26 -> -186
B78: Dividends paid | C78: ='Cash Flow'!B27 -> -242 | D78: ='Cash Flow'!C27 -> -362 | E78: ='Cash Flow'!D27 -> -755 | F78: ='Cash Flow'!E27 -> -1057 | G78: ='Cash Flow'!F27 -> -2266 | H78: ='Cash Flow'!G27 -> -2417 | I78: ='Cash Flow'!H27 -> -2417 | J78: ='Cash Flow'!I27 -> -1812 | ... L78: ='Cash Flow'!K27 -> -1812
B79: Financial liabilities | C79: ='Cash Flow'!B28 -> 0 | D79: ='Cash Flow'!C28 -> 0 | E79: ='Cash Flow'!D28 -> 0 | F79: ='Cash Flow'!E28 -> 0 | G79: ='Cash Flow'!F28 -> 0 | H79: ='Cash Flow'!G28 -> 0 | I79: ='Cash Flow'!H28 -> -10 | J79: ='Cash Flow'!I28 -> -11 | ... L79: ='Cash Flow'!K28 -> -47
B80: Other financing items | C80: ='Cash Flow'!B29 -> -41 | D80: ='Cash Flow'!C29 -> -62 | E80: ='Cash Flow'!D29 -> -154 | F80: ='Cash Flow'!E29 -> -215 | G80: ='Cash Flow'!F29 -> -461 | H80: ='Cash Flow'!G29 -> -497 | I80: ='Cash Flow'!H29 -> -497 | J80: ='Cash Flow'!I29 -> 0 | ... L80: ='Cash Flow'!K29 -> 0
B81: Cash From Financing Activities | C81: =SUM(C75:C80) -> -74 | D81: =SUM(D75:D80) -> -2003 | E81: =SUM(E75:E80) -> -1237 | F81: =SUM(F75:F80) -> -1129 | G81: =SUM(G75:G80) -> -3436 | H81: =SUM(H75:H80) -> -2948 | I81: =SUM(I75:I80) -> -3106 | J81: =SUM(J75:J80) -> -1545 | ... L81: =SUM(L75:L80) -> -1214
B83: Net Cash Flow | C83: =SUM(C81,C72,C60) -> 665 | D83: =SUM(D81,D72,D60) -> 700 | E83: =SUM(E81,E72,E60) -> 1474 | F83: =SUM(F81,F72,F60) -> 2172 | G83: =SUM(G81,G72,G60) -> 2858 | H83: =SUM(H81,H72,H60) -> -1202 | I83: =SUM(I81,I72,I60) -> -2737 | J83: =SUM(J81,J72,J60) -> 4356 | ... L83: =SUM(L81,L72,L60) -> 682

Sheet Comparative Analysis
C2: ="Comparative Analysis"&" - "&'Historical Financials'!B1 -> Comparative Analysis - MARUTI SUZUKI LTD
B3: Year | C3: 2016 | D3: =C3+1 -> 2017 | E3: =D3+1 -> 2018 | F3: =E3+1 -> 2019 | G3: =F3+1 -> 2020 | H3: =G3+1 -> 2021 | I3: =H3+1 -> 2022 | J3: =I3+1 -> 2023 | K3: =J3+1 -> 2024 | L3: =K3+1 -> 2025
B5: Income Statement
B6: Sales | C6: =IFERROR(('Historical Financials'!C7-'Historical Financials'!B7)/'Historical Financials'!B7,"-") -> - | D6: =('Historical Financials'!D7-'Historical Financials'!C7)/'Historical Financials'!C7 -> 0.18225703 | E6: =('Historical Financials'!E7-'Historical Financials'!D7)/'Historical Financials'!D7 -> 0.17220239 | F6: =('Historical Financials'!F7-'Historical Financials'!E7)/'Historical Financials'!E7 -> 0.078425599 | G6: =('Historical Financials'!G7-'Historical Financials'!F7)/'Historical Financials'!F7 -> -0.12093275 | H6: =('Historical Financials'!H7-'Historical Financials'!G7)/'Historical Financials'!G7 -> -0.06989162 | I6: =('Historical Financials'!I7-'Historical Financials'!H7)/'Historical Financials'!H7 -> 0.25518388 | J6: =('Historical Financials'!J7-'Historical Financials'!I7)/'Historical Financials'!I7 -> 0.34054306 | K6: =('Historical Financials'!K7-'Historical Financials'!J7)/'Historical Financials'!J7 -> 0.19802652 | L6: =('Historical Financials'!L7-'Historical Financials'!K7)/'Historical Financials'!K7 -> 0.077928523
B7: COGS | C7: =IFERROR(('Historical Financials'!C8-'Historical Financials'!B8)/'Historical Financials'!B8,"-") -> - | D7: =('Historical Financials'!D8-'Historical Financials'!C8)/'Historical Financials'!C8 -> 0.19546144 | E7: =('Historical Financials'!E8-'Historical Financials'!D8)/'Historical Financials'!D8 -> 0.17960563 | F7: =('Historical Financials'!F8-'Historical Financials'!E8)/'Historical Financials'!E8 -> 0.088110537 | G7: =('Historical Financials'!G8-'Historical Financials'!F8)/'Historical Financials'!F8 -> -0.10166526 | H7: =('Historical Financials'!H8-'Historical Financials'!G8)/'Historical Financials'!G8 -> -0.038876392 | I7: =('Historical Financials'!I8-'Historical Financials'!H8)/'Historical Financials'!H8 -> 0.29167238 | J7: =('Historical Financials'!J8-'Historical Financials'!I8)/'Historical Financials'!I8 -> 0.2955037 | K7: =('Historical Financials'!K8-'Historical Financials'!J8)/'Historical Financials'!J8 -> 0.16482801 | L7: =('Historical Financials'!L8-'Historical Financials'!K8)/'Historical Financials'!K8 -> 0.060191529
B8: Gross Profit | C8: =IFERROR(('Historical Financials'!C9-'Historical Financials'!B9)/'Historical Financials'!B9,"-") -> - | D8: =('Historical Financials'!D9-'Historical Financials'!C9)/'Historical Financials'!C9 -> 0.14721334 | E8: =('Historical Financials'!E9-'Historical Financials'!D9)/'Historical Financials'!D9 -> 0.15172833 | F8: =('Historical Financials'!F9-'Historical Financials'!E9)/'Historical Financials'!E9 -> 0.050993066 | G8: =('Historical Financials'!G9-'Historical Financials'!F9)/'Historical Financials'!F9 -> -0.1774352 | H8: =('Historical Financials'!H9-'Historical Financials'!G9)/'Historical Financials'!G9 -> -0.16922274 | I8: =('Historical Financials'!I9-'Historical Financials'!H9)/'Historical Financials'!H9 -> 0.11998877 | J8: =('Historical Financials'!J9-'Historical Financials'!I9)/'Historical Financials'!I9 -> 0.53300101 | K8: =('Historical Financials'!K9-'Historical Financials'!J9)/'Historical Financials'!J9 -> 0.31790976 | L8: =('Historical Financials'!L9-'Historical Financials'!K9)/'Historical Financials'!K9 -> 0.1345389
B9: Selling & General Expenses | C9: =IFERROR(('Historical Financials'!C10-'Historical Financials'!B10)/'Historical Financials'!B10,"-") -> - | D9: =('Historical Financials'!D10-'Historical Financials'!C10)/'Historical Financials'!C9 -> 0.058563017 | E9: =('Historical Financials'!E10-'Historical Financials'!D10)/'Historical Financials'!D9 -> 0.057895028 | F9: =('Historical Financials'!F10-'Historical Financials'!E10)/'Historical Financials'!E9 -> 0.10197173 | G9: =('Historical Financials'!G10-'Historical Financials'!F10)/'Historical Financials'!F9 -> -0.0083202734 | H9: =('Historical Financials'!H10-'Historical Financials'!G10)/'Historical Financials'!G9 -> -0.061217915 | I9: =('Historical Financials'!I10-'Historical Financials'!H10)/'Historical Financials'!H9 -> 0.097162419 | J9: =('Historical Financials'!J10-'Historical Financials'!I10)/'Historical Financials'!I9 -> 0.093057131 | K9: =('Historical Financials'!K10-'Historical Financials'!J10)/'Historical Financials'!J9 -> 0.10354254 | L9: =('Historical Financials'!L10-'Historical Financials'!K10)/'Historical Financials'!K9 -> 0.089330142
B10: EBITDA | C10: =IFERROR(('Historical Financials'!C11-'Historical Financials'!B11)/'Historical Financials'!B11,"-") -> - | D10: =('Historical Financials'!D11-'Historical Financials'!C11)/'Historical Financials'!C11 -> 0.15482984 | E10: =('Historical Financials'!E11-'Historical Financials'!D11)/'Historical Financials'!D11 -> 0.16280119 | F10: =('Historical Financials'!F11-'Historical Financials'!E11)/'Historical Financials'!E11 -> -0.087605938 | G10: =('Historical Financials'!G11-'Historical Financials'!F11)/'Historical Financials'!F11 -> -0.33476841 | H10: =('Historical Financials'!H11-'Historical Financials'!G11)/'Historical Financials'!G11 -> -0.26436438 | I10: =('Historical Financials'!I11-'Historical Financials'!H11)/'Historical Financials'!H11 -> 0.063098362 | J10: =('Historical Financials'!J11-'Historical Financials'!I11)/'Historical Financials'!I11 -> 1.2812065 | K10: =('Historical Financials'!K11-'Historical Financials'!J11)/'Historical Financials'!J11 -> 0.41952521 | L10: =('Historical Financials'!L11-'Historical Financials'!K11)/'Historical Financials'!K11 -> 0.082141918
B11: Depreciation | C11: =IFERROR(('Historical Financials'!C12-'Historical Financials'!B12)/'Historical Financials'!B12,"-") -> - | D11: =('Historical Financials'!D12-'Historical Financials'!C12)/'Historical Financials'!C12 -> -0.077220214 | E11: =('Historical Financials'!E12-'Historical Financials'!D12)/'Historical Financials'!D12 -> 0.059871731 | F11: =('Historical Financials'!F12-'Historical Financials'!E12)/'Historical Financials'!E12 -> 0.09457207 | G11: =('Historical Financials'!G12-'Historical Financials'!F12)/'Historical Financials'!F12 -> 0.16803496 | H11: =('Historical Financials'!H12-'Historical Financials'!G12)/'Historical Financials'!G12 -> -0.14009183 | I11: =('Historical Financials'!I12-'Historical Financials'!H12)/'Historical Financials'!H12 -> -0.08078178 | J11: =('Historical Financials'!J12-'Historical Financials'!I12)/'Historical Financials'!I12 -> 0.73754034 | K11: =('Historical Financials'!K12-'Historical Financials'!J12)/'Historical Financials'!J12 -> 0.084564589 | L11: =('Historical Financials'!L12-'Historical Financials'!K12)/'Historical Financials'!K12 -> 0.067049736
B12: EBIT | C12: =IFERROR(('Historical Financials'!C13-'Historical Financials'!B13)/'Historical Financials'!B13,"-") -> - | D12: =('Historical Financials'!D13-'Historical Financials'!C13)/'Historical Financials'!C13 -> 0.2604034 | E12: =('Historical Financials'!E13-'Historical Financials'!D13)/'Historical Financials'!D13 -> 0.19708599 | F12: =('Historical Financials'!F13-'Historical Financials'!E13)/'Historical Financials'!E13 -> -0.14133211 | G12: =('Historical Financials'!G13-'Historical Financials'!F13)/'Historical Financials'!F13 -> -0.52378819 | H12: =('Historical Financials'!H13-'Historical Financials'!G13)/'Historical Financials'!G13 -> -0.37895259 | I12: =('Historical Financials'!I13-'Historical Financials'!H13)/'Historical Financials'!H13 -> 0.2467915 | J12: =('Historical Financials'!J13-'Historical Financials'!I13)/'Historical Financials'!I13 -> 1.7929463 | K12: =('Historical Financials'!K13-'Historical Financials'!J13)/'Historical Financials'!J13 -> 0.61567277 | L12: =('Historical Financials'!L13-'Historical Financials'!K13)/'Historical Financials'!K13 -> 0.088074492
B13: Interest | C13: =IFERROR(('Historical Financials'!C14-'Historical Financials'!B14)/'Historical Financials'!B14,"-") -> - | D13: =('Historical Financials'!D14-'Historical Financials'!C14)/'Historical Financials'!C14 -> 0.094247246 | E13: =('Historical Financials'!E14-'Historical Financials'!D14)/'Historical Financials'!D14 -> 2.8680089 | F13: =('Historical Financials'!F14-'Historical Financials'!E14)/'Historical Financials'!E14 -> -0.78050896 | G13: =('Historical Financials'!G14-'Historical Financials'!F14)/'Historical Financials'!F14 -> 0.76811594 | H13: =('Historical Financials'!H14-'Historical Financials'!G14)/'Historical Financials'!G14 -> -0.2414307 | I13: =('Historical Financials'!I14-'Historical Financials'!H14)/'Historical Financials'!H14 -> 0.24361493 | J13: =('Historical Financials'!J14-'Historical Financials'!I14)/'Historical Financials'!I14 -> 0.992891 | K13: =('Historical Financials'!K14-'Historical Financials'!J14)/'Historical Financials'!J14 -> -0.23265953 | L13: =('Historical Financials'!L14-'Historical Financials'!K14)/'Historical Financials'!K14 -> 0.0030991736
B14: Other Income | C14: =IFERROR(('Historical Financials'!C15-'Historical Financials'!B15)/'Historical Financials'!B15,"-") -> - | D14: =('Historical Financials'!D15-'Historical Financials'!C15)/'Historical Financials'!C15 -> 0.63868588 | E14: =('Historical Financials'!E15-'Historical Financials'!D15)/'Historical Financials'!D15 -> -0.10195065 | F14: =('Historical Financials'!F15-'Historical Financials'!E15)/'Historical Financials'!E15 -> 0.23651722 | G14: =('Historical Financials'!G15-'Historical Financials'!F15)/'Historical Financials'!F15 -> 0.28008408 | H14: =('Historical Financials'!H15-'Historical Financials'!G15)/'Historical Financials'!G15 -> -0.10676167 | I14: =('Historical Financials'!I15-'Historical Financials'!H15)/'Historical Financials'!H15 -> -0.38916062 | J14: =('Historical Financials'!J15-'Historical Financials'!I15)/'Historical Financials'!I15 -> 0.29782889 | K14: =('Historical Financials'!K15-'Historical Financials'!J15)/'Historical Financials'!J15 -> 0.75884058 | L14: =('Historical Financials'!L15-'Historical Financials'!K15)/'Historical Financials'!K15 -> 0.23978247
B15: EBT | C15: =IFERROR(('Historical Financials'!C16-'Historical Financials'!B16)/'Historical Financials'!B16,"-") -> - | D15: =('Historical Financials'!D16-'Historical Financials'!C16)/'Historical Financials'!C16 -> 0.14437883 | E15: =('Historical Financials'!E16-'Historical Financials'!D16)/'Historical Financials'!D16 -> 0.28691263 | F15: =('Historical Financials'!F16-'Historical Financials'!E16)/'Historical Financials'!E16 -> -0.22781691 | G15: =('Historical Financials'!G16-'Historical Financials'!F16)/'Historical Financials'!F16 -> -0.94674623 | H15: =('Historical Financials'!H16-'Historical Financials'!G16)/'Historical Financials'!G16 -> -3.7361702 | I15: =('Historical Financials'!I16-'Historical Financials'!H16)/'Historical Financials'!H16 -> -2.2643857 | J15: =('Historical Financials'!J16-'Historical Financials'!I16)/'Historical Financials'!I16 -> 4.7484625 | K15: =('Historical Financials'!K16-'Historical Financials'!J16)/'Historical Financials'!J16 -> 0.59218644 | L15: =('Historical Financials'!L16-'Historical Financials'!K16)/'Historical Financials'!K16 -> 0.017750552
B16: Tax | C16: =IFERROR(('Historical Financials'!C17-'Historical Financials'!B17)/'Historical Financials'!B17,"-") -> - | D16: =('Historical Financials'!D17-'Historical Financials'!C17)/'Historical Financials'!C17 -> 0.25326946 | E16: =('Historical Financials'!E17-'Historical Financials'!D17)/'Historical Financials'!D17 -> 0.25609663 | F16: =('Historical Financials'!F17-'Historical Financials'!E17)/'Historical Financials'!E17 -> -0.09524679 | G16: =('Historical Financials'!G17-'Historical Financials'!F17)/'Historical Financials'!F17 -> -0.52065115 | H16: =('Historical Financials'!H17-'Historical Financials'!G17)/'Historical Financials'!G17 -> -0.34612686 | I16: =('Historical Financials'!I17-'Historical Financials'!H17)/'Historical Financials'!H17 -> -0.12254534 | J16: =('Historical Financials'!J17-'Historical Financials'!I17)/'Historical Financials'!I17 -> 1.6592882 | K16: =('Historical Financials'!K17-'Historical Financials'!J17)/'Historical Financials'!J17 -> 0.81020924 | L16: =('Historical Financials'!L17-'Historical Financials'!K17)/'Historical Financials'!K17 -> 0.30066306
B17: Net Income | C17: =IFERROR(('Historical Financials'!C18-'Historical Financials'!B18)/'Historical Financials'!B18,"-") -> - | D17: =('Historical Financials'!D18-'Historical Financials'!C18)/'Historical Financials'!C18 -> 0.055897236 | E17: =('Historical Financials'!E18-'Historical Financials'!D18)/'Historical Financials'!D18 -> 0.31663349 | F17: =('Historical Financials'!F18-'Historical Financials'!E18)/'Historical Financials'!E18 -> -0.349797 | G17: =('Historical Financials'!G18-'Historical Financials'!F18)/'Historical Financials'!F18 -> -1.4922918 | H17: =('Historical Financials'!H18-'Historical Financials'!G18)/'Historical Financials'!G18 -> 0.49011547 | I17: =('Historical Financials'!I18-'Historical Financials'!H18)/'Historical Financials'!H18 -> -1.0926915 | J17: =('Historical Financials'!J18-'Historical Financials'!I18)/'Historical Financials'!I18 -> 20.746042 | K17: =('Historical Financials'!K18-'Historical Financials'!J18)/'Historical Financials'!J18 -> 0.45411655 | L17: =('Historical Financials'!L18-'Historical Financials'!K18)/'Historical Financials'!K18 -> -0.2052874
B19: Balance Sheet
B20: Equity Share Capital | D20: =('Historical Financials'!D30-'Historical Financials'!C30)/'Historical Financials'!C30 -> 0 | E20: =('Historical Financials'!E30-'Historical Financials'!D30)/'Historical Financials'!D30 -> 0 | F20: =('Historical Financials'!F30-'Historical Financials'!E30)/'Historical Financials'!E30 -> 0 | G20: =('Historical Financials'!G30-'Historical Financials'!F30)/'Historical Financials'!F30 -> 0 | H20: =('Historical Financials'!H30-'Historical Financials'!G30)/'Historical Financials'!G30 -> 0 | I20: =('Historical Financials'!I30-'Historical Financials'!H30)/'Historical Financials'!H30 -> 0 | J20: =('Historical Financials'!J30-'Historical Financials'!I30)/'Historical Financials'!I30 -> 0.041059603 | K20: =('Historical Financials'!K30-'Historical Financials'!J30)/'Historical Financials'!J30 -> 0 | L20: =('Historical Financials'!L30-'Historical Financials'!K30)/'Historical Financials'!K30 -> 0
B21: Reserves | D21: =('Historical Financials'!D31-'Historical Financials'!C31)/'Historical Financials'!C31 -> 0.21201707 | E21: =('Historical Financials'!E31-'Historical Financials'!D31)/'Historical Financials'!D31 -> 0.14852901 | F21: =('Historical Financials'!F31-'Historical Financials'!E31)/'Historical Financials'!E31 -> 0.10688213 | G21: =('Historical Financials'!G31-'Historical Financials'!F31)/'Historical Financials'!F31 -> 0.049442812 | H21: =('Historical Financials'!H31-'Historical Financials'!G31)/'Historical Financials'!G31 -> 0.062677114 | I21: =('Historical Financials'!I31-'Historical Financials'!H31)/'Historical Financials'!H31 -> 0.054115027 | J21: =('Historical Financials'!J31-'Historical Financials'!I31)/'Historical Financials'!I31 -> 0.34903275 | K21: =('Historical Financials'!K31-'Historical Financials'!J31)/'Historical Financials'!J31 -> 0.14824497 | L21: =('Historical Financials'!L31-'Historical Financials'!K31)/'Historical Financials'!K31 -> 0.12405298
B22: Borrowings | D22: =('Historical Financials'!D32-'Historical Financials'!C32)/'Historical Financials'!C32 -> 1.0944132 | E22: =('Historical Financials'!E32-'Historical Financials'!D32)/'Historical Financials'!D32 -> -0.75020678 | F22: =('Historical Financials'!F32-'Historical Financials'!E32)/'Historical Financials'!E32 -> 0.32119205 | G22: =('Historical Financials'!G32-'Historical Financials'!F32)/'Historical Financials'!F32 -> 0.15350877 | H22: =('Historical Financials'!H32-'Historical Financials'!G32)/'Historical Financials'!G32 -> 1.9380771 | I22: =('Historical Financials'!I32-'Historical Financials'!H32)/'Historical Financials'!H32 -> -0.21334812 | J22: =('Historical Financials'!J32-'Historical Financials'!I32)/'Historical Financials'!I32 -> 1.9320799 | K22: =('Historical Financials'!K32-'Historical Financials'!J32)/'Historical Financials'!J32 -> -0.90493748 | L22: =('Historical Financials'!L32-'Historical Financials'!K32)/'Historical Financials'!K32 -> -0.26644182
B23: Other Liabilities | D23: =('Historical Financials'!D33-'Historical Financials'!C33)/'Historical Financials'!C33 -> 0.2124156 | E23: =('Historical Financials'!E33-'Historical Financials'!D33)/'Historical Financials'!D33 -> 0.21986141 | F23: =('Historical Financials'!F33-'Historical Financials'!E33)/'Historical Financials'!E33 -> -0.048451179 | G23: =('Historical Financials'!G33-'Historical Financials'!F33)/'Historical Financials'!F33 -> -0.16069869 | H23: =('Historical Financials'!H33-'Historical Financials'!G33)/'Historical Financials'!G33 -> 0.30675809 | I23: =('Historical Financials'!I33-'Historical Financials'!H33)/'Historical Financials'!H33 -> 0.030646973 | J23: =('Historical Financials'!J33-'Historical Financials'!I33)/'Historical Financials'!I33 -> 0.28374038 | K23: =('Historical Financials'!K33-'Historical Financials'!J33)/'Historical Financials'!J33 -> 0.21812418 | L23: =('Historical Financials'!L33-'Historical Financials'!K33)/'Historical Financials'!K33 -> 0.2062776
B24: Total Liabilities | D24: =('Historical Financials'!D34-'Historical Financials'!C34)/'Historical Financials'!C34 -> 0.21614727 | E24: =('Historical Financials'!E34-'Historical Financials'!D34)/'Historical Financials'!D34 -> 0.15950385 | F24: =('Historical Financials'!F34-'Historical Financials'!E34)/'Historical Financials'!E34 -> 0.061749358 | G24: =('Historical Financials'!G34-'Historical Financials'!F34)/'Historical Financials'!F34 -> -0.0053307321 | H24: =('Historical Financials'!H34-'Historical Financials'!G34)/'Historical Financials'!G34 -> 0.12177715 | I24: =('Historical Financials'!I34-'Historical Financials'!H34)/'Historical Financials'!H34 -> 0.045945351 | J24: =('Historical Financials'!J34-'Historical Financials'!I34)/'Historical Financials'!I34 -> 0.34090589 | K24: =('Historical Financials'!K34-'Historical Financials'!J34)/'Historical Financials'!J34 -> 0.15182007 | L24: =('Historical Financials'!L34-'Historical Financials'!K34)/'Historical Financials'!K34 -> 0.14455427
B26: Fixed Assets Net Block | D26: =('Historical Financials'!D36-'Historical Financials'!C36)/'Historical Financials'!C36 -> 0.062340378 | E26: =('Historical Financials'!E36-'Historical Financials'!D36)/'Historical Financials'!D36 -> 0.00586746 | F26: =('Historical Financials'!F36-'Historical Financials'!E36)/'Historical Financials'!E36 -> 0.15300102 | G26: =('Historical Financials'!G36-'Historical Financials'!F36)/'Historical Financials'!F36 -> 0.019893375 | H26: =('Historical Financials'!H36-'Historical Financials'!G36)/'Historical Financials'!G36 -> -0.047998018 | I26: =('Historical Financials'!I36-'Historical Financials'!H36)/'Historical Financials'!H36 -> -0.082829065 | J26: =('Historical Financials'!J36-'Historical Financials'!I36)/'Historical Financials'!I36 -> 1.0325157 | K26: =('Historical Financials'!K36-'Historical Financials'!J36)/'Historical Financials'!J36 -> -0.0027414518 | L26: =('Historical Financials'!L36-'Historical Financials'!K36)/'Historical Financials'!K36 -> 0.19808863
B27: Capital Work in Progress | D27: =('Historical Financials'!D37-'Historical Financials'!C37)/'Historical Financials'!C37 -> 0.24371834 | E27: =('Historical Financials'!E37-'Historical Financials'!D37)/'Historical Financials'!D37 -> 0.70254731 | F27: =('Historical Financials'!F37-'Historical Financials'!E37)/'Historical Financials'!E37 -> -0.24632991 | G27: =('Historical Financials'!G37-'Historical Financials'!F37)/'Historical Financials'!F37 -> -0.11929803 | H27: =('Historical Financials'!H37-'Historical Financials'!G37)/'Historical Financials'!G37 -> 0.057659695 | I27: =('Historical Financials'!I37-'Historical Financials'!H37)/'Historical Financials'!H37 -> 0.96185195 | J27: =('Historical Financials'!J37-'Historical Financials'!I37)/'Historical Financials'!I37 -> 0.41086327 | K27: =('Historical Financials'!K37-'Historical Financials'!J37)/'Historical Financials'!J37 -> 0.86695631 | L27: =('Historical Financials'!L37-'Historical Financials'!K37)/'Historical Financials'!K37 -> -0.026839737
B28: Investments | D28: =('Historical Financials'!D38-'Historical Financials'!C38)/'Historical Financials'!C38 -> 0.40988982 | E28: =('Historical Financials'!E38-'Historical Financials'!D38)/'Historical Financials'!D38 -> 0.2391889 | F28: =('Historical Financials'!F38-'Historical Financials'!E38)/'Historical Financials'!E38 -> 0.038216543 | G28: =('Historical Financials'!G38-'Historical Financials'!F38)/'Historical Financials'!F38 -> -0.00041596007 | H28: =('Historical Financials'!H38-'Historical Financials'!G38)/'Historical Financials'!G38 -> 0.14556125 | I28: =('Historical Financials'!I38-'Historical Financials'!H38)/'Historical Financials'!H38 -> -0.021192321 | J28: =('Historical Financials'!J38-'Historical Financials'!I38)/'Historical Financials'!I38 -> 0.17008805 | K28: =('Historical Financials'!K38-'Historical Financials'!J38)/'Historical Financials'!J38 -> 0.16492458 | L28: =('Historical Financials'!L38-'Historical Financials'!K38)/'Historical Financials'!K38 -> 0.15654496
B29: Other Assets | D29: =('Historical Financials'!D39-'Historical Financials'!C39)/'Historical Financials'!C39 -> -0.031280834 | E29: =('Historical Financials'!E39-'Historical Financials'!D39)/'Historical Financials'!D39 -> 0.043349622 | F29: =('Historical Financials'!F39-'Historical Financials'!E39)/'Historical Financials'!E39 -> 0.09489331 | G29: =('Historical Financials'!G39-'Historical Financials'!F39)/'Historical Financials'!F39 -> -0.046789585 | H29: =('Historical Financials'!H39-'Historical Financials'!G39)/'Historical Financials'!G39 -> 0.33025245 | I29: =('Historical Financials'!I39-'Historical Financials'!H39)/'Historical Financials'!H39 -> 0.33411743 | J29: =('Historical Financials'!J39-'Historical Financials'!I39)/'Historical Financials'!I39 -> 0.1819779 | K29: =('Historical Financials'!K39-'Historical Financials'!J39)/'Historical Financials'!J39 -> 0.18958131 | L29: =('Historical Financials'!L39-'Historical Financials'!K39)/'Historical Financials'!K39 -> 0.10648638
B30: Total Non-current Assets | D30: =('Historical Financials'!D40-'Historical Financials'!C40)/'Historical Financials'!C40 -> 0.21614727 | E30: =('Historical Financials'!E40-'Historical Financials'!D40)/'Historical Financials'!D40 -> 0.15950385 | F30: =('Historical Financials'!F40-'Historical Financials'!E40)/'Historical Financials'!E40 -> 0.061749358 | G30: =('Historical Financials'!G40-'Historical Financials'!F40)/'Historical Financials'!F40 -> -0.0053307321 | H30: =('Historical Financials'!H40-'Historical Financials'!G40)/'Historical Financials'!G40 -> 0.12177715 | I30: =('Historical Financials'!I40-'Historical Financials'!H40)/'Historical Financials'!H40 -> 0.045945351 | J30: =('Historical Financials'!J40-'Historical Financials'!I40)/'Historical Financials'!I40 -> 0.34090589 | K30: =('Historical Financials'!K40-'Historical Financials'!J40)/'Historical Financials'!J40 -> 0.15182007 | L30: =('Historical Financials'!L40-'Historical Financials'!K40)/'Historical Financials'!K40 -> 0.14455427
B32: Receivables | D32: =('Historical Financials'!D42-'Historical Financials'!C42)/'Historical Financials'!C42 -> -0.091280036 | E32: =('Historical Financials'!E42-'Historical Financials'!D42)/'Historical Financials'!D42 -> 0.21852653 | F32: =('Historical Financials'!F42-'Historical Financials'!E42)/'Historical Financials'!E42 -> 0.57827214 | G32: =('Historical Financials'!G42-'Historical Financials'!F42)/'Historical Financials'!F42 -> -0.14488931 | H32: =('Historical Financials'!H42-'Historical Financials'!G42)/'Historical Financials'!G42 -> -0.3528341 | I32: =('Historical Financials'!I42-'Historical Financials'!H42)/'Historical Financials'!H42 -> 0.58957731 | J32: =('Historical Financials'!J42-'Historical Financials'!I42)/'Historical Financials'!I42 -> 0.61454903 | K32: =('Historical Financials'!K42-'Historical Financials'!J42)/'Historical Financials'!J42 -> 0.39941549 | L32: =('Historical Financials'!L42-'Historical Financials'!K42)/'Historical Financials'!K42 -> 0.42266359
B33: Inventory | D33: =('Historical Financials'!D43-'Historical Financials'!C43)/'Historical Financials'!C43 -> 0.04185022 | E33: =('Historical Financials'!E43-'Historical Financials'!D43)/'Historical Financials'!D43 -> -0.031712474 | F33: =('Historical Financials'!F43-'Historical Financials'!E43)/'Historical Financials'!E43 -> 0.051389153 | G33: =('Historical Financials'!G43-'Historical Financials'!F43)/'Historical Financials'!F43 -> -0.032715343 | H33: =('Historical Financials'!H43-'Historical Financials'!G43)/'Historical Financials'!G43 -> -0.051308379 | I33: =('Historical Financials'!I43-'Historical Financials'!H43)/'Historical Financials'!H43 -> 0.15851099 | J33: =('Historical Financials'!J43-'Historical Financials'!I43)/'Historical Financials'!I43 -> 0.5410639 | K33: =('Historical Financials'!K43-'Historical Financials'!J43)/'Historical Financials'!J43 -> -0.023036649 | L33: =('Historical Financials'!L43-'Historical Financials'!K43)/'Historical Financials'!K43 -> 0.29993795
... B37: Total Assets | D37: =('Historical Financials'!D47-'Historical Financials'!C47)/'Historical Financials'!C47 -> 0.19516559 | E37: =('Historical Financials'!E47-'Historical Financials'!D47)/'Historical Financials'!D47 -> 0.15053419 | F37: =('Historical Financials'!F47-'Historical Financials'!E47)/'Historical Financials'!E47 -> 0.074581203 | G37: =('Historical Financials'!G47-'Historical Financials'!F47)/'Historical Financials'!F47 -> -0.013520194 | H37: =('Historical Financials'!H47-'Historical Financials'!G47)/'Historical Financials'!G47 -> 0.14384959 | I37: =('Historical Financials'!I47-'Historical Financials'!H47)/'Historical Financials'!H47 -> 0.057298789 | J37: =('Historical Financials'!J47-'Historical Financials'!I47)/'Historical Financials'!I47 -> 0.34010052 | K37: =('Historical Financials'!K47-'Historical Financials'!J47)/'Historical Financials'!J47 -> 0.14754604 | L37: =('Historical Financials'!L47-'Historical Financials'!K47)/'Historical Financials'!K47 -> 0.14003674
B39: Cash Flow Statement
B40: Operating Activities
B41: Profit From Operations | D41: =('Historical Financials'!D51-'Historical Financials'!C51)/'Historical Financials'!C51 -> 0.32635492 | E41: =('Historical Financials'!E51-'Historical Financials'!D51)/'Historical Financials'!D51 -> 0.31804101 | F41: =('Historical Financials'!F51-'Historical Financials'!E51)/'Historical Financials'!E51 -> 0.1654169 | G41: =('Historical Financials'!G51-'Historical Financials'!F51)/'Historical Financials'!F51 -> 0.15586286 | H41: =('Historical Financials'!H51-'Historical Financials'!G51)/'Historical Financials'!G51 -> -0.081090063 | I41: =('Historical Financials'!I51-'Historical Financials'!H51)/'Historical Financials'!H51 -> -0.3216094 | J41: =('Historical Financials'!J51-'Historical Financials'!I51)/'Historical Financials'!I51 -> -0.2628282 | K41: =('Historical Financials'!K51-'Historical Financials'!J51)/'Historical Financials'!J51 -> 0.054420539 | L41: =('Historical Financials'!L51-'Historical Financials'!K51)/'Historical Financials'!K51 -> 1.2592593
B42: Receivables | D42: =('Historical Financials'!D52-'Historical Financials'!C52)/'Historical Financials'!C52 -> 6.5 | E42: =('Historical Financials'!E52-'Historical Financials'!D52)/'Historical Financials'!D52 -> -1.5913043 | F42: =('Historical Financials'!F52-'Historical Financials'!E52)/'Historical Financials'!E52 -> -1.5980392 | G42: =('Historical Financials'!G52-'Historical Financials'!F52)/'Historical Financials'!F52 -> -3.147541 | H42: =('Historical Financials'!H52-'Historical Financials'!G52)/'Historical Financials'!G52 -> 2.2480916 | I42: =('Historical Financials'!I52-'Historical Financials'!H52)/'Historical Financials'!H52 -> -1.39953 | J42: =('Historical Financials'!J52-'Historical Financials'!I52)/'Historical Financials'!I52 -> 1.0470588 | K42: =('Historical Financials'!K52-'Historical Financials'!J52)/'Historical Financials'!J52 -> -2.0977011 | L42: =('Historical Financials'!L52-'Historical Financials'!K52)/'Historical Financials'!K52 -> 0.66230366
B43: Inventory | D43: =('Historical Financials'!D53-'Historical Financials'!C53)/'Historical Financials'!C53 -> -8.9193548 | E43: =('Historical Financials'!E53-'Historical Financials'!D53)/'Historical Financials'!D53 -> -0.54175153 | F43: =('Historical Financials'!F53-'Historical Financials'!E53)/'Historical Financials'!E53 -> -0.70888889 | G43: =('Historical Financials'!G53-'Historical Financials'!F53)/'Historical Financials'!F53 -> -1.7938931 | H43: =('Historical Financials'!H53-'Historical Financials'!G53)/'Historical Financials'!G53 -> -2.5576923 | I43: =('Historical Financials'!I53-'Historical Financials'!H53)/'Historical Financials'!H53 -> -1.6728395 | J43: =('Historical Financials'!J53-'Historical Financials'!I53)/'Historical Financials'!I53 -> 0.51376147 | K43: =('Historical Financials'!K53-'Historical Financials'!J53)/'Historical Financials'!J53 -> -3.9272727 | L43: =('Historical Financials'!L53-'Historical Financials'!K53)/'Historical Financials'!K53 -> 1.173913
B44: Payables | D44: =('Historical Financials'!D54-'Historical Financials'!C54)/'Historical Financials'!C54 -> -0.12423124 | E44: =('Historical Financials'!E54-'Historical Financials'!D54)/'Historical Financials'!D54 -> 1.5126404 | F44: =('Historical Financials'!F54-'Historical Financials'!E54)/'Historical Financials'!E54 -> -0.45276691 | G44: =('Historical Financials'!G54-'Historical Financials'!F54)/'Historical Financials'!F54 -> 1.1736466 | H44: =('Historical Financials'!H54-'Historical Financials'!G54)/'Historical Financials'!G54 -> -1.4031955 | I44: =('Historical Financials'!I54-'Historical Financials'!H54)/'Historical Financials'!H54 -> 1.511655 | J44: =('Historical Financials'!J54-'Historical Financials'!I54)/'Historical Financials'!I54 -> -2.2436195 | K44: =('Historical Financials'!K54-'Historical Financials'!J54)/'Historical Financials'!J54 -> -1.1477612 | L44: =('Historical Financials'!L54-'Historical Financials'!K54)/'Historical Financials'!K54 -> -7.290404
B45: Loan Advances | D45: =('Historical Financials'!D55-'Historical Financials'!C55)/'Historical Financials'!C55 -> -1.0408526 | E45: =('Historical Financials'!E55-'Historical Financials'!D55)/'Historical Financials'!D55 -> -1.0434783 | F45: =IFERROR(('Historical Financials'!F55-'Historical Financials'!E55)/'Historical Financials'!E55,"-") -> -2 | G45: =('Historical Financials'!G55-'Historical Financials'!F55)/'Historical Financials'!F55 -> -1 | H45: =('Historical Financials'!H55-'Historical Financials'!G55)/'Historical Financials'!G55 -> #DIV/0! | I45: =('Historical Financials'!I55-'Historical Financials'!H55)/'Historical Financials'!H55 -> -0.92307692 | J45: =('Historical Financials'!J55-'Historical Financials'!I55)/'Historical Financials'!I55 -> 5 | K45: =('Historical Financials'!K55-'Historical Financials'!J55)/'Historical Financials'!J55 -> 0.33333333 | L45: =('Historical Financials'!L55-'Historical Financials'!K55)/'Historical Financials'!K55 -> -1.125
B46: Operating Investments | D46: =IFERROR(('Historical Financials'!D56-'Historical Financials'!C56)/'Historical Financials'!C56,"-") -> - | E46: =IFERROR(('Historical Financials'!E56-'Historical Financials'!D56)/'Historical Financials'!D56,"-") -> - | F46: =IFERROR(('Historical Financials'!F56-'Historical Financials'!E56)/'Historical Financials'!E56,"-") -> - | G46: =IFERROR(('Historical Financials'!G56-'Historical Financials'!F56)/'Historical Financials'!F56,"-") -> - | H46: =IFERROR(('Historical Financials'!H56-'Historical Financials'!G56)/'Historical Financials'!G56,"-") -> - | I46: =IFERROR(('Historical Financials'!I56-'Historical Financials'!H56)/'Historical Financials'!H56,"-") -> - | J46: =IFERROR(('Historical Financials'!J56-'Historical Financials'!I56)/'Historical Financials'!I56,"-") -> - | K46: =IFERROR(('Historical Financials'!K56-'Historical Financials'!J56)/'Historical Financials'!J56,"-") -> - | L46: =IFERROR(('Historical Financials'!L56-'Historical Financials'!K56)/'Historical Financials'!K56,"-") -> -
B47: Other WC Items | D47: =('Historical Financials'!D57-'Historical Financials'!C57)/'Historical Financials'!C57 -> 1.0186916 | E47: =('Historical Financials'!E57-'Historical Financials'!D57)/'Historical Financials'!D57 -> -0.49845679 | F47: =('Historical Financials'!F57-'Historical Financials'!E57)/'Historical Financials'!E57 -> 2.76 | G47: =('Historical Financials'!G57-'Historical Financials'!F57)/'Historical Financials'!F57 -> -0.31342062 | H47: =('Historical Financials'!H57-'Historical Financials'!G57)/'Historical Financials'!G57 -> -0.32181168 | I47: =('Historical Financials'!I57-'Historical Financials'!H57)/'Historical Financials'!H57 -> -2.516696 | J47: =('Historical Financials'!J57-'Historical Financials'!I57)/'Historical Financials'!I57 -> -1.9281576 | K47: =('Historical Financials'!K57-'Historical Financials'!J57)/'Historical Financials'!J57 -> -2.4506866 | L47: =('Historical Financials'!L57-'Historical Financials'!K57)/'Historical Financials'!K57 -> -0.76850258
B48: Working Capital Changes | D48: =('Historical Financials'!D58-'Historical Financials'!C58)/'Historical Financials'!C58 -> 0.0040431267 | E48: =('Historical Financials'!E58-'Historical Financials'!D58)/'Historical Financials'!D58 -> 0.95973154 | F48: =('Historical Financials'!F58-'Historical Financials'!E58)/'Historical Financials'!E58 -> 0.50136986 | G48: =('Historical Financials'!G58-'Historical Financials'!F58)/'Historical Financials'!F58 -> 0.2810219 | H48: =('Historical Financials'!H58-'Historical Financials'!G58)/'Historical Financials'!G58 -> -1.4683048 | I48: =('Historical Financials'!I58-'Historical Financials'!H58)/'Historical Financials'!H58 -> 0.95437262 | J48: =('Historical Financials'!J58-'Historical Financials'!I58)/'Historical Financials'!I58 -> -2.6871595 | K48: =('Historical Financials'!K58-'Historical Financials'!J58)/'Historical Financials'!J58 -> -1.6487546 | L48: =('Historical Financials'!L58-'Historical Financials'!K58)/'Historical Financials'!K58 -> -0.96551724
B49: Direct Taxes | D49: =('Historical Financials'!D59-'Historical Financials'!C59)/'Historical Financials'!C59 -> 0.25291375 | E49: =('Historical Financials'!E59-'Historical Financials'!D59)/'Historical Financials'!D59 -> 0.77860465 | F49: =('Historical Financials'!F59-'Historical Financials'!E59)/'Historical Financials'!E59 -> 0.21495816 | G49: =('Historical Financials'!G59-'Historical Financials'!F59)/'Historical Financials'!F59 -> 0.31554025 | H49: =('Historical Financials'!H59-'Historical Financials'!G59)/'Historical Financials'!G59 -> 0.028795812 | I49: =('Historical Financials'!I59-'Historical Financials'!H59)/'Historical Financials'!H59 -> -0.54262087 | J49: =('Historical Financials'!J59-'Historical Financials'!I59)/'Historical Financials'!I59 -> -0.29694019 | K49: =('Historical Financials'!K59-'Historical Financials'!J59)/'Historical Financials'!J59 -> 0.16518299 | L49: =('Historical Financials'!L59-'Historical Financials'!K59)/'Historical Financials'!K59 -> 0.92275042
B50: Cash From Operating Activities | D50: =('Historical Financials'!D60-'Historical Financials'!C60)/'Historical Financials'!C60 -> 0.25435844 | E50: =('Historical Financials'!E60-'Historical Financials'!D60)/'Historical Financials'!D60 -> 0.38179291 | F50: =('Historical Financials'!F60-'Historical Financials'!E60)/'Historical Financials'!E60 -> 0.25477771 | G50: =('Historical Financials'!G60-'Historical Financials'!F60)/'Historical Financials'!F60 -> 0.1701002 | H50: =('Historical Financials'!H60-'Historical Financials'!G60)/'Historical Financials'!G60 -> -0.6378708 | I50: =('Historical Financials'!I60-'Historical Financials'!H60)/'Historical Financials'!H60 -> -0.82500946 | J50: =('Historical Financials'!J60-'Historical Financials'!I60)/'Historical Financials'!I60 -> 13.261622 | K50: =('Historical Financials'!K60-'Historical Financials'!J60)/'Historical Financials'!J60 -> -1.073681 | L50: =('Historical Financials'!L60-'Historical Financials'!K60)/'Historical Financials'!K60 -> -12.02572
B52: Investing Activities
B53: Fixed assets purchased | D53: =IFERROR(('Historical Financials'!D63-'Historical Financials'!C63)/'Historical Financials'!C63,"-") -> -0.13737659 | E53: =IFERROR(('Historical Financials'!E63-'Historical Financials'!D63)/'Historical Financials'!D63,"-") -> -0.19260955 | F53: =IFERROR(('Historical Financials'!F63-'Historical Financials'!E63)/'Historical Financials'!E63,"-") -> 0.37343054 | G53: =IFERROR(('Historical Financials'!G63-'Historical Financials'!F63)/'Historical Financials'!F63,"-") -> 0.15364199 | H53: =IFERROR(('Historical Financials'!H63-'Historical Financials'!G63)/'Historical Financials'!G63,"-") -> 0.24539877 | I53: =IFERROR(('Historical Financials'!I63-'Historical Financials'!H63)/'Historical Financials'!H63,"-") -> -0.29454023 | J53: =IFERROR(('Historical Financials'!J63-'Historical Financials'!I63)/'Historical Financials'!I63,"-") -> -0.31044516 | K53: =IFERROR(('Historical Financials'!K63-'Historical Financials'!J63)/'Historical Financials'!J63,"-") -> 0.45949367 | L53: =IFERROR(('Historical Financials'!L63-'Historical Financials'!K63)/'Historical Financials'!K63,"-") -> 1.3315987
B54: Fixed assets sold | D54: =IFERROR(('Historical Financials'!D64-'Historical Financials'!C64)/'Historical Financials'!C64,"-") -> 0.77777778 | E54: =IFERROR(('Historical Financials'!E64-'Historical Financials'!D64)/'Historical Financials'!D64,"-") -> -0.25 | F54: =IFERROR(('Historical Financials'!F64-'Historical Financials'!E64)/'Historical Financials'!E64,"-") -> 0.33333333 | G54: =IFERROR(('Historical Financials'!G64-'Historical Financials'!F64)/'Historical Financials'!F64,"-") -> 0.625 | H54: =IFERROR(('Historical Financials'!H64-'Historical Financials'!G64)/'Historical Financials'!G64,"-") -> 5.5384615 | I54: =IFERROR(('Historical Financials'!I64-'Historical Financials'!H64)/'Historical Financials'!H64,"-") -> -0.78235294 | J54: =IFERROR(('Historical Financials'!J64-'Historical Financials'!I64)/'Historical Financials'!I64,"-") -> 0.13513514 | K54: =IFERROR(('Historical Financials'!K64-'Historical Financials'!J64)/'Historical Financials'!J64,"-") -> 2.2380952 | L54: =IFERROR(('Historical Financials'!L64-'Historical Financials'!K64)/'Historical Financials'!K64,"-") -> -0.19852941
B55: Investments purchased | D55: =IFERROR(('Historical Financials'!D65-'Historical Financials'!C65)/'Historical Financials'!C65,"-") -> 0.32473282 | E55: =IFERROR(('Historical Financials'!E65-'Historical Financials'!D65)/'Historical Financials'!D65,"-") -> -0.30598133 | F55: =IFERROR(('Historical Financials'!F65-'Historical Financials'!E65)/'Historical Financials'!E65,"-") -> 0.47093989 | G55: =IFERROR(('Historical Financials'!G65-'Historical Financials'!F65)/'Historical Financials'!F65,"-") -> 1.6568639 | H55: =IFERROR(('Historical Financials'!H65-'Historical Financials'!G65)/'Historical Financials'!G65,"-") -> 0.12509295 | I55: =IFERROR(('Historical Financials'!I65-'Historical Financials'!H65)/'Historical Financials'!H65,"-") -> -0.16526616 | J55: =IFERROR(('Historical Financials'!J65-'Historical Financials'!I65)/'Historical Financials'!I65,"-") -> 0.015020925 | K55: =IFERROR(('Historical Financials'!K65-'Historical Financials'!J65)/'Historical Financials'!J65,"-") -> 0.34892688 | L55: =IFERROR(('Historical Financials'!L65-'Historical Financials'!K65)/'Historical Financials'!K65,"-") -> 0.10032218
B56: Investments sold | D56: =IFERROR(('Historical Financials'!D66-'Historical Financials'!C66)/'Historical Financials'!C66,"-") -> 0.46124402 | E56: =IFERROR(('Historical Financials'!E66-'Historical Financials'!D66)/'Historical Financials'!D66,"-") -> -0.51683039 | F56: =IFERROR(('Historical Financials'!F66-'Historical Financials'!E66)/'Historical Financials'!E66,"-") -> 0.6046354 | G56: =IFERROR(('Historical Financials'!G66-'Historical Financials'!F66)/'Historical Financials'!F66,"-") -> 2.5952361 | H56: =IFERROR(('Historical Financials'!H66-'Historical Financials'!G66)/'Historical Financials'!G66,"-") -> 0.26834884 | I56: =IFERROR(('Historical Financials'!I66-'Historical Financials'!H66)/'Historical Financials'!H66,"-") -> -0.12997814 | J56: =IFERROR(('Historical Financials'!J66-'Historical Financials'!I66)/'Historical Financials'!I66,"-") -> -0.086205795 | K56: =IFERROR(('Historical Financials'!K66-'Historical Financials'!J66)/'Historical Financials'!J66,"-") -> 0.48133737 | L56: =IFERROR(('Historical Financials'!L66-'Historical Financials'!K66)/'Historical Financials'!K66,"-") -> -0.031047988
B57: Interest received | D57: =IFERROR(('Historical Financials'!D67-'Historical Financials'!C67)/'Historical Financials'!C67,"-") -> -0.22051282 | E57: =IFERROR(('Historical Financials'!E67-'Historical Financials'!D67)/'Historical Financials'!D67,"-") -> -0.55921053 | F57: =IFERROR(('Historical Financials'!F67-'Historical Financials'!E67)/'Historical Financials'!E67,"-") -> -0.46268657 | G57: =IFERROR(('Historical Financials'!G67-'Historical Financials'!F67)/'Historical Financials'!F67,"-") -> 0.88888889 | H57: =IFERROR(('Historical Financials'!H67-'Historical Financials'!G67)/'Historical Financials'!G67,"-") -> 0.82352941 | I57: =IFERROR(('Historical Financials'!I67-'Historical Financials'!H67)/'Historical Financials'!H67,"-") -> -0.22580645 | J57: =IFERROR(('Historical Financials'!J67-'Historical Financials'!I67)/'Historical Financials'!I67,"-") -> -0.30208333 | K57: =IFERROR(('Historical Financials'!K67-'Historical Financials'!J67)/'Historical Financials'!J67,"-") -> 1.5970149 | L57: =IFERROR(('Historical Financials'!L67-'Historical Financials'!K67)/'Historical Financials'!K67,"-") -> 0.79885057
B58: Dividends received | D58: =IFERROR(('Historical Financials'!D68-'Historical Financials'!C68)/'Historical Financials'!C68,"-") -> 0 | E58: =IFERROR(('Historical Financials'!E68-'Historical Financials'!D68)/'Historical Financials'!D68,"-") -> -0.7962963 | F58: =IFERROR(('Historical Financials'!F68-'Historical Financials'!E68)/'Historical Financials'!E68,"-") -> 0.18181818 | G58: =IFERROR(('Historical Financials'!G68-'Historical Financials'!F68)/'Historical Financials'!F68,"-") -> 0.53846154 | H58: =IFERROR(('Historical Financials'!H68-'Historical Financials'!G68)/'Historical Financials'!G68,"-") -> -0.55 | I58: =IFERROR(('Historical Financials'!I68-'Historical Financials'!H68)/'Historical Financials'!H68,"-") -> -0.55555556 | J58: =IFERROR(('Historical Financials'!J68-'Historical Financials'!I68)/'Historical Financials'!I68,"-") -> -0.25 | K58: =IFERROR(('Historical Financials'!K68-'Historical Financials'!J68)/'Historical Financials'!J68,"-") -> 0 | L58: =IFERROR(('Historical Financials'!L68-'Historical Financials'!K68)/'Historical Financials'!K68,"-") -> 1
B59: Redemp n Canc of Shares | D59: =IFERROR(('Historical Financials'!D69-'Historical Financials'!C69)/'Historical Financials'!C69,"-") -> - | E59: =IFERROR(('Historical Financials'!E69-'Historical Financials'!D69)/'Historical Financials'!D69,"-") -> - | F59: =IFERROR(('Historical Financials'!F69-'Historical Financials'!E69)/'Historical Financials'!E69,"-") -> - | G59: =IFERROR(('Historical Financials'!G69-'Historical Financials'!F69)/'Historical Financials'!F69,"-") -> -1 | H59: =IFERROR(('Historical Financials'!H69-'Historical Financials'!G69)/'Historical Financials'!G69,"-") -> - | I59: =IFERROR(('Historical Financials'!I69-'Historical Financials'!H69)/'Historical Financials'!H69,"-") -> - | J59: =IFERROR(('Historical Financials'!J69-'Historical Financials'!I69)/'Historical Financials'!I69,"-") -> - | K59: =IFERROR(('Historical Financials'!K69-'Historical Financials'!J69)/'Historical Financials'!J69,"-") -> - | L59: =IFERROR(('Historical Financials'!L69-'Historical Financials'!K69)/'Historical Financials'!K69,"-") -> -
B60: Acquisition of companies | D60: =IFERROR(('Historical Financials'!D70-'Historical Financials'!C70)/'Historical Financials'!C70,"-") -> - | E60: =IFERROR(('Historical Financials'!E70-'Historical Financials'!D70)/'Historical Financials'!D70,"-") -> - | F60: =IFERROR(('Historical Financials'!F70-'Historical Financials'!E70)/'Historical Financials'!E70,"-") -> - | G60: =IFERROR(('Historical Financials'!G70-'Historical Financials'!F70)/'Historical Financials'!F70,"-") -> - | H60: =IFERROR(('Historical Financials'!H70-'Historical Financials'!G70)/'Historical Financials'!G70,"-") -> - | I60: =IFERROR(('Historical Financials'!I70-'Historical Financials'!H70)/'Historical Financials'!H70,"-") -> - | J60: =IFERROR(('Historical Financials'!J70-'Historical Financials'!I70)/'Historical Financials'!I70,"-") -> 3.3333333 | K60: =IFERROR(('Historical Financials'!K70-'Historical Financials'!J70)/'Historical Financials'!J70,"-") -> 1.2461538 | L60: =IFERROR(('Historical Financials'!L70-'Historical Financials'!K70)/'Historical Financials'!K70,"-") -> -1
B61: Other investing items | D61: =IFERROR(('Historical Financials'!D71-'Historical Financials'!C71)/'Historical Financials'!C71,"-") -> -0.54468085 | E61: =IFERROR(('Historical Financials'!E71-'Historical Financials'!D71)/'Historical Financials'!D71,"-") -> -1.4345794 | F61: =IFERROR(('Historical Financials'!F71-'Historical Financials'!E71)/'Historical Financials'!E71,"-") -> -1.0376344 | G61: =IFERROR(('Historical Financials'!G71-'Historical Financials'!F71)/'Historical Financials'!F71,"-") -> -1 | H61: =IFERROR(('Historical Financials'!H71-'Historical Financials'!G71)/'Historical Financials'!G71,"-") -> - | I61: =IFERROR(('Historical Financials'!I71-'Historical Financials'!H71)/'Historical Financials'!H71,"-") -> - | J61: =IFERROR(('Historical Financials'!J71-'Historical Financials'!I71)/'Historical Financials'!I71,"-") -> 602.8 | K61: =IFERROR(('Historical Financials'!K71-'Historical Financials'!J71)/'Historical Financials'!J71,"-") -> -0.99966876 | L61: =IFERROR(('Historical Financials'!L71-'Historical Financials'!K71)/'Historical Financials'!K71,"-") -> -3809
B62: Cash From Investing Activities | D62: =IFERROR(('Historical Financials'!D72-'Historical Financials'!C72)/'Historical Financials'!C72,"-") -> -0.10106064 | E62: =IFERROR(('Historical Financials'!E72-'Historical Financials'!D72)/'Historical Financials'!D72,"-") -> 0.60975067 | F62: =IFERROR(('Historical Financials'!F72-'Historical Financials'!E72)/'Historical Financials'!E72,"-") -> 0.26870419 | G62: =IFERROR(('Historical Financials'!G72-'Historical Financials'!F72)/'Historical Financials'!F72,"-") -> -0.094942228 | H62: =IFERROR(('Historical Financials'!H72-'Historical Financials'!G72)/'Historical Financials'!G72,"-") -> -0.57364808 | I62: =IFERROR(('Historical Financials'!I72-'Historical Financials'!H72)/'Historical Financials'!H72,"-") -> -0.84293785 | J62: =IFERROR(('Historical Financials'!J72-'Historical Financials'!I72)/'Historical Financials'!I72,"-") -> 12.113309 | K62: =IFERROR(('Historical Financials'!K72-'Historical Financials'!J72)/'Historical Financials'!J72,"-") -> -0.96721986 | L62: =IFERROR(('Historical Financials'!L72-'Historical Financials'!K72)/'Historical Financials'!K72,"-") -> 35.90795
B64: Financing Activities
B65: Proceeds from borrowings | D65: =IFERROR(('Historical Financials'!D75-'Historical Financials'!C75)/'Historical Financials'!C75,"-") -> -0.92721519 | E65: =IFERROR(('Historical Financials'!E75-'Historical Financials'!D75)/'Historical Financials'!D75,"-") -> -0.16304348 | F65: =IFERROR(('Historical Financials'!F75-'Historical Financials'!E75)/'Historical Financials'!E75,"-") -> 5.2857143 | G65: =IFERROR(('Historical Financials'!G75-'Historical Financials'!F75)/'Historical Financials'!F75,"-") -> -0.97933884 | H65: =IFERROR(('Historical Financials'!H75-'Historical Financials'!G75)/'Historical Financials'!G75,"-") -> 2.9 | I65: =IFERROR(('Historical Financials'!I75-'Historical Financials'!H75)/'Historical Financials'!H75,"-") -> -1 | J65: =IFERROR(('Historical Financials'!J75-'Historical Financials'!I75)/'Historical Financials'!I75,"-") -> - | K65: =IFERROR(('Historical Financials'!K75-'Historical Financials'!J75)/'Historical Financials'!J75,"-") -> -1 | L65: =IFERROR(('Historical Financials'!L75-'Historical Financials'!K75)/'Historical Financials'!K75,"-") -> -
B66: Repayment of borrowings | D66: =IFERROR(('Historical Financials'!D76-'Historical Financials'!C76)/'Historical Financials'!C76,"-") -> 0.63728814 | E66: =IFERROR(('Historical Financials'!E76-'Historical Financials'!D76)/'Historical Financials'!D76,"-") -> -0.78398896 | F66: =IFERROR(('Historical Financials'!F76-'Historical Financials'!E76)/'Historical Financials'!E76,"-") -> -0.26198083 | G66: =IFERROR(('Historical Financials'!G76-'Historical Financials'!F76)/'Historical Financials'!F76,"-") -> 0.61471861 | H66: =IFERROR(('Historical Financials'!H76-'Historical Financials'!G76)/'Historical Financials'!G76,"-") -> -1 | I66: =IFERROR(('Historical Financials'!I76-'Historical Financials'!H76)/'Historical Financials'!H76,"-") -> - | J66: =IFERROR(('Historical Financials'!J76-'Historical Financials'!I76)/'Historical Financials'!I76,"-") -> -1 | K66: =IFERROR(('Historical Financials'!K76-'Historical Financials'!J76)/'Historical Financials'!J76,"-") -> - | L66: =IFERROR(('Historical Financials'!L76-'Historical Financials'!K76)/'Historical Financials'!K76,"-") -> -1
B67: Interest paid fin | D67: =IFERROR(('Historical Financials'!D77-'Historical Financials'!C77)/'Historical Financials'!C77,"-") -> 0.30588235 | E67: =IFERROR(('Historical Financials'!E77-'Historical Financials'!D77)/'Historical Financials'!D77,"-") -> -0.58558559 | F67: =IFERROR(('Historical Financials'!F77-'Historical Financials'!E77)/'Historical Financials'!E77,"-") -> 0.19565217 | G67: =IFERROR(('Historical Financials'!G77-'Historical Financials'!F77)/'Historical Financials'!F77,"-") -> 2.1454545 | H67: =IFERROR(('Historical Financials'!H77-'Historical Financials'!G77)/'Historical Financials'!G77,"-") -> -0.78901734 | I67: =IFERROR(('Historical Financials'!I77-'Historical Financials'!H77)/'Historical Financials'!H77,"-") -> 0.8630137 | J67: =IFERROR(('Historical Financials'!J77-'Historical Financials'!I77)/'Historical Financials'!I77,"-") -> -0.25 | K67: =IFERROR(('Historical Financials'!K77-'Historical Financials'!J77)/'Historical Financials'!J77,"-") -> 0.2745098 | L67: =IFERROR(('Historical Financials'!L77-'Historical Financials'!K77)/'Historical Financials'!K77,"-") -> 0.43076923
B68: Dividends paid | D68: =IFERROR(('Historical Financials'!D78-'Historical Financials'!C78)/'Historical Financials'!C78,"-") -> 0.49586777 | E68: =IFERROR(('Historical Financials'!E78-'Historical Financials'!D78)/'Historical Financials'!D78,"-") -> 1.0856354 | F68: =IFERROR(('Historical Financials'!F78-'Historical Financials'!E78)/'Historical Financials'!E78,"-") -> 0.4 | G68: =IFERROR(('Historical Financials'!G78-'Historical Financials'!F78)/'Historical Financials'!F78,"-") -> 1.1438032 | H68: =IFERROR(('Historical Financials'!H78-'Historical Financials'!G78)/'Historical Financials'!G78,"-") -> 0.066637246 | I68: =IFERROR(('Historical Financials'!I78-'Historical Financials'!H78)/'Historical Financials'!H78,"-") -> 0 | J68: =IFERROR(('Historical Financials'!J78-'Historical Financials'!I78)/'Historical Financials'!I78,"-") -> -0.2503103 | K68: =IFERROR(('Historical Financials'!K78-'Historical Financials'!J78)/'Historical Financials'!J78,"-") -> -0.25 | L68: =IFERROR(('Historical Financials'!L78-'Historical Financials'!K78)/'Historical Financials'!K78,"-") -> 0.33333333
B69: Financial liabilities | D69: =IFERROR(('Historical Financials'!D79-'Historical Financials'!C79)/'Historical Financials'!C79,"-") -> - | E69: =IFERROR(('Historical Financials'!E79-'Historical Financials'!D79)/'Historical Financials'!D79,"-") -> - | F69: =IFERROR(('Historical Financials'!F79-'Historical Financials'!E79)/'Historical Financials'!E79,"-") -> - | G69: =IFERROR(('Historical Financials'!G79-'Historical Financials'!F79)/'Historical Financials'!F79,"-") -> - | H69: =IFERROR(('Historical Financials'!H79-'Historical Financials'!G79)/'Historical Financials'!G79,"-") -> - | I69: =IFERROR(('Historical Financials'!I79-'Historical Financials'!H79)/'Historical Financials'!H79,"-") -> - | J69: =IFERROR(('Historical Financials'!J79-'Historical Financials'!I79)/'Historical Financials'!I79,"-") -> 0.1 | K69: =IFERROR(('Historical Financials'!K79-'Historical Financials'!J79)/'Historical Financials'!J79,"-") -> -0.27272727 | L69: =IFERROR(('Historical Financials'!L79-'Historical Financials'!K79)/'Historical Financials'!K79,"-") -> 4.875
B70: Other financing items | D70: =IFERROR(('Historical Financials'!D80-'Historical Financials'!C80)/'Historical Financials'!C80,"-") -> 0.51219512 | E70: =IFERROR(('Historical Financials'!E80-'Historical Financials'!D80)/'Historical Financials'!D80,"-") -> 1.483871 | F70: =IFERROR(('Historical Financials'!F80-'Historical Financials'!E80)/'Historical Financials'!E80,"-") -> 0.3961039 | G70: =IFERROR(('Historical Financials'!G80-'Historical Financials'!F80)/'Historical Financials'!F80,"-") -> 1.144186 | H70: =IFERROR(('Historical Financials'!H80-'Historical Financials'!G80)/'Historical Financials'!G80,"-") -> 0.078091106 | I70: =IFERROR(('Historical Financials'!I80-'Historical Financials'!H80)/'Historical Financials'!H80,"-") -> 0 | J70: =IFERROR(('Historical Financials'!J80-'Historical Financials'!I80)/'Historical Financials'!I80,"-") -> -1 | K70: =IFERROR(('Historical Financials'!K80-'Historical Financials'!J80)/'Historical Financials'!J80,"-") -> - | L70: =IFERROR(('Historical Financials'!L80-'Historical Financials'!K80)/'Historical Financials'!K80,"-") -> -
B71: Cash From Financing Activities | D71: =IFERROR(('Historical Financials'!D81-'Historical Financials'!C81)/'Historical Financials'!C81,"-") -> 26.067568 | E71: =IFERROR(('Historical Financials'!E81-'Historical Financials'!D81)/'Historical Financials'!D81,"-") -> -0.38242636 | F71: =IFERROR(('Historical Financials'!F81-'Historical Financials'!E81)/'Historical Financials'!E81,"-") -> -0.087308003 | G71: =IFERROR(('Historical Financials'!G81-'Historical Financials'!F81)/'Historical Financials'!F81,"-") -> 2.0434012 | H71: =IFERROR(('Historical Financials'!H81-'Historical Financials'!G81)/'Historical Financials'!G81,"-") -> -0.14202561 | I71: =IFERROR(('Historical Financials'!I81-'Historical Financials'!H81)/'Historical Financials'!H81,"-") -> 0.053595658 | J71: =IFERROR(('Historical Financials'!J81-'Historical Financials'!I81)/'Historical Financials'!I81,"-") -> -0.50257566 | K71: =IFERROR(('Historical Financials'!K81-'Historical Financials'!J81)/'Historical Financials'!J81,"-") -> 0.04012945 | L71: =IFERROR(('Historical Financials'!L81-'Historical Financials'!K81)/'Historical Financials'!K81,"-") -> -0.24455507
B73: Net Cash Flow | D73: =IFERROR(('Historical Financials'!D83-'Historical Financials'!C83)/'Historical Financials'!C83,"-") -> 0.052631579 | E73: =IFERROR(('Historical Financials'!E83-'Historical Financials'!D83)/'Historical Financials'!D83,"-") -> 1.1057143 | F73: =IFERROR(('Historical Financials'!F83-'Historical Financials'!E83)/'Historical Financials'!E83,"-") -> 0.47354138 | G73: =IFERROR(('Historical Financials'!G83-'Historical Financials'!F83)/'Historical Financials'!F83,"-") -> 0.31583794 | H73: =IFERROR(('Historical Financials'!H83-'Historical Financials'!G83)/'Historical Financials'!G83,"-") -> -1.4205738 | I73: =IFERROR(('Historical Financials'!I83-'Historical Financials'!H83)/'Historical Financials'!H83,"-") -> 1.2770383 | J73: =IFERROR(('Historical Financials'!J83-'Historical Financials'!I83)/'Historical Financials'!I83,"-") -> -2.5915236 | K73: =IFERROR(('Historical Financials'!K83-'Historical Financials'!J83)/'Historical Financials'!J83,"-") -> -1.6469238 | L73: =IFERROR(('Historical Financials'!L83-'Historical Financials'!K83)/'Historical Financials'!K83,"-") -> -1.2420156

Sheet Common Size Statement
B2: ="Common Size Statement"&" - "&'Historical Financials'!B1 -> Common Size Statement - MARUTI SUZUKI LTD
B3: Year | C3: 2016 | D3: =C3+1 -> 2017 | E3: =D3+1 -> 2018 | F3: =E3+1 -> 2019 | G3: =F3+1 -> 2020 | H3: =G3+1 -> 2021 | I3: =H3+1 -> 2022 | J3: =I3+1 -> 2023 | K3: =J3+1 -> 2024 | L3: =K3+1 -> 2025
B5: Income Statement
B6: Sales | C6: ='Historical Financials'!C7/'Historical Financials'!C$7 -> 1 | D6: ='Historical Financials'!D7/'Historical Financials'!D$7 -> 1 | E6: ='Historical Financials'!E7/'Historical Financials'!E$7 -> 1 | F6: ='Historical Financials'!F7/'Historical Financials'!F$7 -> 1 | G6: ='Historical Financials'!G7/'Historical Financials'!G$7 -> 1 | H6: ='Historical Financials'!H7/'Historical Financials'!H$7 -> 1 | I6: ='Historical Financials'!I7/'Historical Financials'!I$7 -> 1 | J6: ='Historical Financials'!J7/'Historical Financials'!J$7 -> 1 | ... L6: ='Historical Financials'!L7/'Historical Financials'!L$7 -> 1
B7: COGS | C7: ='Historical Financials'!C8/'Historical Financials'!C$7 -> 0.72632274 | D7: ='Historical Financials'!D8/'Historical Financials'!D$7 -> 0.7344349 | E7: ='Historical Financials'!E8/'Historical Financials'!E$7 -> 0.73907334 | F7: ='Historical Financials'!F8/'Historical Financials'!F$7 -> 0.74571068 | G7: ='Historical Financials'!G8/'Historical Financials'!G$7 -> 0.76205525 | H7: ='Historical Financials'!H8/'Historical Financials'!H$7 -> 0.78746661 | I7: ='Historical Financials'!I8/'Historical Financials'!I$7 -> 0.81035845 | J7: ='Historical Financials'!J8/'Historical Financials'!J$7 -> 0.78313215 | ... L7: ='Historical Financials'!L8/'Historical Financials'!L$7 -> 0.74890166
B8: Gross Profit | C8: ='Historical Financials'!C9/'Historical Financials'!C$7 -> 0.27367726 | D8: ='Historical Financials'!D9/'Historical Financials'!D$7 -> 0.2655651 | E8: ='Historical Financials'!E9/'Historical Financials'!E$7 -> 0.26092666 | F8: ='Historical Financials'!F9/'Historical Financials'!F$7 -> 0.25428932 | G8: ='Historical Financials'!G9/'Historical Financials'!G$7 -> 0.23794475 | H8: ='Historical Financials'!H9/'Historical Financials'!H$7 -> 0.21253339 | I8: ='Historical Financials'!I9/'Historical Financials'!I$7 -> 0.18964155 | J8: ='Historical Financials'!J9/'Historical Financials'!J$7 -> 0.21686785 | ... L8: ='Historical Financials'!L9/'Historical Financials'!L$7 -> 0.25109834
B9: Selling & General Expenses | C9: ='Historical Financials'!C10/'Historical Financials'!C$7 -> 0.11697894 | D9: ='Historical Financials'!D10/'Historical Financials'!D$7 -> 0.11250202 | E9: ='Historical Financials'!E10/'Historical Financials'!E$7 -> 0.10909116 | F9: ='Historical Financials'!F10/'Historical Financials'!F$7 -> 0.12583001 | G9: ='Historical Financials'!G10/'Historical Financials'!G$7 -> 0.14073354 | H9: ='Historical Financials'!H10/'Historical Financials'!H$7 -> 0.1356477 | I9: ='Historical Financials'!I10/'Historical Financials'!I$7 -> 0.12452196 | J9: ='Historical Financials'!J10/'Historical Financials'!J$7 -> 0.10605363 | ... L9: ='Historical Financials'!L10/'Historical Financials'!L$7 -> 0.11928286
B10: EBITDA | C10: ='Historical Financials'!C11/'Historical Financials'!C$7 -> 0.15669833 | D10: ='Historical Financials'!D11/'Historical Financials'!D$7 -> 0.15306308 | E10: ='Historical Financials'!E11/'Historical Financials'!E$7 -> 0.1518355 | F10: ='Historical Financials'!F11/'Historical Financials'!F$7 -> 0.12845931 | G10: ='Historical Financials'!G11/'Historical Financials'!G$7 -> 0.097211208 | H10: ='Historical Financials'!H11/'Historical Financials'!H$7 -> 0.076885693 | I10: ='Historical Financials'!I11/'Historical Financials'!I$7 -> 0.065119586 | J10: ='Historical Financials'!J11/'Historical Financials'!J$7 -> 0.11081421 | ... L10: ='Historical Financials'!L11/'Historical Financials'!L$7 -> 0.13181548
B11: Depreciation | C11: ='Historical Financials'!C12/'Historical Financials'!C$7 -> 0.048998941 | D11: ='Historical Financials'!D12/'Historical Financials'!D$7 -> 0.038244841 | E11: ='Historical Financials'!E12/'Historical Financials'!E$7 -> 0.034579887 | F11: ='Historical Financials'!F12/'Historical Financials'!F$7 -> 0.035097626 | G11: ='Historical Financials'!G12/'Historical Financials'!G$7 -> 0.046634946 | H11: ='Historical Financials'!H12/'Historical Financials'!H$7 -> 0.043115159 | I11: ='Historical Financials'!I12/'Historical Financials'!I$7 -> 0.031574848 | J11: ='Historical Financials'!J12/'Historical Financials'!J$7 -> 0.040925632 | ... L11: ='Historical Financials'!L12/'Historical Financials'!L$7 -> 0.036675757
B12: EBIT | C12: ='Historical Financials'!C13/'Historical Financials'!C$7 -> 0.10769939 | D12: ='Historical Financials'!D13/'Historical Financials'!D$7 -> 0.11481824 | E12: ='Historical Financials'!E13/'Historical Financials'!E$7 -> 0.11725561 | F12: ='Historical Financials'!F13/'Historical Financials'!F$7 -> 0.093361683 | G12: ='Historical Financials'!G13/'Historical Financials'!G$7 -> 0.050576262 | H12: ='Historical Financials'!H13/'Historical Financials'!H$7 -> 0.033770534 | I12: ='Historical Financials'!I13/'Historical Financials'!I$7 -> 0.033544738 | J12: ='Historical Financials'!J13/'Historical Financials'!J$7 -> 0.069888582 | ... L12: ='Historical Financials'!L13/'Historical Financials'!L$7 -> 0.09513972
B13: Interest | C13: ='Historical Financials'!C14/'Historical Financials'!C$7 -> 0.0014186737 | D13: ='Historical Financials'!D14/'Historical Financials'!D$7 -> 0.0013130646 | E13: ='Historical Financials'!E14/'Historical Financials'!E$7 -> 0.004332823 | F13: ='Historical Financials'!F14/'Historical Financials'!F$7 -> 0.00088185573 | G13: ='Historical Financials'!G14/'Historical Financials'!G$7 -> 0.0017737246 | H13: ='Historical Financials'!H14/'Historical Financials'!H$7 -> 0.0014465981 | I13: ='Historical Financials'!I14/'Historical Financials'!I$7 -> 0.0014332649 | J13: ='Historical Financials'!J14/'Historical Financials'!J$7 -> 0.002130734 | ... L13: ='Historical Financials'!L14/'Historical Financials'!L$7 -> 0.0012700032
B14: Other Income | C14: ='Historical Financials'!C15/'Historical Financials'!C$7 -> 0.025423258 | D14: ='Historical Financials'!D15/'Historical Financials'!D$7 -> 0.035238305 | E14: ='Historical Financials'!E15/'Historical Financials'!E$7 -> 0.02699682 | F14: ='Historical Financials'!F15/'Historical Financials'!F$7 -> 0.030954414 | G14: ='Historical Financials'!G15/'Historical Financials'!G$7 -> 0.045075337 | H14: ='Historical Financials'!H15/'Historical Financials'!H$7 -> 0.043288524 | I14: ='Historical Financials'!I15/'Historical Financials'!I$7 -> 0.021066503 | J14: ='Historical Financials'!J15/'Historical Financials'!J$7 -> 0.020395254 | ... L14: ='Historical Financials'!L15/'Historical Financials'!L$7 -> 0.034438537
B15: EBT | C15: ='Historical Financials'!C16/'Historical Financials'!C$7 -> 0.080857455 | D15: ='Historical Financials'!D16/'Historical Financials'!D$7 -> 0.078266872 | E15: ='Historical Financials'!E16/'Historical Financials'!E$7 -> 0.085925969 | F15: ='Historical Financials'!F16/'Historical Financials'!F$7 -> 0.061525413 | G15: ='Historical Financials'!G16/'Historical Financials'!G$7 -> 0.0037272006 | H15: ='Historical Financials'!H16/'Historical Financials'!H$7 -> -0.010964588 | I15: ='Historical Financials'!I16/'Historical Financials'!I$7 -> 0.01104497 | J15: ='Historical Financials'!J16/'Historical Financials'!J$7 -> 0.047362594 | ... L15: ='Historical Financials'!L16/'Historical Financials'!L$7 -> 0.05943118
B16: Tax | C16: ='Historical Financials'!C17/'Historical Financials'!C$7 -> 0.036248242 | D16: ='Historical Financials'!D17/'Historical Financials'!D$7 -> 0.038425498 | E16: ='Historical Financials'!E17/'Historical Financials'!E$7 -> 0.041175601 | F16: ='Historical Financials'!F17/'Historical Financials'!F$7 -> 0.034544578 | G16: ='Historical Financials'!G17/'Historical Financials'!G$7 -> 0.018836902 | H16: ='Historical Financials'!H17/'Historical Financials'!H$7 -> 0.013242483 | I16: ='Historical Financials'!I17/'Historical Financials'!I$7 -> 0.0092573514 | J16: ='Historical Financials'!J17/'Historical Financials'!J$7 -> 0.018364174 | ... L16: ='Historical Financials'!L17/'Historical Financials'!L$7 -> 0.033481784
B17: Net Profit | C17: ='Historical Financials'!C18/'Historical Financials'!C$7 -> 0.044609214 | D17: ='Historical Financials'!D18/'Historical Financials'!D$7 -> 0.039841375 | E17: ='Historical Financials'!E18/'Historical Financials'!E$7 -> 0.044750368 | F17: ='Historical Financials'!F18/'Historical Financials'!F$7 -> 0.026980835 | G17: ='Historical Financials'!G18/'Historical Financials'!G$7 -> -0.015109701 | H17: ='Historical Financials'!H18/'Historical Financials'!H$7 -> -0.024207071 | I17: ='Historical Financials'!I18/'Historical Financials'!I$7 -> 0.0017876187 | J17: ='Historical Financials'!J18/'Historical Financials'!J$7 -> 0.02899842 | ... L17: ='Historical Financials'!L18/'Historical Financials'!L$7 -> 0.025949396
B19: Balance Sheet
B20: Total Liabilities | C20: =IFERROR('Historical Financials'!C34/'Historical Financials'!C$47,"-") -> 0.90458416 | D20: =IFERROR('Historical Financials'!D34/'Historical Financials'!D$47,"-") -> 0.92046455 | E20: =IFERROR('Historical Financials'!E34/'Historical Financials'!E$47,"-") -> 0.92764057 | F20: =IFERROR('Historical Financials'!F34/'Historical Financials'!F$47,"-") -> 0.91656338 | G20: =IFERROR('Historical Financials'!G34/'Historical Financials'!G$47,"-") -> 0.92417242 | H20: =IFERROR('Historical Financials'!H34/'Historical Financials'!H$47,"-") -> 0.90633901 | I20: =IFERROR('Historical Financials'!I34/'Historical Financials'!I$47,"-") -> 0.8966066 | J20: =IFERROR('Historical Financials'!J34/'Historical Financials'!J$47,"-") -> 0.89714544 | ... L20: =IFERROR('Historical Financials'!L34/'Historical Financials'!L$47,"-") -> 0.90405514
B21: Equity Share Capital | C21: ='Historical Financials'!C30/'Historical Financials'!C$47 -> 0.0031969716 | D21: ='Historical Financials'!D30/'Historical Financials'!D$47 -> 0.0026749194 | E21: ='Historical Financials'!E30/'Historical Financials'!E$47 -> 0.0023249369 | F21: ='Historical Financials'!F30/'Historical Financials'!F$47 -> 0.0021635749 | G21: ='Historical Financials'!G30/'Historical Financials'!G$47 -> 0.0021932277 | H21: ='Historical Financials'!H30/'Historical Financials'!H$47 -> 0.0019174092 | I21: ='Historical Financials'!I30/'Historical Financials'!I$47 -> 0.0018134979 | J21: ='Historical Financials'!J30/'Historical Financials'!J$47 -> 0.0014088193 | ... L21: ='Historical Financials'!L30/'Historical Financials'!L$47 -> 0.0010768775
B22: Reserves | C22: ='Historical Financials'!C31/'Historical Financials'!C$47 -> 0.64500489 | D22: ='Historical Financials'!D31/'Historical Financials'!D$47 -> 0.65409927 | E22: ='Historical Financials'!E31/'Historical Financials'!E$47 -> 0.65295929 | F22: ='Historical Financials'!F31/'Historical Financials'!F$47 -> 0.67258665 | G22: ='Historical Financials'!G31/'Historical Financials'!G$47 -> 0.71551513 | H22: ='Historical Financials'!H31/'Historical Financials'!H$47 -> 0.6647391 | I22: ='Historical Financials'!I31/'Historical Financials'!I$47 -> 0.66273742 | J22: ='Historical Financials'!J31/'Historical Financials'!J$47 -> 0.66715479 | ... L22: ='Historical Financials'!L31/'Historical Financials'!L$47 -> 0.65820167
B23: Borrowings | C23: ='Historical Financials'!C32/'Historical Financials'!C$47 -> 0.0048886141 | D23: ='Historical Financials'!D32/'Historical Financials'!D$47 -> 0.0085668278 | E23: ='Historical Financials'!E32/'Historical Financials'!E$47 -> 0.0018599495 | F23: ='Historical Financials'!F32/'Historical Financials'!F$47 -> 0.0022867983 | G23: ='Historical Financials'!G32/'Historical Financials'!G$47 -> 0.0026739949 | H23: ='Historical Financials'!H32/'Historical Financials'!H$47 -> 0.0068683883 | I23: ='Historical Financials'!I32/'Historical Financials'!I$47 -> 0.005110221 | J23: ='Historical Financials'!J32/'Historical Financials'!J$47 -> 0.011180935 | ... L23: ='Historical Financials'!L32/'Historical Financials'!L$47 -> 0.00059598185
B24: Other Liabilities | C24: ='Historical Financials'!C33/'Historical Financials'!C$47 -> 0.25149368 | D24: ='Historical Financials'!D33/'Historical Financials'!D$47 -> 0.25512353 | E24: ='Historical Financials'!E33/'Historical Financials'!E$47 -> 0.2704964 | F24: ='Historical Financials'!F33/'Historical Financials'!F$47 -> 0.23952636 | G24: ='Historical Financials'!G33/'Historical Financials'!G$47 -> 0.20379007 | H24: ='Historical Financials'!H33/'Historical Financials'!H$47 -> 0.23281411 | I24: ='Historical Financials'!I33/'Historical Financials'!I$47 -> 0.22694546 | J24: ='Historical Financials'!J33/'Historical Financials'!J$47 -> 0.21740089 | ... L24: ='Historical Financials'!L33/'Historical Financials'!L$47 -> 0.24418061
B26: Total Assets | C26: ='Historical Financials'!C47/'Historical Financials'!C47 -> 1 | D26: ='Historical Financials'!D47/'Historical Financials'!D47 -> 1 | E26: ='Historical Financials'!E47/'Historical Financials'!E47 -> 1 | F26: ='Historical Financials'!F47/'Historical Financials'!F47 -> 1 | G26: ='Historical Financials'!G47/'Historical Financials'!G47 -> 1 | H26: ='Historical Financials'!H47/'Historical Financials'!H47 -> 1 | I26: ='Historical Financials'!I47/'Historical Financials'!I47 -> 1 | J26: ='Historical Financials'!J47/'Historical Financials'!J47 -> 1 | ... L26: ='Historical Financials'!L47/'Historical Financials'!L47 -> 1
B27: Fixed Assets Net Block | C27: ='Historical Financials'!C36/'Historical Financials'!C$47 -> 0.26527665 | D27: ='Historical Financials'!D36/'Historical Financials'!D$47 -> 0.23579503 | E27: ='Historical Financials'!E36/'Historical Financials'!E$47 -> 0.20614646 | F27: ='Historical Financials'!F36/'Historical Financials'!F$47 -> 0.22119042 | G27: ='Historical Financials'!G36/'Historical Financials'!G$47 -> 0.22868248 | H27: ='Historical Financials'!H36/'Historical Financials'!H$47 -> 0.19032762 | I27: ='Historical Financials'!I36/'Historical Financials'!I$47 -> 0.16510277 | J27: ='Historical Financials'!J36/'Historical Financials'!J$47 -> 0.25040956 | ... L27: ='Historical Financials'!L36/'Historical Financials'!L$47 -> 0.22869605
B28: Capital Work in Progress | C28: ='Historical Financials'!C37/'Historical Financials'!C$47 -> 0.021318084 | D28: ='Historical Financials'!D37/'Historical Financials'!D$47 -> 0.022184116 | E28: ='Historical Financials'!E37/'Historical Financials'!E$47 -> 0.032827801 | F28: ='Historical Financials'!F37/'Historical Financials'!F$47 -> 0.023024162 | G28: ='Historical Financials'!G37/'Historical Financials'!G$47 -> 0.020555337 | H28: ='Historical Financials'!H37/'Historical Financials'!H$47 -> 0.019006477 | I28: ='Historical Financials'!I37/'Historical Financials'!I$47 -> 0.035267131 | J28: ='Historical Financials'!J37/'Historical Financials'!J$47 -> 0.037129378 | ... L28: ='Historical Financials'!L37/'Historical Financials'!L$47 -> 0.051564076
B29: Investments | C29: ='Historical Financials'!C38/'Historical Financials'!C$47 -> 0.43774798 | D29: ='Historical Financials'!D38/'Historical Financials'!D$47 -> 0.51639407 | E29: ='Historical Financials'!E38/'Historical Financials'!E$47 -> 0.55618495 | F29: ='Historical Financials'!F38/'Historical Financials'!F$47 -> 0.53736322 | G29: ='Historical Financials'!G38/'Historical Financials'!G$47 -> 0.54450146 | H29: ='Historical Financials'!H38/'Historical Financials'!H$47 -> 0.54531625 | I29: ='Historical Financials'!I38/'Historical Financials'!I$47 -> 0.50483339 | J29: ='Historical Financials'!J38/'Historical Financials'!J$47 -> 0.44078747 | ... L29: ='Historical Financials'!L38/'Historical Financials'!L$47 -> 0.45394225
B30: Other Assets | C30: ='Historical Financials'!C39/'Historical Financials'!C$47 -> 0.18024145 | D30: ='Historical Financials'!D39/'Historical Financials'!D$47 -> 0.14609134 | E30: ='Historical Financials'!E39/'Historical Financials'!E$47 -> 0.13248137 | F30: ='Historical Financials'!F39/'Historical Financials'!F$47 -> 0.13498558 | G30: ='Historical Financials'!G39/'Historical Financials'!G$47 -> 0.13043314 | H30: ='Historical Financials'!H39/'Historical Financials'!H$47 -> 0.15168865 | I30: ='Historical Financials'!I39/'Historical Financials'!I$47 -> 0.1914033 | J30: ='Historical Financials'!J39/'Historical Financials'!J$47 -> 0.16881903 | ... L30: ='Historical Financials'!L39/'Historical Financials'!L$47 -> 0.16985277
B31: Receivables | C31: ='Historical Financials'!C40/'Historical Financials'!C$47 -> 0.90458416 | D31: ='Historical Financials'!D40/'Historical Financials'!D$47 -> 0.92046455 | E31: ='Historical Financials'!E40/'Historical Financials'!E$47 -> 0.92764057 | F31: ='Historical Financials'!F40/'Historical Financials'!F$47 -> 0.91656338 | G31: ='Historical Financials'!G40/'Historical Financials'!G$47 -> 0.92417242 | H31: ='Historical Financials'!H40/'Historical Financials'!H$47 -> 0.90633901 | I31: ='Historical Financials'!I40/'Historical Financials'!I$47 -> 0.8966066 | J31: ='Historical Financials'!J40/'Historical Financials'!J$47 -> 0.89714544 | ... L31: ='Historical Financials'!L40/'Historical Financials'!L$47 -> 0.90405514
B32: Inventory | C32: ='Historical Financials'!C41/'Historical Financials'!C$47 -> 0 | D32: ='Historical Financials'!D41/'Historical Financials'!D$47 -> 0 | E32: ='Historical Financials'!E41/'Historical Financials'!E$47 -> 0 | F32: ='Historical Financials'!F41/'Historical Financials'!F$47 -> 0 | G32: ='Historical Financials'!G41/'Historical Financials'!G$47 -> 0 | H32: ='Historical Financials'!H41/'Historical Financials'!H$47 -> 0 | I32: ='Historical Financials'!I41/'Historical Financials'!I$47 -> 0 | J32: ='Historical Financials'!J41/'Historical Financials'!J$47 -> 0 | ... L32: ='Historical Financials'!L41/'Historical Financials'!L$47 -> 0
B33: Cash & Bank | C33: ='Historical Financials'!C42/'Historical Financials'!C$47 -> 0.028019021 | D33: ='Historical Financials'!D42/'Historical Financials'!D$47 -> 0.021303695 | E33: ='Historical Financials'!E42/'Historical Financials'!E$47 -> 0.022562666 | F33: ='Historical Financials'!F42/'Historical Financials'!F$47 -> 0.033138516 | G33: ='Historical Financials'!G42/'Historical Financials'!G$47 -> 0.028725473 | H33: ='Historical Financials'!H42/'Historical Financials'!H$47 -> 0.016252265 | I33: ='Historical Financials'!I42/'Historical Financials'!I$47 -> 0.024434183 | J33: ='Historical Financials'!J42/'Historical Financials'!J$47 -> 0.029438229 | ... L33: ='Historical Financials'!L42/'Historical Financials'!L$47 -> 0.044799339
B35: Cash Flow Statement
B36: Sales | C36: ='Historical Financials'!C7/'Historical Financials'!C$7 -> 1 | D36: ='Historical Financials'!D7/'Historical Financials'!D$7 -> 1 | E36: ='Historical Financials'!E7/'Historical Financials'!E$7 -> 1 | F36: ='Historical Financials'!F7/'Historical Financials'!F$7 -> 1 | G36: ='Historical Financials'!G7/'Historical Financials'!G$7 -> 1 | H36: ='Historical Financials'!H7/'Historical Financials'!H$7 -> 1 | I36: ='Historical Financials'!I7/'Historical Financials'!I$7 -> 1 | J36: ='Historical Financials'!J7/'Historical Financials'!J$7 -> 1 | ... L36: ='Historical Financials'!L7/'Historical Financials'!L$7 -> 1
B37: Cash From Operating Activities | C37: ='Historical Financials'!C60/'Historical Financials'!C$7 -> 0.099602355 | D37: ='Historical Financials'!D60/'Historical Financials'!D$7 -> 0.10567673 | E37: ='Historical Financials'!E60/'Historical Financials'!E$7 -> 0.12457179 | F37: ='Historical Financials'!F60/'Historical Financials'!F$7 -> 0.14494269 | G37: ='Historical Financials'!G60/'Historical Financials'!G$7 -> 0.19292889 | H37: ='Historical Financials'!H60/'Historical Financials'!H$7 -> 0.075115103 | I37: ='Historical Financials'!I60/'Historical Financials'!I$7 -> 0.010472117 | J37: ='Historical Financials'!J60/'Historical Financials'!J$7 -> 0.1114096 | ... L37: ='Historical Financials'!L60/'Historical Financials'!L$7 -> 0.070085604
B38: Cash From Investing Activities | C38: ='Historical Financials'!C72/'Historical Financials'!C$7 -> -0.086770043 | D38: ='Historical Financials'!D72/'Historical Financials'!D$7 -> -0.065976353 | E38: ='Historical Financials'!E72/'Historical Financials'!E$7 -> -0.090603363 | F38: ='Historical Financials'!F72/'Historical Financials'!F$7 -> -0.10658952 | G38: ='Historical Financials'!G72/'Historical Financials'!G$7 -> -0.10974095 | H38: ='Historical Financials'!H72/'Historical Financials'!H$7 -> -0.050304098 | I38: ='Historical Financials'!I72/'Historical Financials'!I$7 -> -0.0062945914 | J38: ='Historical Financials'!J72/'Historical Financials'!J$7 -> -0.061574243 | ... L38: ='Historical Financials'!L72/'Historical Financials'!L$7 -> -0.057686397
B39: Cash From Financing Activities | C39: ='Historical Financials'!C81/'Historical Financials'!C$7 -> -0.0012849676 | D39: ='Historical Financials'!D81/'Historical Financials'!D$7 -> -0.029419108 | E39: ='Historical Financials'!E81/'Historical Financials'!E$7 -> -0.015499427 | F39: ='Historical Financials'!F81/'Historical Financials'!F$7 -> -0.013117459 | G39: ='Historical Financials'!G81/'Historical Financials'!G$7 -> -0.045413693 | H39: ='Historical Financials'!H81/'Historical Financials'!H$7 -> -0.041891661 | I39: ='Historical Financials'!I81/'Historical Financials'!I$7 -> -0.035163671 | J39: ='Historical Financials'!J81/'Historical Financials'!J$7 -> -0.013047895 | ... L39: ='Historical Financials'!L81/'Historical Financials'!L$7 -> -0.0079391549
B40: Net Cash Flow | C40: ='Historical Financials'!C83/'Historical Financials'!C$7 -> 0.011547344 | D40: ='Historical Financials'!D83/'Historical Financials'!D$7 -> 0.010281266 | E40: ='Historical Financials'!E83/'Historical Financials'!E$7 -> 0.018469002 | F40: ='Historical Financials'!F83/'Historical Financials'!F$7 -> 0.025235713 | G40: ='Historical Financials'!G83/'Historical Financials'!G$7 -> 0.037774253 | H40: ='Historical Financials'!H83/'Historical Financials'!H$7 -> -0.017080657 | I40: ='Historical Financials'!I83/'Historical Financials'!I$7 -> -0.030986145 | J40: ='Historical Financials'!J83/'Historical Financials'!J$7 -> 0.036787465 | ... L40: ='Historical Financials'!L83/'Historical Financials'!L$7 -> 0.0044600524

Sheet Ratio Analysis
B2: ="Ratio Analysis"&" - "&'Historical Financials'!B1 -> Ratio Analysis - MARUTI SUZUKI LTD
B3: Year | C3: 2016 | D3: =C3+1 -> 2017 | E3: =D3+1 -> 2018 | F3: =E3+1 -> 2019 | G3: =F3+1 -> 2020 | H3: =G3+1 -> 2021 | I3: =H3+1 -> 2022 | J3: =I3+1 -> 2023 | K3: =J3+1 -> 2024 | L3: =K3+1 -> 2025 | M3: Trend | N3: Mean | O3: Median
B5: Sales Growth | C5: ='Comparative Analysis'!C6 -> - | D5: ='Comparative Analysis'!D6 -> 0.18225703 | E5: ='Comparative Analysis'!E6 -> 0.17220239 | F5: ='Comparative Analysis'!F6 -> 0.078425599 | G5: ='Comparative Analysis'!G6 -> -0.12093275 | H5: ='Comparative Analysis'!H6 -> -0.06989162 | I5: ='Comparative Analysis'!I6 -> 0.25518388 | J5: ='Comparative Analysis'!J6 -> 0.34054306 | ... L5: ='Comparative Analysis'!L6 -> 0.077928523 | N5: =AVERAGE(D5:L5) -> 0.12374918 | O5: =MEDIAN(D5:L5) -> 0.17220239
B6: EBITDA Growth | C6: ='Comparative Analysis'!C10 -> - | D6: ='Comparative Analysis'!D10 -> 0.15482984 | E6: ='Comparative Analysis'!E10 -> 0.16280119 | F6: ='Comparative Analysis'!F10 -> -0.087605938 | G6: ='Comparative Analysis'!G10 -> -0.33476841 | H6: ='Comparative Analysis'!H10 -> -0.26436438 | I6: ='Comparative Analysis'!I10 -> 0.063098362 | J6: ='Comparative Analysis'!J10 -> 1.2812065 | ... L6: ='Comparative Analysis'!L10 -> 0.082141918 | N6: =AVERAGE(C6:L6) -> 0.16409604 | O6: =MEDIAN(C6:L6) -> 0.082141918
B7: EBIT Growth | C7: ='Comparative Analysis'!C12 -> - | D7: ='Comparative Analysis'!D12 -> 0.2604034 | E7: ='Comparative Analysis'!E12 -> 0.19708599 | F7: ='Comparative Analysis'!F12 -> -0.14133211 | G7: ='Comparative Analysis'!G12 -> -0.52378819 | H7: ='Comparative Analysis'!H12 -> -0.37895259 | I7: ='Comparative Analysis'!I12 -> 0.2467915 | J7: ='Comparative Analysis'!J12 -> 1.7929463 | ... L7: ='Comparative Analysis'!L12 -> 0.088074492 | N7: =AVERAGE(C7:L7) -> 0.23965573 | O7: =MEDIAN(C7:L7) -> 0.19708599
B8: Net Profit Growth | C8: ='Comparative Analysis'!C17 -> - | D8: ='Comparative Analysis'!D17 -> 0.055897236 | E8: ='Comparative Analysis'!E17 -> 0.31663349 | F8: ='Comparative Analysis'!F17 -> -0.349797 | G8: ='Comparative Analysis'!G17 -> -1.4922918 | H8: ='Comparative Analysis'!H17 -> 0.49011547 | I8: ='Comparative Analysis'!I17 -> -1.0926915 | J8: ='Comparative Analysis'!J17 -> 20.746042 | ... L8: ='Comparative Analysis'!L17 -> -0.2052874 | N8: =AVERAGE(C8:L8) -> 2.1025263 | O8: =MEDIAN(C8:L8) -> 0.055897236
B9: Dividend Growth | C9: =IFERROR(('Historical Financials'!C24-'Historical Financials'!B24)/'Historical Financials'!B24,"-") -> - | D9: =IFERROR(('Historical Financials'!D24-'Historical Financials'!C24)/'Historical Financials'!C24,"-") -> 1.1428571 | E9: =IFERROR(('Historical Financials'!E24-'Historical Financials'!D24)/'Historical Financials'!D24,"-") -> 0.066666667 | F9: =IFERROR(('Historical Financials'!F24-'Historical Financials'!E24)/'Historical Financials'!E24,"-") -> 0 | G9: =IFERROR(('Historical Financials'!G24-'Historical Financials'!F24)/'Historical Financials'!F24,"-") -> -0.25 | H9: =IFERROR(('Historical Financials'!H24-'Historical Financials'!G24)/'Historical Financials'!G24,"-") -> -0.25 | I9: =IFERROR(('Historical Financials'!I24-'Historical Financials'!H24)/'Historical Financials'!H24,"-") -> 0.33333333 | J9: =IFERROR(('Historical Financials'!J24-'Historical Financials'!I24)/'Historical Financials'!I24,"-") -> 0.5 | ... L9: =IFERROR(('Historical Financials'!L24-'Historical Financials'!K24)/'Historical Financials'!K24,"-") -> 0.08 | N9: =AVERAGE(C9:L9) -> 0.22352734 | O9: =MEDIAN(C9:L9) -> 0.08
B11: Gross Margin | C11: ='Common Size Statement'!C8 -> 0.27367726 | D11: ='Common Size Statement'!D8 -> 0.2655651 | E11: ='Common Size Statement'!E8 -> 0.26092666 | F11: ='Common Size Statement'!F8 -> 0.25428932 | G11: ='Common Size Statement'!G8 -> 0.23794475 | H11: ='Common Size Statement'!H8 -> 0.21253339 | I11: ='Common Size Statement'!I8 -> 0.18964155 | J11: ='Common Size Statement'!J8 -> 0.21686785 | ... L11: ='Common Size Statement'!L8 -> 0.25109834 | N11: =AVERAGE(C11:L11) -> 0.24011134 | O11: =MEDIAN(C11:L11) -> 0.24483378
B12: EBITDA Margin | C12: ='Common Size Statement'!C10 -> 0.15669833 | D12: ='Common Size Statement'!D10 -> 0.15306308 | E12: ='Common Size Statement'!E10 -> 0.1518355 | F12: ='Common Size Statement'!F10 -> 0.12845931 | G12: ='Common Size Statement'!G10 -> 0.097211208 | H12: ='Common Size Statement'!H10 -> 0.076885693 | I12: ='Common Size Statement'!I10 -> 0.065119586 | J12: ='Common Size Statement'!J10 -> 0.11081421 | ... L12: ='Common Size Statement'!L10 -> 0.13181548 | N12: =AVERAGE(C12:L12) -> 0.12032046 | O12: =MEDIAN(C12:L12) -> 0.12988078
B13: EBIT Margin | C13: ='Comparative Analysis'!D12 -> 0.2604034 | D13: ='Comparative Analysis'!E12 -> 0.19708599 | E13: ='Comparative Analysis'!F12 -> -0.14133211 | F13: ='Comparative Analysis'!G12 -> -0.52378819 | G13: ='Comparative Analysis'!H12 -> -0.37895259 | H13: ='Comparative Analysis'!I12 -> 0.2467915 | I13: ='Comparative Analysis'!J12 -> 1.7929463 | J13: ='Comparative Analysis'!K12 -> 0.61567277 | ... L13: ='Comparative Analysis'!M12 -> 0 | N13: =AVERAGE(C13:L13) -> 0.21569016 | O13: =MEDIAN(C13:L13) -> 0.14258024
B14: EBT Margin | C14: ='Comparative Analysis'!D15 -> 0.14437883 | D14: ='Comparative Analysis'!E15 -> 0.28691263 | E14: ='Comparative Analysis'!F15 -> -0.22781691 | F14: ='Comparative Analysis'!G15 -> -0.94674623 | G14: ='Comparative Analysis'!H15 -> -3.7361702 | H14: ='Comparative Analysis'!I15 -> -2.2643857 | I14: ='Comparative Analysis'!J15 -> 4.7484625 | J14: ='Comparative Analysis'!K15 -> 0.59218644 | ... L14: ='Comparative Analysis'!M15 -> 0 | N14: =AVERAGE(C14:L14) -> -0.13854281 | O14: =MEDIAN(C14:L14) -> 0.0088752758
B15: Net Profit Margin | C15: ='Comparative Analysis'!D17 -> 0.055897236 | D15: ='Comparative Analysis'!E17 -> 0.31663349 | E15: ='Comparative Analysis'!F17 -> -0.349797 | F15: ='Comparative Analysis'!G17 -> -1.4922918 | G15: ='Comparative Analysis'!H17 -> 0.49011547 | H15: ='Comparative Analysis'!I17 -> -1.0926915 | I15: ='Comparative Analysis'!J17 -> 20.746042 | J15: ='Comparative Analysis'!K17 -> 0.45411655 | ... L15: ='Comparative Analysis'!M17 -> 0 | N15: =AVERAGE(C15:L15) -> 1.8922737 | O15: =MEDIAN(C15:L15) -> 0.027948618
B17: SalesExpenses%Sales | C17: ='Historical Financials'!C10/'Historical Financials'!C7 -> 0.11697894 | D17: ='Historical Financials'!D10/'Historical Financials'!D7 -> 0.11250202 | E17: ='Historical Financials'!E10/'Historical Financials'!E7 -> 0.10909116 | F17: ='Historical Financials'!F10/'Historical Financials'!F7 -> 0.12583001 | G17: ='Historical Financials'!G10/'Historical Financials'!G7 -> 0.14073354 | H17: ='Historical Financials'!H10/'Historical Financials'!H7 -> 0.1356477 | I17: ='Historical Financials'!I10/'Historical Financials'!I7 -> 0.12452196 | J17: ='Historical Financials'!J10/'Historical Financials'!J7 -> 0.10605363 | ... L17: ='Historical Financials'!L10/'Historical Financials'!L7 -> 0.11928286 | N17: =AVERAGE(C17:L17) -> 0.11979088 | O17: =MEDIAN(C17:L17) -> 0.1181309
B18: Depreciation%Sales | C18: ='Historical Financials'!C12/'Historical Financials'!C7 -> 0.048998941 | D18: ='Historical Financials'!D12/'Historical Financials'!D7 -> 0.038244841 | E18: ='Historical Financials'!E12/'Historical Financials'!E7 -> 0.034579887 | F18: ='Historical Financials'!F12/'Historical Financials'!F7 -> 0.035097626 | G18: ='Historical Financials'!G12/'Historical Financials'!G7 -> 0.046634946 | H18: ='Historical Financials'!H12/'Historical Financials'!H7 -> 0.043115159 | I18: ='Historical Financials'!I12/'Historical Financials'!I7 -> 0.031574848 | J18: ='Historical Financials'!J12/'Historical Financials'!J7 -> 0.040925632 | ... L18: ='Historical Financials'!L12/'Historical Financials'!L7 -> 0.036675757 | N18: =AVERAGE(C18:L18) -> 0.039289731 | O18: =MEDIAN(C18:L18) -> 0.037647257
B19: OperatingIncome%Sales | C19: ='Historical Financials'!C11/'Historical Financials'!C7 -> 0.15669833 | D19: ='Historical Financials'!D11/'Historical Financials'!D7 -> 0.15306308 | E19: ='Historical Financials'!E11/'Historical Financials'!E7 -> 0.1518355 | F19: ='Historical Financials'!F11/'Historical Financials'!F7 -> 0.12845931 | G19: ='Historical Financials'!G11/'Historical Financials'!G7 -> 0.097211208 | H19: ='Historical Financials'!H11/'Historical Financials'!H7 -> 0.076885693 | I19: ='Historical Financials'!I11/'Historical Financials'!I7 -> 0.065119586 | J19: ='Historical Financials'!J11/'Historical Financials'!J7 -> 0.11081421 | ... L19: ='Historical Financials'!L11/'Historical Financials'!L7 -> 0.13181548 | N19: =AVERAGE(C19:L19) -> 0.12032046 | O19: =MEDIAN(C19:L19) -> 0.12988078
B21: Return on Capital Employed | C21: =('Historical Financials'!C47-'Historical Financials'!C34)/'Historical Financials'!C13 -> 0.72661755 | D21: =('Historical Financials'!D47-'Historical Financials'!D34)/'Historical Financials'!D13 -> 0.57433418 | E21: =('Historical Financials'!E47-'Historical Financials'!E34)/'Historical Financials'!E13 -> 0.50219596 | F21: =('Historical Financials'!F47-'Historical Financials'!F34)/'Historical Financials'!F13 -> 0.72468421 | G21: =('Historical Financials'!G47-'Historical Financials'!G34)/'Historical Financials'!G13 -> 1.3642921 | H21: =('Historical Financials'!H47-'Historical Financials'!H34)/'Historical Financials'!H13 -> 3.103724 | I21: =('Historical Financials'!I47-'Historical Financials'!I34)/'Historical Financials'!I13 -> 2.9055012 | J21: =('Historical Financials'!J47-'Historical Financials'!J34)/'Historical Financials'!J13 -> 1.3868407 | ... L21: =('Historical Financials'!L47-'Historical Financials'!L34)/'Historical Financials'!L13 -> 0.96272365 | N21: =AVERAGE(C21:L21) -> 1.3203929 | O21: =MEDIAN(C21:L21) -> 0.95786981
B22: Retained Earnings% | C22: ='Historical Financials'!C27 -> 0.58855586 | D22: ='Historical Financials'!D27 -> 0.16500774 | E22: ='Historical Financials'!E27 -> 0.32353353 | F22: ='Historical Financials'!F27 -> 0 | G22: ='Historical Financials'!G27 -> 0 | H22: ='Historical Financials'!H27 -> 0 | I22: ='Historical Financials'!I27 -> 0 | J22: ='Historical Financials'!J27 -> 0.17593267 | ... L22: ='Historical Financials'!L27 -> 0 | N22: =AVERAGE(C22:L22) -> 0.14659279 | O22: =MEDIAN(C22:L22) -> 0.082503871
B23: Return on Equity% | C23: ='Historical Financials'!C18/SUM('Historical Financials'!C30:C31) -> 0.083910374 | D23: ='Historical Financials'!D18/SUM('Historical Financials'!D30:D31) -> 0.073165008 | E23: ='Historical Financials'!E18/SUM('Historical Financials'!E30:E31) -> 0.083918006 | F23: ='Historical Financials'!F18/SUM('Historical Financials'!F30:F31) -> 0.04931188 | G23: ='Historical Financials'!G18/SUM('Historical Financials'!G30:G31) -> -0.023135612 | H23: ='Historical Financials'!H18/SUM('Historical Financials'!H30:H31) -> -0.032447248 | I23: ='Historical Financials'!I18/SUM('Historical Financials'!I30:I31) -> 0.0028536059 | J23: ='Historical Financials'!J18/SUM('Historical Financials'!J30:J31) -> 0.046028027 | ... L23: ='Historical Financials'!L18/SUM('Historical Financials'!L30:L31) -> 0.041230301 | N23: =AVERAGE(C23:L23) -> 0.038313926 | O23: =MEDIAN(C23:L23) -> 0.047669954
B24: Self Sustained Growth Rate | C24: =C21*C22 -> 0.42765501 | D24: =D21*D22 -> 0.094769586 | E24: =E21*E22 -> 0.16247723 | F24: =F21*F22 -> 0 | G24: =G21*G22 -> 0 | H24: =H21*H22 -> 0 | I24: =I21*I22 -> 0 | J24: =J21*J22 -> 0.24399058 | ... L24: =L21*L22 -> 0 | N24: =AVERAGE(C24:L24) -> 0.11317877 | O24: =MEDIAN(C24:L24) -> 0.047384793
B25: Interest Coverage Ratio | C25: ='Historical Financials'!C13/'Historical Financials'!C14 -> 75.915545 | D25: ='Historical Financials'!D13/'Historical Financials'!D14 -> 87.442953 | E25: ='Historical Financials'!E13/'Historical Financials'!E14 -> 27.062175 | F25: ='Historical Financials'!F13/'Historical Financials'!F14 -> 105.86957 | G25: ='Historical Financials'!G13/'Historical Financials'!G14 -> 28.514158 | H25: ='Historical Financials'!H13/'Historical Financials'!H14 -> 23.344794 | I25: ='Historical Financials'!I13/'Historical Financials'!I14 -> 23.404423 | J25: ='Historical Financials'!J13/'Historical Financials'!J14 -> 32.800238 | ... L25: ='Historical Financials'!L13/'Historical Financials'!L14 -> 74.912976 | N25: =AVERAGE(C25:L25) -> 54.832933 | O25: =MEDIAN(C25:L25) -> 50.931369
B27: Debtor Turnover Ratio | C27: ='Historical Financials'!C15/'Historical Financials'!C16 -> 0.3144207 | D27: ='Historical Financials'!D15/'Historical Financials'!D16 -> 0.4502327 | E27: ='Historical Financials'!E15/'Historical Financials'!E16 -> 0.31418697 | F27: ='Historical Financials'!F15/'Historical Financials'!F16 -> 0.50311591 | G27: ='Historical Financials'!G15/'Historical Financials'!G16 -> 12.093617 | H27: ='Historical Financials'!H15/'Historical Financials'!H16 -> -3.9480301 | I27: ='Historical Financials'!I15/'Historical Financials'!I16 -> 1.9073391 | J27: ='Historical Financials'!J15/'Historical Financials'!J16 -> 0.43061945 | ... L27: ='Historical Financials'!L15/'Historical Financials'!L16 -> 0.57946918 | N27: =AVERAGE(C27:L27) -> 1.3120663 | O27: =MEDIAN(C27:L27) -> 0.46296254
B28: Creditor Turnover Ratio | C28: ='Historical Financials'!C7/'Historical Financials'!C33 -> 4.8481303 | D28: ='Historical Financials'!D7/'Historical Financials'!D33 -> 4.7275341 | E28: ='Historical Financials'!E7/'Historical Financials'!E33 -> 4.5428331 | F28: ='Historical Financials'!F7/'Historical Financials'!F33 -> 5.1485613 | G28: ='Historical Financials'!G7/'Historical Financials'!G33 -> 5.3924993 | H28: ='Historical Financials'!H7/'Historical Financials'!H33 -> 3.8382075 | I28: ='Historical Financials'!I7/'Historical Financials'!I33 -> 4.6744 | J28: ='Historical Financials'!J7/'Historical Financials'!J33 -> 4.8812319 | ... L28: ='Historical Financials'!L7/'Historical Financials'!L33 -> 4.2898984 | N28: =AVERAGE(C28:L28) -> 4.7143993 | O28: =MEDIAN(C28:L28) -> 4.7641156
B29: Inventory Turnover | C29: ='Historical Financials'!C8/'Historical Financials'!C43 -> 13.352551 | D29: ='Historical Financials'!D8/'Historical Financials'!D43 -> 15.321261 | E29: ='Historical Financials'!E8/'Historical Financials'!E43 -> 18.664958 | F29: ='Historical Financials'!F8/'Historical Financials'!F43 -> 19.31686 | G29: ='Historical Financials'!G8/'Historical Financials'!G43 -> 17.939917 | H29: ='Historical Financials'!H8/'Historical Financials'!H43 -> 18.175008 | I29: ='Historical Financials'!I8/'Historical Financials'!I43 -> 20.264077 | J29: ='Historical Financials'!J8/'Historical Financials'!J43 -> 17.035106 | ... L29: ='Historical Financials'!L8/'Historical Financials'!L43 -> 16.564948 | N29: =AVERAGE(C29:L29) -> 17.694555 | O29: =MEDIAN(C29:L29) -> 18.057463
B30: Fixed Asset Turnover | C30: ='Historical Financials'!C7/'Historical Financials'!C36 -> 4.5962361 | D30: ='Historical Financials'!D7/'Historical Financials'!D36 -> 5.1150578 | E30: ='Historical Financials'!E7/'Historical Financials'!E36 -> 5.9609076 | F30: ='Historical Financials'!F7/'Historical Financials'!F36 -> 5.5753597 | G30: ='Historical Financials'!G7/'Historical Financials'!G36 -> 4.8055182 | H30: ='Historical Financials'!H7/'Historical Financials'!H36 -> 4.6950036 | I30: ='Historical Financials'!I7/'Historical Financials'!I36 -> 6.4252939 | J30: ='Historical Financials'!J7/'Historical Financials'!J36 -> 4.2377941 | ... L30: ='Historical Financials'!L7/'Historical Financials'!L36 -> 4.5803591 | N30: =AVERAGE(C30:L30) -> 5.1082476 | O30: =MEDIAN(C30:L30) -> 4.9482322
B31: Capital Turnover Ratio | C31: ='Historical Financials'!C7/('Historical Financials'!C47-'Historical Financials'!C33) -> 1.628943 | D31: ='Historical Financials'!D7/('Historical Financials'!D47-'Historical Financials'!D33) -> 1.6192016 | E31: ='Historical Financials'!E7/('Historical Financials'!E47-'Historical Financials'!E33) -> 1.6844605 | F31: ='Historical Financials'!F7/('Historical Financials'!F47-'Historical Financials'!F33) -> 1.6216422 | G31: ='Historical Financials'!G7/('Historical Financials'!G47-'Historical Financials'!G33) -> 1.3802111 | H31: ='Historical Financials'!H7/('Historical Financials'!H47-'Historical Financials'!H33) -> 1.1647619 | I31: ='Historical Financials'!I7/('Historical Financials'!I47-'Historical Financials'!I33) -> 1.3722626 | J31: ='Historical Financials'!J7/('Historical Financials'!J47-'Historical Financials'!J33) -> 1.3559741 | ... L31: ='Historical Financials'!L7/('Historical Financials'!L47-'Historical Financials'!L33) -> 1.3859264 | N31: =AVERAGE(C31:L31) -> 1.4653614 | O31: =MEDIAN(C31:L31) -> 1.4130782
B33: Debtor Days | C33: =('Historical Financials'!C42/'Historical Financials'!C7)*365 -> 8.3877303 | D33: =('Historical Financials'!D42/'Historical Financials'!D7)*365 -> 6.4470735 | E33: =('Historical Financials'!E42/'Historical Financials'!E7)*365 -> 6.7018547 | F33: =('Historical Financials'!F42/'Historical Financials'!F7)*365 -> 9.8081412 | G33: =('Historical Financials'!G42/'Historical Financials'!G7)*365 -> 9.5408472 | H33: =('Historical Financials'!H42/'Historical Financials'!H7)*365 -> 6.6384855 | I33: =('Historical Financials'!I42/'Historical Financials'!I7)*365 -> 8.4070438 | J33: =('Historical Financials'!J42/'Historical Financials'!J7)*365 -> 10.125437 | ... L33: =('Historical Financials'!L42/'Historical Financials'!L7)*365 -> 15.610121 | N33: =AVERAGE(C33:L33) -> 9.3494264 | O33: =MEDIAN(C33:L33) -> 8.9739455
B34: Payable Days | C34: =('Historical Financials'!C33/'Historical Financials'!C7)*365 -> 75.286756 | D34: =('Historical Financials'!D33/'Historical Financials'!D7)*365 -> 77.20727 | E34: =('Historical Financials'!E33/'Historical Financials'!E7)*365 -> 80.346338 | F34: =('Historical Financials'!F33/'Historical Financials'!F7)*365 -> 70.893591 | G34: =('Historical Financials'!G33/'Historical Financials'!G7)*365 -> 67.686611 | H34: =('Historical Financials'!H33/'Historical Financials'!H7)*365 -> 95.096473 | I34: =('Historical Financials'!I33/'Historical Financials'!I7)*365 -> 78.084888 | J34: =('Historical Financials'!J33/'Historical Financials'!J7)*365 -> 74.776205 | ... L34: =('Historical Financials'!L33/'Historical Financials'!L7)*365 -> 85.0836 | N34: =AVERAGE(C34:L34) -> 78.049236 | O34: =MEDIAN(C34:L34) -> 76.618947
B35: Inventory Days | C35: =('Historical Financials'!C43/'Historical Financials'!C8)*365 -> 27.335601 | D35: =('Historical Financials'!D43/'Historical Financials'!D8)*365 -> 23.823104 | E35: =('Historical Financials'!E43/'Historical Financials'!E8)*365 -> 19.555362 | F35: =('Historical Financials'!F43/'Historical Financials'!F8)*365 -> 18.89541 | G35: =('Historical Financials'!G43/'Historical Financials'!G8)*365 -> 20.34569 | H35: =('Historical Financials'!H43/'Historical Financials'!H8)*365 -> 20.082522 | I35: =('Historical Financials'!I43/'Historical Financials'!I8)*365 -> 18.01217 | J35: =('Historical Financials'!J43/'Historical Financials'!J8)*365 -> 21.426341 | ... L35: =('Historical Financials'!L43/'Historical Financials'!L8)*365 -> 22.034479 | N35: =AVERAGE(C35:L35) -> 20.948136 | O35: =MEDIAN(C35:L35) -> 20.214106
B36: Cash Conversion Cycle (in days) | C36: =C33+C35-C34 -> -39.563425 | D36: =D33+D35-D34 -> -46.937093 | E36: =E33+E35-E34 -> -54.089121 | F36: =F33+F35-F34 -> -42.190039 | G36: =G33+G35-G34 -> -37.800074 | H36: =H33+H35-H34 -> -68.375466 | I36: =I33+I35-I34 -> -51.665674 | J36: =J33+J35-J34 -> -43.224427 | ... L36: =L33+L35-L34 -> -47.439 | N36: =AVERAGE(C36:L36) -> -47.751673 | O36: =MEDIAN(C36:L36) -> -46.584754
B38: CFO/Sales | C38: ='Common Size Statement'!C38 -> -0.086770043 | D38: ='Common Size Statement'!D38 -> -0.065976353 | E38: ='Common Size Statement'!E38 -> -0.090603363 | F38: ='Common Size Statement'!F38 -> -0.10658952 | G38: ='Common Size Statement'!G38 -> -0.10974095 | H38: ='Common Size Statement'!H38 -> -0.050304098 | I38: ='Common Size Statement'!I38 -> -0.0062945914 | J38: ='Common Size Statement'!J38 -> -0.061574243 | ... L38: ='Common Size Statement'!L38 -> -0.057686397 | N38: =AVERAGE(C38:L38) -> -0.063722433 | O38: =MEDIAN(C38:L38) -> -0.063775298
B39: CFO/Total Assets | C39: =IFERROR('Historical Financials'!C58/'Historical Financials'!C47,"-") -> 0.015709622 | D39: =IFERROR('Historical Financials'!D58/'Historical Financials'!D47,"-") -> 0.01319745 | E39: =IFERROR('Historical Financials'!E58/'Historical Financials'!E47,"-") -> 0.022479522 | F39: =IFERROR('Historical Financials'!F58/'Historical Financials'!F47,"-") -> 0.031407656 | G39: =IFERROR('Historical Financials'!G58/'Historical Financials'!G47,"-") -> 0.040785321 | H39: =IFERROR('Historical Financials'!H58/'Historical Financials'!H47,"-") -> -0.016697967 | I39: =IFERROR('Historical Financials'!I58/'Historical Financials'!I47,"-") -> -0.030865495 | J39: =IFERROR('Historical Financials'!J58/'Historical Financials'!J47,"-") -> 0.038859036 | ... L39: =IFERROR('Historical Financials'!L58/'Historical Financials'!L47,"-") -> -0.00066448551 | N39: =AVERAGE(C39:L39) -> 0.009224206 | O39: =MEDIAN(C39:L39) -> 0.014453536
B40: CFO/Total Debt | C40: =IFERROR('Historical Financials'!C58/SUM('Historical Financials'!C32:C33),"-") -> 0.061274206 | D40: =IFERROR('Historical Financials'!D58/SUM('Historical Financials'!D32:D33),"-") -> 0.050049041 | E40: =IFERROR('Historical Financials'!E58/SUM('Historical Financials'!E32:E33),"-") -> 0.08253717 | F40: =IFERROR('Historical Financials'!F58/SUM('Historical Financials'!F32:F33),"-") -> 0.12988398 | G40: =IFERROR('Historical Financials'!G58/SUM('Historical Financials'!G32:G33),"-") -> 0.19754198 | H40: =IFERROR('Historical Financials'!H58/SUM('Historical Financials'!H32:H33),"-") -> -0.069667029 | I40: =IFERROR('Historical Financials'!I58/SUM('Historical Financials'!I32:I33),"-") -> -0.13300901 | J40: =IFERROR('Historical Financials'!J58/SUM('Historical Financials'!J32:J33),"-") -> 0.17000055 | ... L40: =IFERROR('Historical Financials'!L58/SUM('Historical Financials'!L32:L33),"-") -> -0.0027146611 | N40: =AVERAGE(C40:L40) -> 0.039108059 | O40: =MEDIAN(C40:L40) -> 0.055661624

Sheet Cash Flow
B2: 41699 | C2: 42064 | D2: 42430 | E2: 42795 | F2: 43160 | G2: 43525 | H2: 43891 | I2: 44256 | J2: 44621 | K2: 44986 | L2: 45352 | M2: 45717
A3: Cash from Operating Activity - | B3: 4995 | C3: 6449 | D3: 8482 | E3: 10282 | F3: 11788 | G3: 6601 | H3: 3496 | I3: 8856 | J3: 1840 | K3: 10815 | L3: 16801 | M3: 16136
A4: Profit from operations | B4: 5111 | C4: 6779 | D4: 8935 | E4: 10413 | F4: 12036 | G4: 11060 | H4: 7503 | I4: 5531 | J4: 5832 | K4: 13176 | L4: 18676 | M4: 20322
A5: Receivables | B5: 46 | C5: 345 | D5: -204 | E5: 122 | F5: -262 | G5: -851 | H5: 340 | I5: 696 | J5: -764 | K5: -1270 | L5: -1316 | M5: -1969
A6: Inventory | B6: 124 | C6: -982 | D6: -450 | E6: -131 | F6: 104 | G6: -162 | H6: 109 | I6: 165 | J6: -483 | K6: -1050 | L6: 125 | M6: -1595
A7: Payables | B7: 813 | C7: 712 | D7: 1789 | E7: 979 | F7: 2128 | G7: -858 | H7: -2155 | I7: 2680 | J7: -396 | K7: 2491 | L7: 3321 | M7: 3509
A8: Loans Advances | B8: -563 | C8: 23 | D8: -1 | E8: 1 | F8: 0 | G8: -13 | H8: -1 | I8: -6 | J8: -8 | K8: 1 | L8: -3 | M8: -10
A9: Operating investments | B9: 0 | C9: 0 | D9: 0 | E9: 0 | F9: 0 | G9: 0 | H9: 0 | I9: 0 | J9: 0 | K9: 0 | L9: 0 | M9: -3
A10: Other WC items | B10: 321 | C10: 648 | D10: 325 | E10: 1222 | F10: 839 | G10: 569 | H10: -863 | I10: 801 | J10: -1162 | K10: -269 | L10: -406 | M10: -310
A11: Working capital changes | B11: 742 | C11: 745 | D11: 1460 | E11: 2192 | F11: 2808 | G11: -1315 | H11: -2570 | I11: 4336 | J11: -2813 | K11: -97 | L11: 1722 | M11: -378
A12: Direct taxes | B12: -858 | C12: -1075 | D12: -1912 | E12: -2323 | F12: -3056 | G12: -3144 | H12: -1438 | I12: -1011 | J12: -1178 | K12: -2265 | L12: -3597 | M12: -3807
A13: Cash from Investing Activity - | B13: -4997 | C13: -4491 | D13: -7230 | E13: -9173 | F13: -8302 | G13: -3540 | H13: -557 | I13: -7291 | J13: -239 | K13: -8820 | L13: -11865 | M13: -14456
A14: Fixed assets purchased | B14: -3545 | C14: -3058 | D14: -2469 | E14: -3391 | F14: -3912 | G14: -4872 | H14: -3437 | I14: -2370 | J14: -3459 | K14: -8065 | L14: -9200 | M14: -10641
... A30: Net Cash Flow | B30: -76 | C30: -45 | D30: 16 | E30: -20 | F30: 50 | G30: 113 | H30: -165 | I30: 20 | J30: -6 | K30: 780 | L30: 874 | M30: -2475

Sheet Rough Sheet
A5: COGS
A6: Total Expenses | B6: 48565 | C6: 57664 | D6: 67692 | E6: 75012 | F6: 68305 | G6: 64961 | H6: 82578 | I6: 105288 | J6: 123232 | K6: 132757
A7: Operating Profit | B7: 9024 | C7: 10421 | D7: 12118 | E7: 11056 | F7: 7355 | G7: 5411 | H7: 5752 | I7: 13122 | J7: 18626 | K7: 20156
A8: COGS | B8: =B6-B7 -> 39541 | C8: =C6-C7 -> 47243 | D8: =D6-D7 -> 55574 | E8: =E6-E7 -> 63956 | F8: =F6-F7 -> 60950 | G8: =G6-G7 -> 59550 | H8: =H6-H7 -> 76826 | I8: =I6-I7 -> 92166 | ... K8: =K6-K7 -> 112601
A10: S&G Expenses
A11: Total Expenses | B11: 48565 | C11: 57664 | D11: 67692 | E11: 75012 | F11: 68305 | G11: 64961 | H11: 82578 | I11: 105288 | J11: 123232 | K11: 132757
A12: COGS | B12: 39541 | C12: 47243 | D12: 55574 | E12: 63956 | F12: 60950 | G12: 59550 | H12: 76826 | I12: 92166 | J12: 104606 | K12: 112601
A13: S&G Expenses | B13: =B11-B12 -> 9024 | C13: =C11-C12 -> 10421 | D13: =D11-D12 -> 12118 | E13: =E11-E12 -> 11056 | F13: =F11-F12 -> 7355 | G13: =G11-G12 -> 5411 | H13: =H11-H12 -> 5752 | I13: =I11-I12 -> 13122 | ... K13: =K11-K12 -> 20156
B15: 7585 | C15: 10127 | D15: 11167 | E15: 10624 | F15: 7103 | G15: 5321 | H15: 4697 | I15: 10438 | J15: 17424 | K15: 19620
B16: 0.28 | C16: 0.26 | D16: 0.29 | E16: 0.28 | F16: 0.2 | G16: 0.18 | H16: 0.17 | I16: 0.21 | J16: 0.23 | K16: 0.26
B18: 9709 | C18: 12760 | D18: 14405 | E18: 13599 | F18: 8524 | G18: 6279 | H18: 5495 | I18: 12630 | J18: 21432 | K18: 24721
B19: =B18-B15 -> 2124 | C19: =C18-C15 -> 2633 | D19: =D18-D15 -> 3238 | E19: =E18-E15 -> 2975 | F19: =F18-F15 -> 1421 | G19: =G18-G15 -> 958 | H19: =H18-H15 -> 798 | I19: =I18-I15 -> 2192 | ... K19: =K18-K15 -> 5101

Sheet Data Sheet
A1: COMPANY NAME | B1: MARUTI SUZUKI INDIA LTD
A2: LATEST VERSION | B2: 2.1 | E2: PLEASE DO NOT MAKE ANY CHANGES TO THIS SHEET
A3: CURRENT VERSION | B3: 2.1
A5: META
A6: Number of shares
A7: Face Value | B7: 5
A8: Current Price | B8: 12642
A9: Market Capitalization | B9: 397467.73
A15: PROFIT & LOSS
A16: Report Date | B16: 42460 | C16: 42825 | D16: 43190 | E16: 43555 | F16: 43921 | G16: 44286 | H16: 44651 | I16: 45016 | J16: 45382 | K16: 45747
A17: Sales | B17: 57589 | C17: 68085 | D17: 79809.4 | E17: 86068.5 | F17: 75660 | G17: 70372 | H17: 88329.8 | I17: 118409.9 | J17: 141858.2 | K17: 152913
A18: Raw Material Cost | B18: 38701.2 | C18: 47121.5 | D18: 54945.3 | E18: 59346.6 | F18: 53402 | G18: 50550.5 | H18: 66137.1 | I18: 86066.9 | J18: 100119.5 | K18: 108718.3
A19: Change in Inventory | B19: -4.8 | C19: 379.3 | D19: -40.8 | E19: -211.6 | F19: 238.7 | G19: -273.6 | H19: 93.1 | I19: 580.5 | J19: 378.6 | K19: 1227.5
A20: Power and Fuel | B20: 694.1 | C20: 518.6 | D20: 673.4 | E20: 863.3 | F20: 699.5 | G20: 476.6 | H20: 630.9 | I20: 1091.9 | J20: 1033.4
A21: Other Mfr. Exp | B21: 427.8 | C21: 382.9 | D21: 462.1 | E21: 475.7 | F21: 378.1 | G21: 683.3 | H21: 852.5 | I21: 843.8 | J21: 939.3
A22: Employee Cost | B22: 2000.3 | C22: 2360.3 | D22: 2863.4 | E22: 3285 | F22: 3416.2 | G22: 3431.6 | H22: 4051.4 | I22: 5308.5 | J22: 6301.6 | K22: 7026
A23: Selling and admin | B23: 5367.3 | C23: 6111.3 | D23: 6755.3 | E23: 8390.3 | F23: 8456.3 | G23: 7924 | H23: 9119.1 | I23: 10316.3 | J23: 12082.6
A24: Other Expenses | B24: 1369.4 | C24: 1548.4 | D24: 1951.2 | E24: 2439.7 | F24: 2191.6 | G24: 1621.8 | H24: 1879.9 | I24: 2241.5 | J24: 3134.1 | K24: 18239.9
A25: Other Income | B25: 1464.1 | C25: 2399.2 | D25: 2154.6 | E25: 2664.2 | F25: 3410.4 | G25: 3046.3 | H25: 1860.8 | I25: 2415 | J25: 4247.6 | K25: 5266.1
A26: Depreciation | B26: 2821.8 | C26: 2603.9 | D26: 2759.8 | E26: 3020.8 | F26: 3528.4 | G26: 3034.1 | H26: 2789 | I26: 4846 | J26: 5255.8 | K26: 5608.2
A27: Interest | B27: 81.7 | C27: 89.4 | D27: 345.8 | E27: 75.9 | F27: 134.2 | G27: 101.8 | H27: 126.6 | I27: 252.3 | J27: 193.6 | K27: 194.2
A28: Profit before tax | B28: 7584.7 | C28: 10127.2 | D28: 11166.9 | E28: 10623.8 | F28: 7102.8 | G28: 5321 | H28: 4697.2 | I28: 10438.2 | J28: 17424.5 | K28: 19620
A29: Tax | B29: 2087.5 | C29: 2616.2 | D29: 3286.2 | E29: 2973.2 | F29: 1425.2 | G29: 931.9 | H29: 817.7 | I29: 2174.5 | J29: 3936.3 | K29: 5119.8
A30: Net profit | B30: 5497.2 | C30: 7509.9 | D30: 7880 | E30: 7649.1 | F30: 5676 | G30: 4389.1 | H30: 3879.5 | I30: 8263.7 | J30: 13488.2 | K30: 14500.2
A31: Dividend Amount | B31: 1057 | C31: 2265 | D31: 2416 | E31: 2416 | F31: 1812 | G31: 1359 | H31: 1812 | I31: 2829.6 | J31: 3930 | K31: 4244.4
A40: Quarters
A41: Report Date | B41: 44926 | C41: 45016 | D41: 45107 | E41: 45199 | F41: 45291 | G41: 45382 | H41: 45473 | I41: 45565 | J41: 45657 | K41: 45747
A42: Sales | B42: 29251.1 | C42: 32213.5 | D42: 32534.8 | E42: 37339.4 | F42: 33512.8 | G42: 38471.2 | H42: 35779.4 | I42: 37449.2 | J42: 38764.3 | K42: 40920.1
A43: Expenses | B43: 25878 | C43: 28319.8 | D43: 29014.9 | E43: 32027.9 | F43: 29072.8 | G43: 33250.1 | H43: 30672.8 | I43: 32450.4 | J43: 33687.8 | K43: 36076.1
A44: Other Income | B44: 892.9 | C44: 850.4 | D44: 1109.7 | E44: 957.8 | F44: 1052.9 | G44: 1261 | H44: 1118.1 | I44: 1570.5 | J44: 1124.8 | K44: 1583.1
A45: Depreciation | B45: 1209.3 | C45: 1239.9 | D45: 1314.1 | E45: 1341.9 | F45: 1301.5 | G45: 1298.3 | H45: 1331.7 | I45: 1385.7 | J45: 1429 | K45: 1461.8
A46: Interest | B46: 29.6 | C46: 163.5 | D46: 46.5 | E46: 35.1 | F46: 35.8 | G46: 76.2 | H46: 57.3 | I46: 43 | J46: 46.3 | K46: 47.6
A47: Profit before tax | B47: 3027.1 | C47: 3340.7 | D47: 3269 | E47: 4892.3 | F47: 4155.6 | G47: 5107.6 | H47: 4835.7 | I47: 5140.6 | J47: 4726 | K47: 4917.7
A48: Tax | B48: 621 | C48: 653 | D48: 726.1 | E48: 1106.1 | F48: 948.8 | G48: 1155.3 | H48: 1076 | I48: 2038.1 | J48: 999.1 | K48: 1006.6
A49: Net profit | B49: 2406.1 | C49: 2687.7 | D49: 2542.9 | E49: 3786.2 | F49: 3206.8 | G49: 3952.3 | H49: 3759.7 | I49: 3102.5 | J49: 3726.9 | K49: 3911.1
A50: Operating Profit | B50: 3373.1 | C50: 3893.7 | D50: 3519.9 | E50: 5311.5 | F50: 4440 | G50: 5221.1 | H50: 5106.6 | I50: 4998.8 | J50: 5076.5 | K50: 4844
A55: BALANCE SHEET
A56: Report Date | B56: 42460 | C56: 42825 | D56: 43190 | E56: 43555 | F56: 43921 | G56: 44286 | H56: 44651 | I56: 45016 | J56: 45382 | K56: 45747
A57: Equity Share Capital | B57: 151 | C57: 151 | D57: 151 | E57: 151 | F57: 151 | G57: 151 | H57: 151 | I57: 157.2 | J57: 157.2 | K57: 157.2
A58: Reserves | B58: 30465 | C58: 36924.1 | D58: 42408.4 | E58: 46941.1 | F58: 49262 | G58: 52349.6 | H58: 55182.5 | I58: 74443 | J58: 85478.8 | K58: 96082.7
A59: Borrowings | B59: 230.9 | C59: 483.6 | D59: 120.8 | E59: 159.6 | F59: 184.1 | G59: 540.9 | H59: 425.5 | I59: 1247.6 | J59: 118.6 | K59: 87
A60: Other Liabilities | B60: 11878.6 | C60: 14401.8 | D60: 17568.2 | E60: 16717 | F60: 14030.6 | G60: 18334.6 | H60: 18896.5 | I60: 24258.2 | J60: 29549.5 | K60: 35644.9
A61: Total | B61: 42725.5 | C61: 51960.5 | D61: 60248.4 | E61: 63968.7 | F61: 63627.7 | G61: 71376.1 | H61: 74655.5 | I61: 100106 | J61: 115304.1 | K61: 131971.8
A62: Net Block | B62: 12529.6 | C62: 13310.7 | D62: 13388.8 | E62: 15437.3 | F62: 15744.4 | G62: 14988.7 | H62: 13747.2 | I62: 27941.4 | J62: 27864.8 | K62: 33384.5
A63: Capital Work in Progress | B63: 1006.9 | C63: 1252.3 | D63: 2132.1 | E63: 1606.9 | F63: 1415.2 | G63: 1496.8 | H63: 2936.5 | I63: 4143 | J63: 7734.8 | K63: 7527.2
A64: Investments | B64: 20675.8 | C64: 29150.6 | D64: 36123.1 | E64: 37503.6 | F64: 37488 | G64: 42944.8 | H64: 42034.7 | I64: 49184.3 | J64: 57296 | K64: 66265.4
A65: Other Assets | B65: 8513.2 | C65: 8246.9 | D65: 8604.4 | E65: 9420.9 | F65: 8980.1 | G65: 11945.8 | H65: 15937.1 | I65: 18837.3 | J65: 22408.5 | K65: 24794.7
A66: Total | B66: 42725.5 | C66: 51960.5 | D66: 60248.4 | E66: 63968.7 | F66: 63627.7 | G66: 71376.1 | H66: 74655.5 | I66: 100106 | J66: 115304.1 | K66: 131971.8
A67: Receivables | B67: 1323.4 | C67: 1202.6 | D67: 1465.4 | E67: 2312.8 | F67: 1977.7 | G67: 1279.9 | H67: 2034.5 | I67: 3284.8 | J67: 4596.8 | K67: 6539.7
... A69: Cash & Bank | B69: 50.7 | C69: 23.5 | D69: 74 | E69: 187.8 | F69: 29 | G69: 3047.1 | H69: 3042.2 | I69: 2748.5 | J69: 2827.4 | K69: 552.9
A70: No. of Equity Shares | B70: 302080060 | C70: 302080060 | D70: 302080060 | E70: 302080060 | F70: 302080060 | G70: 302080060 | H70: 302080060 | I70: 302080060 | J70: 314402574
A71: New Bonus Shares
A72: Face value | B72: 5 | C72: 5 | D72: 5 | E72: 5 | F72: 5 | G72: 5 | H72: 5 | I72: 5 | J72: 5 | K72: 5
A80: CASH FLOW:
A81: Report Date | B81: 42460 | C81: 42825 | D81: 43190 | E81: 43555 | F81: 43921 | G81: 44286 | H81: 44651 | I81: 45016 | J81: 45382 | K81: 45747
A82: Cash from Operating Activity | B82: 8482.5 | C82: 10282 | D82: 11787.9 | E82: 6600.9 | F82: 3495.8 | G82: 8856.2 | H82: 1840.5 | I82: 10814.6 | J82: 16801.1 | K82: 16136.2
A83: Cash from Investing Activity | B83: -7230.4 | C83: -9173.2 | D83: -8301.7 | E83: -3539.9 | F83: -556.6 | G83: -7291.3 | H83: -239.2 | I83: -8820.5 | J83: -11864.8 | K83: -14456.1
A84: Cash from Financing Activity | B84: -1236.6 | C84: -1129.3 | D84: -3436.1 | E84: -2947.9 | F84: -3104.3 | G84: -1544.9 | H84: -1607 | I84: -1213.9 | J84: -4062 | K84: -4155.1
A85: Net Cash Flow | B85: 15.5 | C85: -20.5 | D85: 50.1 | E85: 113.1 | F85: -165.1 | G85: 20 | H85: -5.7 | I85: 780.2 | J85: 874.3 | K85: -2475
A90: PRICE: | B90: 3716.3 | C90: 6015.7 | D90: 8861.1 | E90: 6672.55 | F90: 4288.3 | G90: 6859.2 | H90: 7561.3 | I90: 8292.15 | J90: 12600.35 | K90: 11522.15
A92: DERIVED:
A93: Adjusted Equity Shares in Cr | B93: 30.21 | C93: 30.21 | D93: 30.21 | E93: 30.21 | F93: 30.21 | G93: 30.21 | H93: 30.21 | I93: 30.21 | J93: 31.44 | K93: 31.44

Sheet DuPoint Analysis
B2: (IN CRORES)
B3: ="Du Point Analysis"&" - "&'Historical Financials'!B1 -> Du Point Analysis - MARUTI SUZUKI LTD
B4: Year | C4: 2016 | D4: =C4+1 -> 2017 | E4: =D4+1 -> 2018 | F4: =E4+1 -> 2019 | G4: =F4+1 -> 2020 | H4: =G4+1 -> 2021 | I4: =H4+1 -> 2022 | J4: =I4+1 -> 2023 | K4: =J4+1 -> 2024 | L4: =K4+1 -> 2025
B6: Return On Equity
B7: Net Income | C7: ='Historical Financials'!C18 -> 2569 | D7: ='Historical Financials'!D18 -> 2712.6 | E7: ='Historical Financials'!E18 -> 3571.5 | F7: ='Historical Financials'!F18 -> 2322.2 | G7: ='Historical Financials'!G18 -> -1143.2 | H7: ='Historical Financials'!H18 -> -1703.5 | I7: ='Historical Financials'!I18 -> 157.9 | J7: ='Historical Financials'!J18 -> 3433.7 | ... L7: ='Historical Financials'!L18 -> 3968
B8: Equity | C8: =SUM('Historical Financials'!C30:C31) -> 30616 | D8: =SUM('Historical Financials'!D30:D31) -> 37075.1 | E8: =SUM('Historical Financials'!E30:E31) -> 42559.4 | F8: =SUM('Historical Financials'!F30:F31) -> 47092.1 | G8: =SUM('Historical Financials'!G30:G31) -> 49413 | H8: =SUM('Historical Financials'!H30:H31) -> 52500.6 | I8: =SUM('Historical Financials'!I30:I31) -> 55333.5 | J8: =SUM('Historical Financials'!J30:J31) -> 74600.2 | ... L8: =SUM('Historical Financials'!L30:L31) -> 96239.9
B9: ROE | C9: =C7/C8 -> 0.083910374 | D9: =D7/D8 -> 0.073165008 | E9: =E7/E8 -> 0.083918006 | F9: =F7/F8 -> 0.04931188 | G9: =G7/G8 -> -0.023135612 | H9: =H7/H8 -> -0.032447248 | I9: =I7/I8 -> 0.0028536059 | J9: =J7/J8 -> 0.046028027 | ... L9: =L7/L8 -> 0.041230301
B11: Return on Equity - Du Pont Equation
B13: Net Income | C13: ='Historical Financials'!C18 -> 2569 | D13: ='Historical Financials'!D18 -> 2712.6 | E13: ='Historical Financials'!E18 -> 3571.5 | F13: ='Historical Financials'!F18 -> 2322.2 | G13: ='Historical Financials'!G18 -> -1143.2 | H13: ='Historical Financials'!H18 -> -1703.5 | I13: ='Historical Financials'!I18 -> 157.9 | J13: ='Historical Financials'!J18 -> 3433.7 | ... L13: ='Historical Financials'!L18 -> 3968
B14: EBT | C14: ='Historical Financials'!C16 -> 4656.5 | D14: ='Historical Financials'!D16 -> 5328.8 | E14: ='Historical Financials'!E16 -> 6857.7 | F14: ='Historical Financials'!F16 -> 5295.4 | G14: ='Historical Financials'!G16 -> 282 | H14: ='Historical Financials'!H16 -> -771.6 | I14: ='Historical Financials'!I16 -> 975.6 | J14: ='Historical Financials'!J16 -> 5608.2 | ... L14: ='Historical Financials'!L16 -> 9087.8
B15: Tax Burden | C15: =C13/C14 -> 0.55170192 | D15: =D13/D14 -> 0.50904519 | E15: =E13/E14 -> 0.52080143 | F15: =F13/F14 -> 0.43853156 | G15: =G13/G14 -> -4.0539007 | H15: =H13/H14 -> 2.2077501 | I15: =I13/I14 -> 0.16184912 | J15: =J13/J14 -> 0.61226418 | ... L15: =L13/L14 -> 0.43662933
B17: EBT | C17: ='Historical Financials'!C16 -> 4656.5 | D17: ='Historical Financials'!D16 -> 5328.8 | E17: ='Historical Financials'!E16 -> 6857.7 | F17: ='Historical Financials'!F16 -> 5295.4 | G17: ='Historical Financials'!G16 -> 282 | H17: ='Historical Financials'!H16 -> -771.6 | I17: ='Historical Financials'!I16 -> 975.6 | J17: ='Historical Financials'!J16 -> 5608.2 | ... L17: ='Historical Financials'!L16 -> 9087.8
B18: EBIT | C18: ='Historical Financials'!C13 -> 6202.3 | D18: ='Historical Financials'!D13 -> 7817.4 | E18: ='Historical Financials'!E13 -> 9358.1 | F18: ='Historical Financials'!F13 -> 8035.5 | G18: ='Historical Financials'!G13 -> 3826.6 | H18: ='Historical Financials'!H13 -> 2376.5 | I18: ='Historical Financials'!I13 -> 2963 | J18: ='Historical Financials'!J13 -> 8275.5 | ... L18: ='Historical Financials'!L13 -> 14548.1
B19: Interest Burden | C19: =C17/C18 -> 0.75076988 | D19: =D17/D18 -> 0.68165886 | E19: =E17/E18 -> 0.73280901 | F19: =F17/F18 -> 0.65900068 | G19: =G17/G18 -> 0.073694664 | H19: =H17/H18 -> -0.32467915 | I19: =I17/I18 -> 0.32926088 | J19: =J17/J18 -> 0.67768715 | ... L19: =L17/L18 -> 0.62467264
B21: EBIT | C21: ='Historical Financials'!C13 -> 6202.3 | D21: ='Historical Financials'!D13 -> 7817.4 | E21: ='Historical Financials'!E13 -> 9358.1 | F21: ='Historical Financials'!F13 -> 8035.5 | G21: ='Historical Financials'!G13 -> 3826.6 | H21: ='Historical Financials'!H13 -> 2376.5 | I21: ='Historical Financials'!I13 -> 2963 | J21: ='Historical Financials'!J13 -> 8275.5 | ... L21: ='Historical Financials'!L13 -> 14548.1
B22: Sales | C22: ='Historical Financials'!C7 -> 57589 | D22: ='Historical Financials'!D7 -> 68085 | E22: ='Historical Financials'!E7 -> 79809.4 | F22: ='Historical Financials'!F7 -> 86068.5 | G22: ='Historical Financials'!G7 -> 75660 | H22: ='Historical Financials'!H7 -> 70372 | I22: ='Historical Financials'!I7 -> 88329.8 | J22: ='Historical Financials'!J7 -> 118409.9 | ... L22: ='Historical Financials'!L7 -> 152913
B23: Operating Profit Margin | C23: =C21/C22 -> 0.10769939 | D23: =D21/D22 -> 0.11481824 | E23: =E21/E22 -> 0.11725561 | F23: =F21/F22 -> 0.093361683 | G23: =G21/G22 -> 0.050576262 | H23: =H21/H22 -> 0.033770534 | I23: =I21/I22 -> 0.033544738 | J23: =J21/J22 -> 0.069888582 | ... L23: =L21/L22 -> 0.09513972
B25: Sales | C25: ='Historical Financials'!C7 -> 57589 | D25: ='Historical Financials'!D7 -> 68085 | E25: ='Historical Financials'!E7 -> 79809.4 | F25: ='Historical Financials'!F7 -> 86068.5 | G25: ='Historical Financials'!G7 -> 75660 | H25: ='Historical Financials'!H7 -> 70372 | I25: ='Historical Financials'!I7 -> 88329.8 | J25: ='Historical Financials'!J7 -> 118409.9 | ... L25: ='Historical Financials'!L7 -> 152913
B26: Total Asset | C26: ='Historical Financials'!C47 -> 47232.2 | D26: ='Historical Financials'!D47 -> 56450.3 | E26: ='Historical Financials'!E47 -> 64948 | F26: ='Historical Financials'!F47 -> 69791.9 | G26: ='Historical Financials'!G47 -> 68848.3 | H26: ='Historical Financials'!H47 -> 78752.1 | I26: ='Historical Financials'!I47 -> 83264.5 | J26: ='Historical Financials'!J47 -> 111582.8 | ... L26: ='Historical Financials'!L47 -> 145977.6
B27: Asset Turnover | C27: =C25/C26 -> 1.2192741 | D27: =D25/D26 -> 1.2061052 | E27: =E25/E26 -> 1.22882 | F27: =F25/F26 -> 1.2332162 | G27: =G25/G26 -> 1.0989378 | H27: =H25/H26 -> 0.89358887 | I27: =I25/I26 -> 1.0608338 | J27: =J25/J26 -> 1.0611842 | ... L27: =L25/L26 -> 1.04751
B29: Total Assets | C29: ='Historical Financials'!C47 -> 47232.2 | D29: ='Historical Financials'!D47 -> 56450.3 | E29: ='Historical Financials'!E47 -> 64948 | F29: ='Historical Financials'!F47 -> 69791.9 | G29: ='Historical Financials'!G47 -> 68848.3 | H29: ='Historical Financials'!H47 -> 78752.1 | I29: ='Historical Financials'!I47 -> 83264.5 | J29: ='Historical Financials'!J47 -> 111582.8 | ... L29: ='Historical Financials'!L47 -> 145977.6
B30: Equity | C30: =SUM('Historical Financials'!C30:C31) -> 30616 | D30: =SUM('Historical Financials'!D30:D31) -> 37075.1 | E30: =SUM('Historical Financials'!E30:E31) -> 42559.4 | F30: =SUM('Historical Financials'!F30:F31) -> 47092.1 | G30: =SUM('Historical Financials'!G30:G31) -> 49413 | H30: =SUM('Historical Financials'!H30:H31) -> 52500.6 | I30: =SUM('Historical Financials'!I30:I31) -> 55333.5 | J30: =SUM('Historical Financials'!J30:J31) -> 74600.2 | ... L30: =SUM('Historical Financials'!L30:L31) -> 96239.9
B31: Equity Multiplier | C31: =C29/C30 -> 1.5427293 | D31: =D29/D30 -> 1.5225933 | E31: =E29/E30 -> 1.5260553 | F31: =F29/F30 -> 1.4820299 | G31: =G29/G30 -> 1.3933236 | H31: =H29/H30 -> 1.5000229 | I31: =I29/I30 -> 1.5047756 | J31: =J29/J30 -> 1.495744 | ... L31: =L29/L30 -> 1.5168096
B33: ROE | C33: =C15*C19*C23*C27*C31 -> 0.083910374 | D33: =D15*D19*D23*D27*D31 -> 0.073165008 | E33: =E15*E19*E23*E27*E31 -> 0.083918006 | F33: =F15*F19*F23*F27*F31 -> 0.04931188 | G33: =G15*G19*G23*G27*G31 -> -0.023135612 | H33: =H15*H19*H23*H27*H31 -> -0.032447248 | I33: =I15*I19*I23*I27*I31 -> 0.0028536059 | J33: =J15*J19*J23*J27*J31 -> 0.046028027 | ... L33: =L15*L19*L23*L27*L31 -> 0.041230301

Sheet Altman Z Score
B2: (IN CRORES)
B3: ="Altman's Z-Score"&" - "&'Historical Financials'!B1 -> Altman's Z-Score - MARUTI SUZUKI LTD
B4: Year | C4: 2016 | D4: =C4+1 -> 2017 | E4: =D4+1 -> 2018 | F4: =E4+1 -> 2019 | G4: =F4+1 -> 2020 | H4: =G4+1 -> 2021 | I4: =H4+1 -> 2022 | J4: =I4+1 -> 2023 | K4: =J4+1 -> 2024 | L4: =K4+1 -> 2025
B6: Working Capital | C6: ='Historical Financials'!C45-'Historical Financials'!C33 -> -7371.9 | D6: ='Historical Financials'!D45-'Historical Financials'!D33 -> -9912 | E6: ='Historical Financials'!E45-'Historical Financials'!E33 -> -12868.6 | F6: ='Historical Financials'!F45-'Historical Financials'!F33 -> -10893.8 | G6: ='Historical Financials'!G45-'Historical Financials'!G33 -> -8810 | H6: ='Historical Financials'!H45-'Historical Financials'!H33 -> -10958.6 | I6: ='Historical Financials'!I45-'Historical Financials'!I33 -> -10287.5 | J6: ='Historical Financials'!J45-'Historical Financials'!J33 -> -12781.4 | ... L6: ='Historical Financials'!L45-'Historical Financials'!L33 -> -21639.1
B7: Total Assets | C7: ='Historical Financials'!C47 -> 47232.2 | D7: ='Historical Financials'!D47 -> 56450.3 | E7: ='Historical Financials'!E47 -> 64948 | F7: ='Historical Financials'!F47 -> 69791.9 | G7: ='Historical Financials'!G47 -> 68848.3 | H7: ='Historical Financials'!H47 -> 78752.1 | I7: ='Historical Financials'!I47 -> 83264.5 | J7: ='Historical Financials'!J47 -> 111582.8 | ... L7: ='Historical Financials'!L47 -> 145977.6
B8: X1: Working Capital/Total Assets | C8: =C6/C7 -> -0.15607785 | D8: =D6/D7 -> -0.17558808 | E8: =E6/E7 -> -0.19813697 | F8: =F6/F7 -> -0.15608975 | G8: =G6/G7 -> -0.12796249 | H8: =H6/H7 -> -0.13915311 | I8: =I6/I7 -> -0.12355205 | J8: =J6/J7 -> -0.11454633 | ... L8: =L6/L7 -> -0.14823576
B10: Retained Earnings | C10: ='Historical Financials'!C31 -> 30465 | D10: ='Historical Financials'!D31 -> 36924.1 | E10: ='Historical Financials'!E31 -> 42408.4 | F10: ='Historical Financials'!F31 -> 46941.1 | G10: ='Historical Financials'!G31 -> 49262 | H10: ='Historical Financials'!H31 -> 52349.6 | I10: ='Historical Financials'!I31 -> 55182.5 | J10: ='Historical Financials'!J31 -> 74443 | ... L10: ='Historical Financials'!L31 -> 96082.7
B11: Total Assets | C11: ='Historical Financials'!C47 -> 47232.2 | D11: ='Historical Financials'!D47 -> 56450.3 | E11: ='Historical Financials'!E47 -> 64948 | F11: ='Historical Financials'!F47 -> 69791.9 | G11: ='Historical Financials'!G47 -> 68848.3 | H11: ='Historical Financials'!H47 -> 78752.1 | I11: ='Historical Financials'!I47 -> 83264.5 | J11: ='Historical Financials'!J47 -> 111582.8 | ... L11: ='Historical Financials'!L47 -> 145977.6
B12: X2: Retained Earnings / Total Assets | C12: =C10/C11 -> 0.64500489 | D12: =D10/D11 -> 0.65409927 | E12: =E10/E11 -> 0.65295929 | F12: =F10/F11 -> 0.67258665 | G12: =G10/G11 -> 0.71551513 | H12: =H10/H11 -> 0.6647391 | I12: =I10/I11 -> 0.66273742 | J12: =J10/J11 -> 0.66715479 | ... L12: =L10/L11 -> 0.65820167
B14: EBIT | C14: ='Historical Financials'!C13 -> 6202.3 | D14: ='Historical Financials'!D13 -> 7817.4 | E14: ='Historical Financials'!E13 -> 9358.1 | F14: ='Historical Financials'!F13 -> 8035.5 | G14: ='Historical Financials'!G13 -> 3826.6 | H14: ='Historical Financials'!H13 -> 2376.5 | I14: ='Historical Financials'!I13 -> 2963 | J14: ='Historical Financials'!J13 -> 8275.5 | ... L14: ='Historical Financials'!L13 -> 14548.1
B15: Total Assets | C15: ='Historical Financials'!C47 -> 47232.2 | D15: ='Historical Financials'!D47 -> 56450.3 | E15: ='Historical Financials'!E47 -> 64948 | F15: ='Historical Financials'!F47 -> 69791.9 | G15: ='Historical Financials'!G47 -> 68848.3 | H15: ='Historical Financials'!H47 -> 78752.1 | I15: ='Historical Financials'!I47 -> 83264.5 | J15: ='Historical Financials'!J47 -> 111582.8 | ... L15: ='Historical Financials'!L47 -> 145977.6
B16: X3: EBIT / Total Assets | C16: =C14/C15 -> 0.13131508 | D16: =D14/D15 -> 0.13848288 | E16: =E14/E15 -> 0.14408604 | F16: =F14/F15 -> 0.11513514 | G16: =G14/G15 -> 0.055580167 | H16: =H14/H15 -> 0.030176973 | I16: =I14/I15 -> 0.035585394 | J16: =J14/J15 -> 0.074164656 | ... L16: =L14/L15 -> 0.099659811
B18: Market Value of Equity | C18: =('Data Sheet'!B70*'Data Sheet'!B90)/10000000 -> 112262.01 | D18: =('Data Sheet'!C70*'Data Sheet'!C90)/10000000 -> 181722.3 | E18: =('Data Sheet'!D70*'Data Sheet'!D90)/10000000 -> 267676.16 | F18: =('Data Sheet'!E70*'Data Sheet'!E90)/10000000 -> 201564.43 | G18: =('Data Sheet'!F70*'Data Sheet'!F90)/10000000 -> 129540.99 | H18: =('Data Sheet'!G70*'Data Sheet'!G90)/10000000 -> 207202.75 | I18: =('Data Sheet'!H70*'Data Sheet'!H90)/10000000 -> 228411.8 | J18: =('Data Sheet'!I70*'Data Sheet'!I90)/10000000 -> 250489.32 | ... L18: =('Data Sheet'!K70*'Data Sheet'!K90)/10000000 -> 0
B19: Total Liabilities | C19: ='Historical Financials'!C34 -> 42725.5 | D19: ='Historical Financials'!D34 -> 51960.5 | E19: ='Historical Financials'!E34 -> 60248.4 | F19: ='Historical Financials'!F34 -> 63968.7 | G19: ='Historical Financials'!G34 -> 63627.7 | H19: ='Historical Financials'!H34 -> 71376.1 | I19: ='Historical Financials'!I34 -> 74655.5 | J19: ='Historical Financials'!J34 -> 100106 | ... L19: ='Historical Financials'!L34 -> 131971.8
B20: X4: Market Capitalization / Total Liabilities | C20: =C18/C19 -> 2.6275178 | D20: =D18/D19 -> 3.4973163 | E20: =E18/E19 -> 4.4428759 | F20: =F18/F19 -> 3.1509853 | G20: =G18/G19 -> 2.0359213 | H20: =H18/H19 -> 2.9029711 | I20: =I18/I19 -> 3.0595441 | J20: =J18/J19 -> 2.5022408 | ... L20: =L18/L19 -> 0
B22: Sales | C22: ='Historical Financials'!C7 -> 57589 | D22: ='Historical Financials'!D7 -> 68085 | E22: ='Historical Financials'!E7 -> 79809.4 | F22: ='Historical Financials'!F7 -> 86068.5 | G22: ='Historical Financials'!G7 -> 75660 | H22: ='Historical Financials'!H7 -> 70372 | I22: ='Historical Financials'!I7 -> 88329.8 | J22: ='Historical Financials'!J7 -> 118409.9 | ... L22: ='Historical Financials'!L7 -> 152913
B23: Total Assets | C23: ='Historical Financials'!C47 -> 47232.2 | D23: ='Historical Financials'!D47 -> 56450.3 | E23: ='Historical Financials'!E47 -> 64948 | F23: ='Historical Financials'!F47 -> 69791.9 | G23: ='Historical Financials'!G47 -> 68848.3 | H23: ='Historical Financials'!H47 -> 78752.1 | I23: ='Historical Financials'!I47 -> 83264.5 | J23: ='Historical Financials'!J47 -> 111582.8 | ... L23: ='Historical Financials'!L47 -> 145977.6
B24: X5: Sales / Total Assets | C24: =C22/C23 -> 1.2192741 | D24: =D22/D23 -> 1.2061052 | E24: =E22/E23 -> 1.22882 | F24: =F22/F23 -> 1.2332162 | G24: =G22/G23 -> 1.0989378 | H24: =H22/H23 -> 0.89358887 | I24: =I22/I23 -> 1.0608338 | J24: =J22/J23 -> 1.0611842 | ... L24: =L22/L23 -> 1.04751
B26: Altman's Z-Score: Z=1.2X1 +1.4X2 +3.3X3 +0.6X4 +1.0X5
B27: Z Score | C27: =1.2*C8+1.4*C12+3.3*C16+0.6*C20+1*C24 -> 3.944838 | D27: =1.2*D8+1.4*D12+3.3*D16+0.6*D20+1*D24 -> 4.4665217 | E27: =1.2*E8+1.4*E12+3.3*E16+0.6*E20+1*E24 -> 5.0464081 | F27: =1.2*F8+1.4*F12+3.3*F16+0.6*F20+1*F24 -> 4.2580669 | G27: =1.2*G8+1.4*G12+3.3*G16+0.6*G20+1*G24 -> 3.3520713 | H27: =1.2*H8+1.4*H12+3.3*H16+0.6*H20+1*H24 -> 3.4986065 | I27: =1.2*I8+1.4*I12+3.3*I16+0.6*I20+1*I24 -> 3.793562 | J27: =1.2*J8+1.4*J12+3.3*J16+0.6*J20+1*J24 -> 3.6038331 | ... L27: =1.2*L8+1.4*L12+3.3*L16+0.6*L20+1*L24 -> 2.1199868
B28: Financial Stability | C28: =IF(C27<1.81,"Distress Zone",IF(AND(C27>1.81,C27<2.99),"Gray Zone",IF(C27>2.99,"Safe Zone","NA"))) -> Safe Zone | D28: =IF(D27<1.81,"Distress Zone",IF(AND(D27>1.81,D27<2.99),"Gray Zone",IF(D27>2.99,"Safe Zone","NA"))) -> Safe Zone | E28: =IF(E27<1.81,"Distress Zone",IF(AND(E27>1.81,E27<2.99),"Gray Zone",IF(E27>2.99,"Safe Zone","NA"))) -> Safe Zone | F28: =IF(F27<1.81,"Distress Zone",IF(AND(F27>1.81,F27<2.99),"Gray Zone",IF(F27>2.99,"Safe Zone","NA"))) -> Safe Zone | G28: =IF(G27<1.81,"Distress Zone",IF(AND(G27>1.81,G27<2.99),"Gray Zone",IF(G27>2.99,"Safe Zone","NA"))) -> Safe Zone | H28: =IF(H27<1.81,"Distress Zone",IF(AND(H27>1.81,H27<2.99),"Gray Zone",IF(H27>2.99,"Safe Zone","NA"))) -> Safe Zone | I28: =IF(I27<1.81,"Distress Zone",IF(AND(I27>1.81,I27<2.99),"Gray Zone",IF(I27>2.99,"Safe Zone","NA"))) -> Safe Zone | J28: =IF(J27<1.81,"Distress Zone",IF(AND(J27>1.81,J27<2.99),"Gray Zone",IF(J27>2.99,"Safe Zone","NA"))) -> Safe Zone | ... L28: =IF(L27<1.81,"Distress Zone",IF(AND(L27>1.81,L27<2.99),"Gray Zone",IF(L27>2.99,"Safe Zone","NA"))) -> Gray Zone

Sheet Linear Forecasting
B2: In Crores | G2: In Crores | L2: In Crores
B3: ="Sales Forecasting"&" - "&'Historical Financials'!B1 -> Sales Forecasting - MARUTI SUZUKI LTD | G3: ="EBITDA Forecasting"&" - "&'Historical Financials'!B1 -> EBITDA Forecasting - MARUTI SUZUKI LTD | L3: ="EPS Forecasting"&" - "&'Historical Financials'!B1 -> EPS Forecasting - MARUTI SUZUKI LTD
B4: Year Weight | C4: Year | D4: Sales | E4: Sales Growth | G4: Year Weight | H4: Year | I4: EBITDA | J4: EBITDA Growth | L4: Year Weight | M4: Year | N4: EPS | O4: EPS Growth
B5: 1 | C5: 2016 | D5: {=TRANSPOSE('Historical Financials'!C7:L7)} -> 57589 | G5: 1 | H5: 2016 | I5: {=TRANSPOSE('Historical Financials'!C11:L11)} -> 9024.1 | L5: 1 | M5: 2016 | N5: {=TRANSPOSE('Historical Financials'!C22:L22)} -> 85.066225
B6: =B5+1 -> 2 | C6: =C5+1 -> 2017 | D6: 68085 | E6: =(D6-D5)/D5 -> 0.18225703 | G6: =G5+1 -> 2 | H6: =H5+1 -> 2017 | I6: 10421.3 | J6: =(I6-I5)/I5 -> 0.15482984 | L6: =L5+1 -> 2 | M6: =M5+1 -> 2017 | N6: 89.821192 | O6: =(N6-N5)/N5 -> 0.055897236
B7: =B6+1 -> 3 | C7: =C6+1 -> 2018 | D7: 79809.4 | E7: =(D7-D6)/D6 -> 0.17220239 | G7: =G6+1 -> 3 | H7: =H6+1 -> 2018 | I7: 12117.9 | J7: =(I7-I6)/I6 -> 0.16280119 | L7: =L6+1 -> 3 | M7: =M6+1 -> 2018 | N7: 118.26159 | O7: =(N7-N6)/N6 -> 0.31663349
B8: =B7+1 -> 4 | C8: =C7+1 -> 2019 | D8: 86068.5 | E8: =(D8-D7)/D7 -> 0.078425599 | G8: =G7+1 -> 4 | H8: =H7+1 -> 2019 | I8: 11056.3 | J8: =(I8-I7)/I7 -> -0.087605938 | L8: =L7+1 -> 4 | M8: =M7+1 -> 2019 | N8: 76.89404 | O8: =(N8-N7)/N7 -> -0.349797
B9: =B8+1 -> 5 | C9: =C8+1 -> 2020 | D9: 75660 | E9: =(D9-D8)/D8 -> -0.12093275 | G9: =G8+1 -> 5 | H9: =H8+1 -> 2020 | I9: 7355 | J9: =(I9-I8)/I8 -> -0.33476841 | L9: =L8+1 -> 5 | M9: =M8+1 -> 2020 | N9: -37.854305 | O9: =(N9-N8)/N8 -> -1.4922918
B10: =B9+1 -> 6 | C10: =C9+1 -> 2021 | D10: 70372 | E10: =(D10-D9)/D9 -> -0.06989162 | G10: =G9+1 -> 6 | H10: =H9+1 -> 2021 | I10: 5410.6 | J10: =(I10-I9)/I9 -> -0.26436438 | L10: =L9+1 -> 6 | M10: =M9+1 -> 2021 | N10: -56.407285 | O10: =(N10-N9)/N9 -> 0.49011547
B11: =B10+1 -> 7 | C11: =C10+1 -> 2022 | D11: 88329.8 | E11: =(D11-D10)/D10 -> 0.25518388 | G11: =G10+1 -> 7 | H11: =H10+1 -> 2022 | I11: 5752 | J11: =(I11-I10)/I10 -> 0.063098362 | L11: =L10+1 -> 7 | M11: =M10+1 -> 2022 | N11: 5.2284768 | O11: =(N11-N10)/N10 -> -1.0926915
B12: =B11+1 -> 8 | C12: =C11+1 -> 2023 | D12: 118409.9 | E12: =(D12-D11)/D11 -> 0.34054306 | G12: =G11+1 -> 8 | H12: =H11+1 -> 2023 | I12: 13121.5 | J12: =(I12-I11)/I11 -> 1.2812065 | L12: =L11+1 -> 8 | M12: =M11+1 -> 2023 | N12: 109.21438 | O12: =(N12-N11)/N11 -> 19.888373
B13: =B12+1 -> 9 | C13: =C12+1 -> 2024 | D13: 141858.2 | E13: =(D13-D12)/D12 -> 0.19802652 | G13: =G12+1 -> 9 | H13: =H12+1 -> 2024 | I13: 18626.3 | J13: =(I13-I12)/I12 -> 0.41952521 | L13: =L12+1 -> 9 | M13: =M12+1 -> 2024 | N13: 158.81043 | O13: =(N13-N12)/N12 -> 0.45411655
B14: =B13+1 -> 10 | C14: =C13+1 -> 2025 | D14: 152913 | E14: =(D14-D13)/D13 -> 0.077928523 | G14: =G13+1 -> 10 | H14: =H13+1 -> 2025 | I14: 20156.3 | J14: =(I14-I13)/I13 -> 0.082141918 | L14: =L13+1 -> 10 | M14: =M13+1 -> 2025 | N14: 126.20865 | O14: =(N14-N13)/N13 -> -0.2052874
B15: =B14+1 -> 11 | C15: =C14+1 -> 2026 | D15: =_xlfn.FORECAST.LINEAR(B15,$D$4:$D$14,$B$4:$B$14) -> 146203.71 | E15: =(D15-D14)/D14 -> -0.04387654 | G15: =G14+1 -> 11 | H15: =H14+1 -> 2026 | I15: =_xlfn.FORECAST.LINEAR(G15,$I$4:$I$14,$G$4:$G$14) -> 16130.313 | J15: =(I15-I14)/I14 -> -0.19973838 | L15: =L14+1 -> 11 | M15: =M14+1 -> 2026 | N15: =_xlfn.FORECAST.LINEAR(L15,$N$4:$N$14,$L$4:$L$14) -> 86.671699 | O15: =(N15-N14)/N14 -> -0.31326658
B16: =B15+1 -> 12 | C16: =C15+1 -> 2027 | D16: =_xlfn.FORECAST.LINEAR(B16,$D$4:$D$14,$B$4:$B$14) -> 155711.75 | E16: =(D16-D15)/D15 -> 0.065032833 | G16: =G15+1 -> 12 | H16: =H15+1 -> 2027 | I16: =_xlfn.FORECAST.LINEAR(G16,$I$4:$I$14,$G$4:$G$14) -> 17007.801 | J16: =(I16-I15)/I15 -> 0.054399928 | L16: =L15+1 -> 12 | M16: =M15+1 -> 2027 | N16: =_xlfn.FORECAST.LINEAR(L16,$N$4:$N$14,$L$4:$L$14) -> 90.153037 | O16: =(N16-N15)/N15 -> 0.040166953
B17: =B16+1 -> 13 | C17: =C16+1 -> 2028 | D17: =_xlfn.FORECAST.LINEAR(B17,$D$4:$D$14,$B$4:$B$14) -> 165219.79 | E17: =(D17-D16)/D16 -> 0.06106181 | G17: =G16+1 -> 13 | H17: =H16+1 -> 2028 | I17: =_xlfn.FORECAST.LINEAR(G17,$I$4:$I$14,$G$4:$G$14) -> 17885.289 | J17: =(I17-I16)/I16 -> 0.051593258 | L17: =L16+1 -> 13 | M17: =M16+1 -> 2028 | N17: =_xlfn.FORECAST.LINEAR(L17,$N$4:$N$14,$L$4:$L$14) -> 93.634375 | O17: =(N17-N16)/N16 -> 0.038615872
B18: =B17+1 -> 14 | C18: =C17+1 -> 2029 | D18: =_xlfn.FORECAST.LINEAR(B18,$D$4:$D$14,$B$4:$B$14) -> 174727.83 | E18: =(D18-D17)/D17 -> 0.057547835 | G18: =G17+1 -> 14 | H18: =H17+1 -> 2029 | I18: =_xlfn.FORECAST.LINEAR(G18,$I$4:$I$14,$G$4:$G$14) -> 18762.777 | J18: =(I18-I17)/I17 -> 0.04906199 | L18: =L17+1 -> 14 | M18: =M17+1 -> 2029 | N18: =_xlfn.FORECAST.LINEAR(L18,$N$4:$N$14,$L$4:$L$14) -> 97.115713 | O18: =(N18-N17)/N17 -> 0.037180128
B19: =B18+1 -> 15 | C19: =C18+1 -> 2030 | D19: =_xlfn.FORECAST.LINEAR(B19,$D$4:$D$14,$B$4:$B$14) -> 184235.87 | E19: =(D19-D18)/D18 -> 0.054416295 | G19: =G18+1 -> 15 | H19: =H18+1 -> 2030 | I19: =_xlfn.FORECAST.LINEAR(G19,$I$4:$I$14,$G$4:$G$14) -> 19640.265 | J19: =(I19-I18)/I18 -> 0.046767484 | L19: =L18+1 -> 15 | M19: =M18+1 -> 2030 | N19: =_xlfn.FORECAST.LINEAR(L19,$N$4:$N$14,$L$4:$L$14) -> 100.59705 | O19: =(N19-N18)/N18 -> 0.035847321
D39: Actual | E39: Forecasting | I39: Actual | J39: Forecasting | N39: Actual | O39: Forecasting
C40: 2016 | D40: 57589 | H40: 2016 | I40: 9024.1 | M40: 2016 | N40: 85.066225
C41: =C40+1 -> 2017 | D41: 68085 | H41: =H40+1 -> 2017 | I41: 10421.3 | M41: =M40+1 -> 2017 | N41: 89.821192
C42: =C41+1 -> 2018 | D42: 79809.4 | H42: =H41+1 -> 2018 | I42: 12117.9 | M42: =M41+1 -> 2018 | N42: 118.26159
C43: =C42+1 -> 2019 | D43: 86068.5 | H43: =H42+1 -> 2019 | I43: 11056.3 | M43: =M42+1 -> 2019 | N43: 76.89404
C44: =C43+1 -> 2020 | D44: 75660 | H44: =H43+1 -> 2020 | I44: 7355 | M44: =M43+1 -> 2020 | N44: -37.854305
C45: =C44+1 -> 2021 | D45: 70372 | H45: =H44+1 -> 2021 | I45: 5410.6 | M45: =M44+1 -> 2021 | N45: -56.407285
C46: =C45+1 -> 2022 | D46: 88329.8 | H46: =H45+1 -> 2022 | I46: 5752 | M46: =M45+1 -> 2022 | N46: 5.2284768
C47: =C46+1 -> 2023 | D47: 118409.9 | H47: =H46+1 -> 2023 | I47: 13121.5 | M47: =M46+1 -> 2023 | N47: 109.21438
C48: =C47+1 -> 2024 | D48: 141858.2 | H48: =H47+1 -> 2024 | I48: 18626.3 | M48: =M47+1 -> 2024 | N48: 158.81043
C49: =C48+1 -> 2025 | D49: 152913 | E49: 152913 | H49: =H48+1 -> 2025 | I49: 20156.3 | J49: 20156.3 | M49: =M48+1 -> 2025 | N49: 126.20865 | O49: 126.20865
C50: =C49+1 -> 2026 | E50: 146203.71 | H50: =H49+1 -> 2026 | J50: 16130.313 | M50: =M49+1 -> 2026 | O50: 86.671699
C51: =C50+1 -> 2027 | E51: 155711.75 | H51: =H50+1 -> 2027 | J51: 17007.801 | M51: =M50+1 -> 2027 | O51: 90.153037
C52: =C51+1 -> 2028 | E52: 165219.79 | H52: =H51+1 -> 2028 | J52: 17885.289 | M52: =M51+1 -> 2028 | O52: 93.634375
C53: =C52+1 -> 2029 | E53: 174727.83 | H53: =H52+1 -> 2029 | J53: 18762.777 | M53: =M52+1 -> 2029 | O53: 97.115713
C54: =C53+1 -> 2030 | E54: 184235.87 | H54: =H53+1 -> 2030 | J54: 19640.265 | M54: =M53+1 -> 2030 | O54: 100.59705

Sheet Scenario Analysis Forecasting
B2: Scenarios: | F2: Rates
B3: Case:1 | C3: Upside Case | F3: 0.04
B4: Case:2 | C4: Base Case | F4: 0.05
B5: Case:3 | C5: Downside Case
B7: Selected Case 2 | C7: 2
B9: In Crores
B10: Actual | M10: Forecast
B11: Years | C11: 2016 | D11: =C11+1 -> 2017 | E11: =D11+1 -> 2018 | F11: =E11+1 -> 2019 | G11: =F11+1 -> 2020 | H11: =G11+1 -> 2021 | I11: =H11+1 -> 2022 | J11: =I11+1 -> 2023 | K11: =J11+1 -> 2024 | L11: =K11+1 -> 2025 | M11: 2026 | N11: =M11+1 -> 2027 | O11: =N11+1 -> 2028
B13: Sales | C13: ='Data Sheet'!B17 -> 57589 | D13: ='Data Sheet'!C17 -> 68085 | E13: ='Data Sheet'!D17 -> 79809.4 | F13: ='Data Sheet'!E17 -> 86068.5 | G13: ='Data Sheet'!F17 -> 75660 | H13: ='Data Sheet'!G17 -> 70372 | I13: ='Data Sheet'!H17 -> 88329.8 | J13: ='Data Sheet'!I17 -> 118409.9 | ... L13: ='Data Sheet'!K17 -> 152913 | M13: =L13+(L13*M14) -> 171835.86 | N13: =M13+(M13*N14) -> 193100.41 | O13: =N13+(N13*O14) -> 216996.42
B14: y-o-y growth rate % | D14: =(D13-C13)/C13 -> 0.18225703 | E14: =(E13-D13)/D13 -> 0.17220239 | F14: =(F13-E13)/E13 -> 0.078425599 | G14: =(G13-F13)/F13 -> -0.12093275 | H14: =(H13-G13)/G13 -> -0.06989162 | I14: =(I13-H13)/H13 -> 0.25518388 | J14: =(J13-I13)/I13 -> 0.34054306 | K14: =(K13-J13)/J13 -> 0.19802652 | L14: =(L13-K13)/K13 -> 0.077928523 | M14: =CHOOSE($C$7,M15,M16,M17) -> 0.12374918 | N14: =CHOOSE($C$7,N15,N16,N17) -> 0.12374918 | O14: =CHOOSE($C$7,O15,O16,O17) -> 0.12374918
B15: Case 1: | M15: =M16+$F$4 -> 0.17374918 | N15: =N16+$F$4 -> 0.17374918 | O15: =O16+$F$4 -> 0.17374918
B16: Case 2: | M16: =AVERAGE(D14:L14) -> 0.12374918 | N16: =M16 -> 0.12374918 | O16: =N16 -> 0.12374918
B17: Case 3: | M17: =M16-$F$3 -> 0.083749181 | N17: =N16-$F$3 -> 0.083749181 | O17: =O16-$F$3 -> 0.083749181
B19: COGS | C19: =SUM('Data Sheet'!B18,'Data Sheet'!B20,'Data Sheet'!B21,'Data Sheet'!B22)-1*'Data Sheet'!B19 -> 41828.2 | D19: =SUM('Data Sheet'!C18,'Data Sheet'!C20,'Data Sheet'!C21,'Data Sheet'!C22)-1*'Data Sheet'!C19 -> 50004 | E19: =SUM('Data Sheet'!D18,'Data Sheet'!D20,'Data Sheet'!D21,'Data Sheet'!D22)-1*'Data Sheet'!D19 -> 58985 | F19: =SUM('Data Sheet'!E18,'Data Sheet'!E20,'Data Sheet'!E21,'Data Sheet'!E22)-1*'Data Sheet'!E19 -> 64182.2 | G19: =SUM('Data Sheet'!F18,'Data Sheet'!F20,'Data Sheet'!F21,'Data Sheet'!F22)-1*'Data Sheet'!F19 -> 57657.1 | H19: =SUM('Data Sheet'!G18,'Data Sheet'!G20,'Data Sheet'!G21,'Data Sheet'!G22)-1*'Data Sheet'!G19 -> 55415.6 | I19: =SUM('Data Sheet'!H18,'Data Sheet'!H20,'Data Sheet'!H21,'Data Sheet'!H22)-1*'Data Sheet'!H19 -> 71578.8 | J19: =SUM('Data Sheet'!I18,'Data Sheet'!I20,'Data Sheet'!I21,'Data Sheet'!I22)-1*'Data Sheet'!I19 -> 92730.6 | ... L19: =SUM('Data Sheet'!K18,'Data Sheet'!K20,'Data Sheet'!K21,'Data Sheet'!K22)-1*'Data Sheet'!K19 -> 114516.8 | M19: =L19+(L19*M20) -> 128956.5 | N19: =M19+(M19*N20) -> 145216.93 | O19: =N19+(N19*O20) -> 163527.68
B20: y-o-y growth rate % | D20: =(D19-C19)/C19 -> 0.19546144 | E20: =(E19-D19)/D19 -> 0.17960563 | F20: =(F19-E19)/E19 -> 0.088110537 | G20: =(G19-F19)/F19 -> -0.10166526 | H20: =(H19-G19)/G19 -> -0.038876392 | I20: =(I19-H19)/H19 -> 0.29167238 | J20: =(J19-I19)/I19 -> 0.2955037 | K20: =(K19-J19)/J19 -> 0.16482801 | L20: =(L19-K19)/K19 -> 0.060191529 | M20: =CHOOSE($C$7,M21,M22,M23) -> 0.1260924 | N20: =CHOOSE($C$7,N21,N22,N23) -> 0.1260924 | O20: =CHOOSE($C$7,O21,O22,O23) -> 0.1260924
B21: Case 1: | M21: =M22-$F$4 -> 0.076092396 | N21: =N22-$F$4 -> 0.076092396 | O21: =O22-$F$4 -> 0.076092396
B22: Case 2: | M22: =AVERAGE(D20:L20) -> 0.1260924 | N22: =M22 -> 0.1260924 | O22: =N22 -> 0.1260924
B23: Case 3: | M23: =M22+$F$3 -> 0.1660924 | N23: =N22+$F$3 -> 0.1660924 | O23: =O22+$F$3 -> 0.1660924
B25: Gross Profits | C25: =C13-C19 -> 15760.8 | D25: =D13-D19 -> 18081 | E25: =E13-E19 -> 20824.4 | F25: =F13-F19 -> 21886.3 | G25: =G13-G19 -> 18002.9 | H25: =H13-H19 -> 14956.4 | I25: =I13-I19 -> 16751 | J25: =J13-J19 -> 25679.3 | ... O25: =O13-O19 -> 53468.74
B26: Selling & General Expenses | C26: =SUM('Data Sheet'!B23:B24) -> 6736.7 | D26: =SUM('Data Sheet'!C23:C24) -> 7659.7 | E26: =SUM('Data Sheet'!D23:D24) -> 8706.5 | F26: =SUM('Data Sheet'!E23:E24) -> 10830 | G26: =SUM('Data Sheet'!F23:F24) -> 10647.9 | H26: =SUM('Data Sheet'!G23:G24) -> 9545.8 | I26: =SUM('Data Sheet'!H23:H24) -> 10999 | J26: =SUM('Data Sheet'!I23:I24) -> 12557.8 | ... L26: =SUM('Data Sheet'!K23:K24) -> 18239.9 | M26: =L26+(L26*M27) -> 20472.504 | N26: =M26+(M26*N27) -> 22978.383 | O26: =N26+(N26*O27) -> 25790.988
B27: y-o-y growth rate % | D27: =(D26-C26)/C26 -> 0.1370107 | E27: =(E26-D26)/D26 -> 0.13666332 | F27: =(F26-E26)/E26 -> 0.24389824 | G27: =(G26-F26)/F26 -> -0.016814404 | H27: =(H26-G26)/G26 -> -0.10350398 | I27: =(I26-H26)/H26 -> 0.15223449 | J27: =(J26-I26)/I26 -> 0.14172197 | K27: =(K26-J26)/J26 -> 0.21173295 | L27: =(L26-K26)/K26 -> 0.19867645 | M27: =CHOOSE($C$7,M28,M29,M30) -> 0.12240219 | N27: =CHOOSE($C$7,N28,N29,N30) -> 0.12240219 | O27: =CHOOSE($C$7,O28,O29,O30) -> 0.12240219
B28: Case 1: | M28: =M29-$F$4 -> 0.072402193 | N28: =N29-$F$4 -> 0.072402193 | O28: =O29-$F$4 -> 0.072402193
B29: Case 2: | M29: =AVERAGE(D27:L27) -> 0.12240219 | N29: =M29 -> 0.12240219 | O29: =N29 -> 0.12240219
B30: Case 3: | M30: =M29+$F$3 -> 0.16240219 | N30: =N29+$F$3 -> 0.16240219 | O30: =O29+$F$3 -> 0.16240219
B32: EBITDA | C32: =C25-C26 -> 9024.1 | D32: =D25-D26 -> 10421.3 | E32: =E25-E26 -> 12117.9 | F32: =F25-F26 -> 11056.3 | G32: =G25-G26 -> 7355 | H32: =H25-H26 -> 5410.6 | I32: =I25-I26 -> 5752 | J32: =J25-J26 -> 13121.5 | ... O32: =O25-O26 -> 27677.752
B33: Depreciation | C33: ='Data Sheet'!B26 -> 2821.8 | D33: ='Data Sheet'!C26 -> 2603.9 | E33: ='Data Sheet'!D26 -> 2759.8 | F33: ='Data Sheet'!E26 -> 3020.8 | G33: ='Data Sheet'!F26 -> 3528.4 | H33: ='Data Sheet'!G26 -> 3034.1 | I33: ='Data Sheet'!H26 -> 2789 | J33: ='Data Sheet'!I26 -> 4846 | ... L33: ='Data Sheet'!K26 -> 5608.2 | M33: =L33+(L33*M34) -> 6177.457 | N33: =M33+(M33*N34) -> 6804.496 | O33: =N33+(N33*O34) -> 7495.1823
B34: y-o-y growth rate % | D34: =(D33-C33)/C33 -> -0.077220214 | E34: =(E33-D33)/D33 -> 0.059871731 | F34: =(F33-E33)/E33 -> 0.09457207 | G34: =(G33-F33)/F33 -> 0.16803496 | H34: =(H33-G33)/G33 -> -0.14009183 | I34: =(I33-H33)/H33 -> -0.08078178 | J34: =(J33-I33)/I33 -> 0.73754034 | K34: =(K33-J33)/J33 -> 0.084564589 | L34: =(L33-K33)/K33 -> 0.067049736 | M34: =CHOOSE($C$7,M35,M36,M37) -> 0.1015044 | N34: =CHOOSE($C$7,N35,N36,N37) -> 0.1015044 | O34: =CHOOSE($C$7,O35,O36,O37) -> 0.1015044
B35: Case 1: | M35: =M36+$F$4 -> 0.1515044 | N35: =N36+$F$4 -> 0.1515044 | O35: =O36+$F$4 -> 0.1515044
B36: Case 2: | M36: =AVERAGE(D34:L34) -> 0.1015044 | N36: =M36 -> 0.1015044 | O36: =N36 -> 0.1015044
B37: Case 3: | M37: =M36-$F$3 -> 0.0615044 | N37: =N36-$F$3 -> 0.0615044 | O37: =O36-$F$3 -> 0.0615044
B39: EBIT | C39: =C32-C33 -> 6202.3 | D39: =D32-D33 -> 7817.4 | E39: =E32-E33 -> 9358.1 | F39: =F32-F33 -> 8035.5 | G39: =G32-G33 -> 3826.6 | H39: =H32-H33 -> 2376.5 | I39: =I32-I33 -> 2963 | J39: =J32-J33 -> 8275.5 | ... O39: =O32-O33 -> 20182.57
B40: Interest | C40: ='Data Sheet'!B27 -> 81.7 | D40: ='Data Sheet'!C27 -> 89.4 | E40: ='Data Sheet'!D27 -> 345.8 | F40: ='Data Sheet'!E27 -> 75.9 | G40: ='Data Sheet'!F27 -> 134.2 | H40: ='Data Sheet'!G27 -> 101.8 | I40: ='Data Sheet'!H27 -> 126.6 | J40: ='Data Sheet'!I27 -> 252.3 | ... L40: ='Data Sheet'!K27 -> 194.2 | M40: =L40+(L40*M41) -> 274.3696 | N40: =M40+(M40*N41) -> 387.6348 | O40: =N40+(N40*O41) -> 547.65811
B41: y-o-y growth rate % | D41: =(D40-C40)/C40 -> 0.094247246 | E41: =(E40-D40)/D40 -> 2.8680089 | F41: =(F40-E40)/E40 -> -0.78050896 | G41: =(G40-F40)/F40 -> 0.76811594 | H41: =(H40-G40)/G40 -> -0.2414307 | I41: =(I40-H40)/H40 -> 0.24361493 | J41: =(J40-I40)/I40 -> 0.992891 | K41: =(K40-J40)/J40 -> -0.23265953 | L41: =(L40-K40)/K40 -> 0.0030991736 | M41: =CHOOSE($C$7,M42,M43,M44) -> 0.41281978 | N41: =CHOOSE($C$7,N42,N43,N44) -> 0.41281978 | O41: =CHOOSE($C$7,O42,O43,O44) -> 0.41281978
B42: Case 1: | M42: =M43-$F$4 -> 0.36281978 | N42: =N43-$F$4 -> 0.36281978 | O42: =O43-$F$4 -> 0.36281978
B43: Case 2: | M43: =AVERAGE(D41:L41) -> 0.41281978 | N43: =M43 -> 0.41281978 | O43: =N43 -> 0.41281978
B44: Case 3: | M44: =M43+$F$3 -> 0.45281978 | N44: =N43+$F$3 -> 0.45281978 | O44: =O43+$F$3 -> 0.45281978
B46: Other Income | C46: ='Data Sheet'!B25 -> 1464.1 | D46: ='Data Sheet'!C25 -> 2399.2 | E46: ='Data Sheet'!D25 -> 2154.6 | F46: ='Data Sheet'!E25 -> 2664.2 | G46: ='Data Sheet'!F25 -> 3410.4 | H46: ='Data Sheet'!G25 -> 3046.3 | I46: ='Data Sheet'!H25 -> 1860.8 | J46: ='Data Sheet'!I25 -> 2415 | ... L46: ='Data Sheet'!K25 -> 5266.1 | M46: =L46+(L46*M47) -> 6350.8383 | N46: =M46+(M46*N47) -> 7659.0165 | O46: =N46+(N46*O47) -> 9236.6601
B47: y-o-y growth rate % | D47: =(D46-C46)/C46 -> 0.63868588 | E47: =(E46-D46)/D46 -> -0.10195065 | F47: =(F46-E46)/E46 -> 0.23651722 | G47: =(G46-F46)/F46 -> 0.28008408 | H47: =(H46-G46)/G46 -> -0.10676167 | I47: =(I46-H46)/H46 -> -0.38916062 | J47: =(J46-I46)/I46 -> 0.29782889 | K47: =(K46-J46)/J46 -> 0.75884058 | L47: =(L46-K46)/K46 -> 0.23978247 | M47: =CHOOSE($C$7,M48,M49,M50) -> 0.20598513 | N47: =CHOOSE($C$7,N48,N49,N50) -> 0.20598513 | O47: =CHOOSE($C$7,O48,O49,O50) -> 0.20598513
B48: Case 1: | M48: =M49+$F$4 -> 0.25598513 | N48: =N49+$F$4 -> 0.25598513 | O48: =O49+$F$4 -> 0.25598513
B49: Case 2: | M49: =AVERAGE(D47:L47) -> 0.20598513 | N49: =M49 -> 0.20598513 | O49: =N49 -> 0.20598513
B50: Case 3: | M50: =M49-$F$3 -> 0.16598513 | N50: =N49-$F$3 -> 0.16598513 | O50: =O49-$F$3 -> 0.16598513
B52: EBT | C52: =C39-C40+C46 -> 7584.7 | D52: =D39-D40+D46 -> 10127.2 | E52: =E39-E40+E46 -> 11166.9 | F52: =F39-F40+F46 -> 10623.8 | G52: =G39-G40+G46 -> 7102.8 | H52: =H39-H40+H46 -> 5321 | I52: =I39-I40+I46 -> 4697.2 | J52: =J39-J40+J46 -> 10438.2 | ... O52: =O39-O40+O46 -> 28871.572
B53: Tax | C53: ='Data Sheet'!B29 -> 2087.5 | D53: ='Data Sheet'!C29 -> 2616.2 | E53: ='Data Sheet'!D29 -> 3286.2 | F53: ='Data Sheet'!E29 -> 2973.2 | G53: ='Data Sheet'!F29 -> 1425.2 | H53: ='Data Sheet'!G29 -> 931.9 | I53: ='Data Sheet'!H29 -> 817.7 | J53: ='Data Sheet'!I29 -> 2174.5 | ... L53: ='Data Sheet'!K29 -> 5119.8 | M53: =M52*M55 -> 6363.3047 | N53: =N52*N55 -> 7237.9883 | O53: =O52*O55 -> 8236.3351
B54: Tax % of EBT | C54: =C53/C52 -> 0.27522512 | D54: =D53/D52 -> 0.25833399 | E54: =E53/E52 -> 0.29428042 | F54: =F53/F52 -> 0.2798622 | G54: =G53/G52 -> 0.20065326 | H54: =H53/H52 -> 0.17513625 | I54: =I53/I52 -> 0.17408243 | J54: =J53/J52 -> 0.20832136 | ... L54: =L53/L52 -> 0.26094801 | M54: =CHOOSE($C$7,M55,M56,M57) -> 0.23527491 | N54: =CHOOSE($C$7,N55,N56,N57) -> 0.23527491 | O54: =CHOOSE($C$7,O55,O56,O57) -> 0.23527491
B55: Case 1: | M55: =M56+$F$4 -> 0.28527491 | N55: =N56+$F$4 -> 0.28527491 | O55: =O56+$F$4 -> 0.28527491
B56: Case 2: | M56: =AVERAGE(C54:L54) -> 0.23527491 | N56: =M56 -> 0.23527491 | O56: =N56 -> 0.23527491
B57: Case 3: | M57: =M56-$F$3 -> 0.19527491 | N57: =N56-$F$3 -> 0.19527491 | O57: =O56-$F$3 -> 0.19527491
B59: Net Profit | C59: =C52-C53 -> 5497.2 | D59: =D52-D53 -> 7511 | E59: =E52-E53 -> 7880.7 | F59: =F52-F53 -> 7650.6 | G59: =G52-G53 -> 5677.6 | H59: =H52-H53 -> 4389.1 | I59: =I52-I53 -> 3879.5 | J59: =J52-J53 -> 8263.7 | ... O59: =O52-O53 -> 20635.237
